Workbook

Sheet INSTRUCCIONES
A1: DASHBOARD FINANCIERO — EMPRESA PESQUERA
A2: Guía de uso y estructura del archivo
A6: 📋 ESTRUCTURA DEL ARCHIVO
A7: Hoja | B7: Descripción
A8: INSTRUCCIONES | B8: Esta hoja — guía de uso
A9: CARGA_DIARIA | B9: Acá cargás los datos todos los días (una fila por día)
A10: ACTIVO_CORRIENTE | B10: Desglose diario de activos: bancos, cheques, divisas, créditos, FCI
A11: GASTOS_DIARIOS | B11: Detalle de egresos por sector (13 categorías)
A12: PASIVO_CORRIENTE | B12: Compromisos y deudas a corto plazo
A13: VENCIMIENTOS | B13: Cheques a cobrar y pagar en los próximos 30 días
A14: AJUSTES | B14: Stock a precio de venta, posición fiscal, otras deudas
A15: POSICION_NETA | B15: Hoja de cálculo automática — no modificar
A17: 🎨 CONVENCIÓN DE COLORES
A18: Color | B18: Significado
A19: Texto AZUL | B19: Dato a ingresar manualmente (input)
A20: Texto NEGRO | B20: Fórmula calculada automáticamente — no modificar
A21: Texto VERDE | B21: Vínculo a otra hoja del mismo archivo
A22: Fondo AMARILLO | B22: Celda importante que requiere atención o actualización
A24: 📌 INSTRUCCIONES DE CARGA DIARIA
A25: 1. | B25: Abrir la hoja CARGA_DIARIA
A26: 2. | B26: Ir a la última fila con datos e insertar una nueva fila debajo
A27: 3. | B27: Ingresar la fecha del día en la columna A (formato DD/MM/AAAA)
A28: 4. | B28: Ingresar el tipo de cambio BNA del día en la columna B
A29: 5. | B29: Completar el resto de columnas con los valores en PESOS del día
A30: 6. | B30: Los valores en USD se calculan automáticamente dividiendo por el TC
A31: 7. | B31: La hoja POSICION_NETA se actualiza automáticamente
A33: ⚠️ IMPORTANTE
A34: • | B34: No eliminar ni mover filas de encabezado
A35: • | B35: No modificar las hojas de fórmulas (POSICION_NETA)
A36: • | B36: Siempre cargar valores en PESOS — el dashboard convierte a USD
A37: • | B37: Los cheques en cartera cargar en hoja VENCIMIENTOS con fecha de acreditación
A38: • | B38: Guardar el archivo con Ctrl+S después de cada carga

Sheet POSICION_NETA
A1: POSICIÓN FINANCIERA NETA DIARIA | Valores en USD (conversión automática)
A2: ⚠ Hoja de cálculo automática — No modificar. Los datos vienen de CARGA_DIARIA.
A3: Fecha | B3: TC BNA | C3: Activo Corriente (USD) | D3: Gastos del Día (USD) | E3: Pasivo Corriente (USD) | F3: Ajustes + (incluido en Activo) | G3: Ajustes - (incluido en Activo) | H3: POSICIÓN NETA (USD)
A4: =CARGA_DIARIA!A4 -> 46148 | B4: =CARGA_DIARIA!B4 -> 1394 | C4: =IF(CARGA_DIARIA!B4=0,0,(CARGA_DIARIA!C4+CARGA_DIARIA!D4+CARGA_DIARIA!E4+CARGA_DIARIA!F4+CARGA_DIARIA!G4+CARGA_DIARIA!H4+CARGA_DIARIA!I4+CARGA_DIARIA!AG4+CARGA_DIARIA!AH4+CARGA_DIARIA!AI4+CARGA_DIARIA!AJ4)/CARGA_DIARIA!B4+CARGA_DIARIA!AF4) -> 26967200 | D4: =IF(CARGA_DIARIA!B4=0,0,(CARGA_DIARIA!J4+CARGA_DIARIA!K4+CARGA_DIARIA!L4+CARGA_DIARIA!M4+CARGA_DIARIA!N4+CARGA_DIARIA!O4+CARGA_DIARIA!P4+CARGA_DIARIA!Q4+CARGA_DIARIA!R4+CARGA_DIARIA!S4+CARGA_DIARIA!T4+CARGA_DIARIA!U4+CARGA_DIARIA!V4+CARGA_DIARIA!W4)/CARGA_DIARIA!B4) -> 405159.25 | E4: =IF(CARGA_DIARIA!B4=0,0,(CARGA_DIARIA!X4+CARGA_DIARIA!Y4+CARGA_DIARIA!Z4+CARGA_DIARIA!AA4)/CARGA_DIARIA!B4+CARGA_DIARIA!AB4+CARGA_DIARIA!AC4+CARGA_DIARIA!AD4+CARGA_DIARIA!AE4) -> 18836188 | H4: =C4-D4-E4 -> 7725852.8
A5: =CARGA_DIARIA!A5 -> 0 | B5: =CARGA_DIARIA!B5 -> 0 | C5: =IF(CARGA_DIARIA!B5=0,0,(CARGA_DIARIA!C5+CARGA_DIARIA!D5+CARGA_DIARIA!E5+CARGA_DIARIA!F5+CARGA_DIARIA!G5+CARGA_DIARIA!H5+CARGA_DIARIA!I5+CARGA_DIARIA!AG5+CARGA_DIARIA!AH5+CARGA_DIARIA!AI5+CARGA_DIARIA!AJ5)/CARGA_DIARIA!B5+CARGA_DIARIA!AF5) -> 0 | D5: =IF(CARGA_DIARIA!B5=0,0,(CARGA_DIARIA!J5+CARGA_DIARIA!K5+CARGA_DIARIA!L5+CARGA_DIARIA!M5+CARGA_DIARIA!N5+CARGA_DIARIA!O5+CARGA_DIARIA!P5+CARGA_DIARIA!Q5+CARGA_DIARIA!R5+CARGA_DIARIA!S5+CARGA_DIARIA!T5+CARGA_DIARIA!U5+CARGA_DIARIA!V5+CARGA_DIARIA!W5)/CARGA_DIARIA!B5) -> 0 | E5: =IF(CARGA_DIARIA!B5=0,0,(CARGA_DIARIA!X5+CARGA_DIARIA!Y5+CARGA_DIARIA!Z5+CARGA_DIARIA!AA5)/CARGA_DIARIA!B5+CARGA_DIARIA!AB5+CARGA_DIARIA!AC5+CARGA_DIARIA!AD5+CARGA_DIARIA!AE5) -> 0 | H5: =C5-D5-E5 -> 0
A6: =CARGA_DIARIA!A6 -> 0 | B6: =CARGA_DIARIA!B6 -> 0 | C6: =IF(CARGA_DIARIA!B6=0,0,(CARGA_DIARIA!C6+CARGA_DIARIA!D6+CARGA_DIARIA!E6+CARGA_DIARIA!F6+CARGA_DIARIA!G6+CARGA_DIARIA!H6+CARGA_DIARIA!I6+CARGA_DIARIA!AG6+CARGA_DIARIA!AH6+CARGA_DIARIA!AI6+CARGA_DIARIA!AJ6)/CARGA_DIARIA!B6+CARGA_DIARIA!AF6) -> 0 | D6: =IF(CARGA_DIARIA!B6=0,0,(CARGA_DIARIA!J6+CARGA_DIARIA!K6+CARGA_DIARIA!L6+CARGA_DIARIA!M6+CARGA_DIARIA!N6+CARGA_DIARIA!O6+CARGA_DIARIA!P6+CARGA_DIARIA!Q6+CARGA_DIARIA!R6+CARGA_DIARIA!S6+CARGA_DIARIA!T6+CARGA_DIARIA!U6+CARGA_DIARIA!V6+CARGA_DIARIA!W6)/CARGA_DIARIA!B6) -> 0 | E6: =IF(CARGA_DIARIA!B6=0,0,(CARGA_DIARIA!X6+CARGA_DIARIA!Y6+CARGA_DIARIA!Z6+CARGA_DIARIA!AA6)/CARGA_DIARIA!B6+CARGA_DIARIA!AB6+CARGA_DIARIA!AC6+CARGA_DIARIA!AD6+CARGA_DIARIA!AE6) -> 0 | H6: =C6-D6-E6 -> 0
A7: =CARGA_DIARIA!A7 -> 0 | B7: =CARGA_DIARIA!B7 -> 0 | C7: =IF(CARGA_DIARIA!B7=0,0,(CARGA_DIARIA!C7+CARGA_DIARIA!D7+CARGA_DIARIA!E7+CARGA_DIARIA!F7+CARGA_DIARIA!G7+CARGA_DIARIA!H7+CARGA_DIARIA!I7+CARGA_DIARIA!AG7+CARGA_DIARIA!AH7+CARGA_DIARIA!AI7+CARGA_DIARIA!AJ7)/CARGA_DIARIA!B7+CARGA_DIARIA!AF7) -> 0 | D7: =IF(CARGA_DIARIA!B7=0,0,(CARGA_DIARIA!J7+CARGA_DIARIA!K7+CARGA_DIARIA!L7+CARGA_DIARIA!M7+CARGA_DIARIA!N7+CARGA_DIARIA!O7+CARGA_DIARIA!P7+CARGA_DIARIA!Q7+CARGA_DIARIA!R7+CARGA_DIARIA!S7+CARGA_DIARIA!T7+CARGA_DIARIA!U7+CARGA_DIARIA!V7+CARGA_DIARIA!W7)/CARGA_DIARIA!B7) -> 0 | E7: =IF(CARGA_DIARIA!B7=0,0,(CARGA_DIARIA!X7+CARGA_DIARIA!Y7+CARGA_DIARIA!Z7+CARGA_DIARIA!AA7)/CARGA_DIARIA!B7+CARGA_DIARIA!AB7+CARGA_DIARIA!AC7+CARGA_DIARIA!AD7+CARGA_DIARIA!AE7) -> 0 | H7: =C7-D7-E7 -> 0
A8: =CARGA_DIARIA!A8 -> 0 | B8: =CARGA_DIARIA!B8 -> 0 | C8: =IF(CARGA_DIARIA!B8=0,0,(CARGA_DIARIA!C8+CARGA_DIARIA!D8+CARGA_DIARIA!E8+CARGA_DIARIA!F8+CARGA_DIARIA!G8+CARGA_DIARIA!H8+CARGA_DIARIA!I8+CARGA_DIARIA!AG8+CARGA_DIARIA!AH8+CARGA_DIARIA!AI8+CARGA_DIARIA!AJ8)/CARGA_DIARIA!B8+CARGA_DIARIA!AF8) -> 0 | D8: =IF(CARGA_DIARIA!B8=0,0,(CARGA_DIARIA!J8+CARGA_DIARIA!K8+CARGA_DIARIA!L8+CARGA_DIARIA!M8+CARGA_DIARIA!N8+CARGA_DIARIA!O8+CARGA_DIARIA!P8+CARGA_DIARIA!Q8+CARGA_DIARIA!R8+CARGA_DIARIA!S8+CARGA_DIARIA!T8+CARGA_DIARIA!U8+CARGA_DIARIA!V8+CARGA_DIARIA!W8)/CARGA_DIARIA!B8) -> 0 | E8: =IF(CARGA_DIARIA!B8=0,0,(CARGA_DIARIA!X8+CARGA_DIARIA!Y8+CARGA_DIARIA!Z8+CARGA_DIARIA!AA8)/CARGA_DIARIA!B8+CARGA_DIARIA!AB8+CARGA_DIARIA!AC8+CARGA_DIARIA!AD8+CARGA_DIARIA!AE8) -> 0 | H8: =C8-D8-E8 -> 0
A9: Promedio período | C9: =IFERROR(AVERAGE(C4:C8),"-") -> 5393439.9 | D9: =IFERROR(AVERAGE(D4:D8),"-") -> 81031.849 | E9: =IFERROR(AVERAGE(E4:E8),"-") -> 3767237.5 | F9: — | G9: — | H9: =IFERROR(AVERAGE(H4:H8),"-") -> 1545170.6

Sheet VENCIMIENTOS
A1: VENCIMIENTOS — Cheques a cobrar y compromisos de pago próximos
A2: Ingresá cada cheque o compromiso con su fecha exacta. El dashboard lo muestra en el calendario de vencimientos.
A3: Fecha | B3: Tipo | C3: Descripción / Contraparte | D3: Monto (ARS) | E3: TC del día | F3: Monto (USD) | G3: Estado
A4: 46148 | B4: COBRO | C4: Cheque acreditación — Cliente Norte | D4: 42000000 | E4: 1197 | F4: =IFERROR(D4/E4,0) -> 35087.719 | G4: Pendiente
A5: 46149 | B5: PAGO | C5: Proveedor Pescadores del Sur | D5: 87000000 | E5: 1197 | F5: =IFERROR(D5/E5,0) -> 72681.704 | G5: Pendiente
A6: 46150 | B6: COBRO | C6: Cheque — Distribuidora Atlántica | D6: 65000000 | E6: 1197 | F6: =IFERROR(D6/E6,0) -> 54302.423 | G6: Pendiente
A7: 46151 | B7: PAGO | C7: Cuota préstamo Banco Galicia | D7: 48500000 | E7: 1197 | F7: =IFERROR(D7/E7,0) -> 40517.962 | G7: Pendiente
A8: 46152 | B8: COBRO | C8: Cobro exportación (USD 95.000) | D8: 113715000 | E8: 1197 | F8: =IFERROR(D8/E8,0) -> 95000 | G8: Pendiente
A9: 46152 | B9: PAGO | C9: RRHH — sueldos quincena | D9: 96000000 | E9: 1197 | F9: =IFERROR(D9/E9,0) -> 80200.501 | G9: Pendiente
A10: 46154 | B10: PAGO | C10: Arancel / canon mensual | D10: 23000000 | E10: 1197 | F10: =IFERROR(D10/E10,0) -> 19214.703 | G10: Pendiente
A11: 46157 | B11: COBRO | C11: Cheque — Exportadora Patagónica | D11: 145000000 | E11: 1197 | F11: =IFERROR(D11/E11,0) -> 121136.17 | G11: Pendiente
A12: 46162 | B12: PAGO | C12: Deuda proveedor exterior (USD 80.000) | D12: 95760000 | E12: 1197 | F12: =IFERROR(D12/E12,0) -> 80000 | G12: Pendiente

Sheet DIVISAS
A1: DIVISAS DISPONIBLES — Seguimiento diario de posición en USD
A2: Fecha | B2: TC BNA | C2: Patag. (USD) | D2: Francés (USD) | E2: Total USD | F2: Liquidado hoy (USD)
A3: 46140 | B3: 1194 | C3: 285000 | D3: 140000 | E3: =C3+D3 -> 425000 | F3: 87000
A4: 46141 | B4: 1196 | C4: 268000 | D4: 135000 | E4: =C4+D4 -> 403000 | F4: 72000
A5: 46142 | B5: 1197 | C5: 301000 | D5: 148000 | E5: =C5+D5 -> 449000 | F5: 95000
A6: 46144 | B6: 1198.5 | C6: 275000 | D6: 128000 | E6: =C6+D6 -> 403000 | F6: 68000
A7: 46147 | B7: 1197 | C7: 285000 | D7: 140000 | E7: =C7+D7 -> 425000 | F7: 87000

Sheet CREDITOS_EXTERIOR
A1: CRÉDITOS POR VENTAS AL EXTERIOR — Facturas de exportación pendientes de cobro
A2: N° Factura | B2: Cliente (País) | C2: Fecha Factura | D2: Fecha Vto. | E2: Días al vto. | F2: Monto (USD) | G2: TC estimado | H2: ARS equivalente | I2: Estado
A3: EXP-2026-041 | B3: Nordic Fish AS (Noruega) | C3: 46096 | D3: 46157 | E3: =IFERROR(D3-TODAY(),"") -> 8 | F3: 320000 | G3: 1197 | H3: =IFERROR(F3*G3,0) -> 383040000 | I3: Pendiente
A4: EXP-2026-055 | B4: Iberian Seafood SL (España) | C4: 46113 | D4: 46172 | E4: =IFERROR(D4-TODAY(),"") -> 23 | F4: 185000 | G4: 1197 | H4: =IFERROR(F4*G4,0) -> 221445000 | I4: Pendiente
A5: EXP-2026,062 | B5: Ocean Trade LLC (EEUU) | C5: 46122 | D5: 46183 | E5: =IFERROR(D5-TODAY(),"") -> 34 | F5: 240000 | G5: 1197 | H5: =IFERROR(F5*G5,0) -> 287280000 | I5: Pendiente
A6: EXP-2026-071 | B6: Maruha Nichiro (Japón) | C6: 46132 | D6: 46193 | E6: =IFERROR(D6-TODAY(),"") -> 44 | F6: 495000 | G6: 1197 | H6: =IFERROR(F6*G6,0) -> 592515000 | I6: Pendiente

Sheet CARGA_DIARIA
A1: CARGA DIARIA — POSICIÓN FINANCIERA | Valores en PESOS argentinos (ARS)
A2: FECHA | B2: TIPO DE CAMBIO BNA (ARS/USD) | C2: ACTIVO CORRIENTE (ARS) | J2: GASTOS DEL DÍA POR SECTOR (ARS) | W2: PASIVO CORRIENTE (ARS)
A3: Fecha | B3: TC BNA (ARS/USD) | C3: Efectivo (MI) | D3: Cheques en cartera | E3: Banco Patagonia | F3: Banco Galicia | G3: Banco Francés | H3: Banco Santander | I3: Créditos MI | J3: Proveedores | K3: Aranceles y Cánones | L3: Comercio Exterior | M3: Directores / Accionistas | N3: Empresas del Grupo | O3: Gastos de Buques | P3: Impuestos y Tasas | Q3: RRHH | R3: Servicios Varios | S3: Retiros Particulares | T3: Pago Importaciones | U3: Compra Dólares (CCL) | V3: Pago Préstamos | W3: Otros Gastos | X3: Cheques Emitidos | Y3: Gs. Presup. Próximos | Z3: Préstamos ML (ARS) | AA3: Deuda Proveed. MI | AB3: Deuda Proveed. Ext. (USD) | AC3: Préstamos ME (USD) | AD3: Intereses Proy. (USD) | AE3: Otras Deudas (USD) | AF3: Stock a Precio Venta (USD) | AG3: Posición Fiscal | AH3: Divisas Disp. (ARS eq.) | AI3: Créditos Exterior (ARS eq.) | AJ3: Inversiones FCI
A4: 46148 | B4: 1394 | C4: 0 | D4: 1004100985 | E4: 169968000 | F4: 154116000 | G4: 5631000 | H4: 2000000 | I4: 1157142384 | J4: 164021678 | K4: 0 | L4: 8902350 | M4: 0 | N4: 0 | O4: 0 | P4: =8169453+7200000 -> 15369453 | Q4: 196498507 | R4: 0 | S4: 0 | T4: 0 | U4: 180000000 | V4: 0 | W4: 0 | X4: 1105183352 | Y4: 3123849992 | Z4: 2.0273466e+08 | AA4: 7025155800 | AB4: 1196248 | AC4: 9000000 | AD4: 141199.47 | AE4: =160000+120000 -> 280000 | AF4: 12797568 | AG4: 5582721359 | AH4: 2.680599e+09 | AI4: 8928795828 | AJ4: 67392000
A9: → NUEVA FECHA | B9: ← Ingresar TC del día
A10: ⚠ Columnas en AMARILLO → valores ya expresados en USD (no se dividen por el tipo de cambio). Todas las demás columnas se ingresan en ARS.

Sheet CHEQUES
A1: CHEQUES EN CARTERA — Listado completo para flujo de fondos
A2: Pegá acá los datos exportados del sistema. Fecha de acreditación = Fecha de pago + 2 días hábiles (48hs). El dashboard lee esta hoja automáticamente.
A3: Razón Social | B3: N° Cheque | C3: Monto (ARS) | D3: Fecha de Emisión | E3: Fecha de Pago | F3: Fecha Acreditación (Pago + 48hs) | G3: Observaciones
A4: CONGELADOS LOS TANOS S. A. | B4: 2219061 | C4: 3400000 | D4: 46149 | E4: 46127 | F4: =+E4+2 -> 46129
A5: LUCRINO MARE SA | B5: 13111470 | C5: 3224950 | D5: 46150 | E5: 46132 | F5: =+E5+2 -> 46134
A6: LUDAPEZ SA | B6: 13377997 | C6: 3100000 | D6: 46151 | E6: 46147 | F6: =+E6+2 -> 46149
A7: LUCRINO MARE SA | B7: 12924495 | C7: 4981600 | D7: 46152 | E7: 46147 | F7: =+E7+2 -> 46149
A8: LACAR FISH SA | B8: 78055845 | C8: 600000 | D8: 46153 | E8: 46147 | F8: =+E8+2 -> 46149
A9: SAORI SA | B9: 66003981 | C9: 4000000 | D9: 46154 | E9: 46147 | F9: =+E9+2 -> 46149
A10: LACAR FISH SA | B10: 78055854 | C10: 1235000 | D10: 46155 | E10: 46147 | F10: =+E10+2 -> 46149
A11: LACAR FISH SA | B11: 78055860 | C11: 1325000 | D11: 46156 | E11: 46147 | F11: =+E11+2 -> 46149
A12: FRIGOSUR SRL | B12: 9583069 | C12: 12938400 | D12: 46157 | E12: 46147 | F12: =+E12+2 -> 46149
A13: COOPERATIVA DE TRABAJO CAÑAMAR LIMITADA | B13: 3940 | C13: 115144.56 | D13: 46158 | E13: 46147 | F13: =+E13+2 -> 46149
A14: COOPERATIVA DE TRABAJO CAÑAMAR LIMITADA | B14: 10333097 | C14: 509557.57 | D14: 46159 | E14: 46147 | F14: =+E14+2 -> 46149
A15: LUDAPEZ SA | B15: 13377998 | C15: 3100000 | D15: 46160 | E15: 46148 | F15: =+E15+2 -> 46150
... A192: CLUB ATLETICO ALDOSIVI | B192: 3436588 | C192: 1934482.9 | D192: 46337 | E192: 46223 | F192: =+E192+2 -> 46225
A671: TOTAL | C671: =SUM(C4:C8) -> 15306550
F672: =IF(E672="","",E672+2)
F673: =IF(E673="","",E673+2)
F674: =IF(E674="","",E674+2)
F675: =IF(E675="","",E675+2)
F676: =IF(E676="","",E676+2)
A678: 📌 Para agregar cheques: pegá las filas del sistema sobre las filas grises, respetando el formato de fechas DD/MM/AAAA. La col. F (Acreditación) se calcula sola.

Sheet Hoja1
A1: Cuenta corriente | B1: Descripción cuenta de tesoreria | C1: Fecha calculada | D1: Número interno | E1: Número de cheque/doc | F1: Categoría del cheque | G1: Código de banco | H1: Importe | I1: CLIENTE | J1: PROVEEDOR | K1: NCLIENTE | L1: NPROVEEDOR | M1: BANCO | N1: MECHEQ | O1: ECHEQ
A2: VAL01 | B2: Valores a depositar | C2: 46127 | D2: 23454 | E2: 2219061 | F2: T | G2: 011 | H2: 3400000 | I2: CONGELADOS LOS TANOS S. A. | K2: I7358 | M2: BANCO DE LA NACION ARGENTINA
A3: VAL01 | B3: Valores a depositar | C3: 46132 | D3: 23238 | E3: 13111470 | F3: T | G3: 014 | H3: 3224950 | I3: LUCRINO MARE SA | K3: I7159 | M3: BANCO DE LA PROVINCIA DE BUENOS AIRES
A4: VAL01 | B4: Valores a depositar | C4: 46147 | D4: 23289 | E4: 13377997 | F4: P | G4: 015 | H4: 3100000 | I4: LUDAPEZ SA | K4: I7238 | M4: ICBC-INDUSTRIAL AND COMMERCIAL BANK OF CHINA | N4: S | O4: E
A5: VAL01 | B5: Valores a depositar | C5: 46147 | D5: 23353 | E5: 12924495 | F5: P | G5: 014 | H5: 4981600 | I5: LUCRINO MARE SA | K5: I7159 | M5: BANCO DE LA PROVINCIA DE BUENOS AIRES | N5: S | O5: E
A6: VAL01 | B6: Valores a depositar | C6: 46147 | D6: 23378 | E6: 78055845 | F6: P | G6: 025 | H6: 600000 | I6: LACAR FISH SA | K6: I7116 | M6: BANCO SANTANDER RIO | N6: S | O6: E
A7: VAL01 | B7: Valores a depositar | C7: 46147 | D7: 23395 | E7: 66003981 | F7: P | G7: 285 | H7: 4000000 | I7: SAORI SA | K7: I7302 | M7: BANCO MACRO BANSUD S.A. | N7: S | O7: E
A8: VAL01 | B8: Valores a depositar | C8: 46147 | D8: 23416 | E8: 78055854 | F8: P | G8: 025 | H8: 1235000 | I8: LACAR FISH SA | K8: I7116 | M8: BANCO SANTANDER RIO | N8: S | O8: E
A9: VAL01 | B9: Valores a depositar | C9: 46147 | D9: 23422 | E9: 78055860 | F9: P | G9: 025 | H9: 1325000 | I9: LACAR FISH SA | K9: I7116 | M9: BANCO SANTANDER RIO | N9: S | O9: E
A10: VAL01 | B10: Valores a depositar | C10: 46147 | D10: 23462 | E10: 9583069 | F10: P | G10: 014 | H10: 12938400 | I10: FRIGOSUR SRL | K10: I468 | M10: BANCO DE LA PROVINCIA DE BUENOS AIRES | N10: S | O10: E
A11: VAL01 | B11: Valores a depositar | C11: 46147 | D11: 23475 | E11: 3940 | F11: T | G11: 025 | H11: 115144.56 | I11: COOPERATIVA DE TRABAJO CAÑAMAR LIMITADA | K11: I7310 | M11: BANCO SANTANDER RIO | N11: S | O11: E
A12: VAL01 | B12: Valores a depositar | C12: 46147 | D12: 23476 | E12: 10333097 | F12: T | G12: 299 | H12: 509557.57 | I12: COOPERATIVA DE TRABAJO CAÑAMAR LIMITADA | K12: I7310 | M12: BANCO COMAFI SOCIEDAD ANONIMA | N12: S | O12: E
A13: VAL01 | B13: Valores a depositar | C13: 46148 | D13: 23290 | E13: 13377998 | F13: P | G13: 015 | H13: 3100000 | I13: LUDAPEZ SA | K13: I7238 | M13: ICBC-INDUSTRIAL AND COMMERCIAL BANK OF CHINA | N13: S | O13: E
A14: VAL01 | B14: Valores a depositar | C14: 46148 | D14: 23292 | E14: 13378000 | F14: P | G14: 015 | H14: 3100000 | I14: LUDAPEZ SA | K14: I7238 | M14: ICBC-INDUSTRIAL AND COMMERCIAL BANK OF CHINA | N14: S | O14: E
A15: VAL01 | B15: Valores a depositar | C15: 46148 | D15: 23383 | E15: 1142 | F15: P | G15: 007 | H15: 24001062 | I15: MARDI SA | K15: I227 | M15: BANCO DE GALICIA Y BUENOS AIRES S.A. | N15: S | O15: E
... A25: VAL01 | B25: Valores a depositar | C25: 46149 | D25: 23451 | E25: 29050276 | F25: P | G25: 191 | H25: 9811200 | I25: COOPERATIVA DE TRABAJO CAÑAMAR LIMITADA | K25: I7310 | M25: BANCO CREDICOOP COOPERATIVO LIMITADO | N25: S | O25: E
A26: VAL01 | B26: Valores a depositar | C26: 46149 | D26: 23455 | E26: 65636545 | F26: T | G26: 093 | H26: 2800000 | I26: CONGELADOS LOS TANOS S. A. | K26: I7358 | M26: BANCO DE LA PAMPA SOCIEDAD DE ECONOMÍA M
A27: VAL01 | B27: Valores a depositar | C27: 46149 | D27: 23467 | E27: 4510 | F27: P | G27: 007 | H27: 1200000 | I27: MARISQUERIA SANTA RITA SRL | K27: I6 | M27: BANCO DE GALICIA Y BUENOS AIRES S.A. | N27: S | O27: E
A28: VAL01 | B28: Valores a depositar | C28: 46150 | D28: 23380 | E28: 78055847 | F28: P | G28: 025 | H28: 589500 | I28: LACAR FISH SA | K28: I7116 | M28: BANCO SANTANDER RIO | N28: S | O28: E
A29: VAL01 | B29: Valores a depositar | C29: 46150 | D29: 23394 | E29: 4445 | F29: P | G29: 007 | H29: 1200000 | I29: MARISQUERIA SANTA RITA SRL | K29: I6 | M29: BANCO DE GALICIA Y BUENOS AIRES S.A. | N29: S | O29: E
A30: VAL01 | B30: Valores a depositar | C30: 46150 | D30: 23400 | E30: 6753 | F30: P | G30: 007 | H30: 19891200 | I30: COMERCIAL INAL 2005 SA | K30: I7222 | M30: BANCO DE GALICIA Y BUENOS AIRES S.A. | N30: S | O30: E
A31: VAL01 | B31: Valores a depositar | C31: 46150 | D31: 23405 | E31: 1198 | F31: P | G31: 007 | H31: 9846730 | I31: MARDI SA | K31: I227 | M31: BANCO DE GALICIA Y BUENOS AIRES S.A. | N31: S | O31: E
A32: VAL01 | B32: Valores a depositar | C32: 46150 | D32: 23406 | E32: 9583048 | F32: P | G32: 014 | H32: 12134230 | I32: FRIGOSUR SRL | K32: I468 | M32: BANCO DE LA PROVINCIA DE BUENOS AIRES | N32: S | O32: E
A33: VAL01 | B33: Valores a depositar | C33: 46150 | D33: 23418 | E33: 78055856 | F33: P | G33: 025 | H33: 1235000 | I33: LACAR FISH SA | K33: I7116 | M33: BANCO SANTANDER RIO | N33: S | O33: E
A34: VAL01 | B34: Valores a depositar | C34: 46150 | D34: 23424 | E34: 78055862 | F34: P | G34: 025 | H34: 1325000 | I34: LACAR FISH SA | K34: I7116 | M34: BANCO SANTANDER RIO | N34: S | O34: E
A35: VAL01 | B35: Valores a depositar | C35: 46150 | D35: 23430 | E35: 90000109 | F35: P | G35: 017 | H35: 2000000 | I35: PUERTO RAWAMAR S.A. | K35: I7359 | M35: BBVA Banco Frances S.A | N35: S | O35: E
A36: VAL01 | B36: Valores a depositar | C36: 46150 | D36: 23468 | E36: 4511 | F36: P | G36: 007 | H36: 966000 | I36: MARISQUERIA SANTA RITA SRL | K36: I6 | M36: BANCO DE GALICIA Y BUENOS AIRES S.A. | N36: S | O36: E
A37: VAL01 | B37: Valores a depositar | C37: 46150 | D37: 23490 | E37: 4536 | F37: P | G37: 007 | H37: 930000 | I37: MARISQUERIA SANTA RITA SRL | K37: I6 | M37: BANCO DE GALICIA Y BUENOS AIRES S.A. | N37: S | O37: E
A38: VAL01 | B38: Valores a depositar | C38: 46150 | D38: 23551 | E38: 78055879 | F38: P | G38: 025 | H38: 500000 | I38: LACAR FISH SA | K38: I7116 | M38: BANCO SANTANDER RIO | N38: S | O38: E
A39: VAL01 | B39: Valores a depositar | C39: 46150 | D39: 23590 | E39: 51747693 | F39: P | G39: 285 | H39: 7588800 | I39: GUBITI SA | K39: I7325 | M39: BANCO MACRO BANSUD S.A. | N39: N
A40: VAL01 | B40: Valores a depositar | C40: 46153 | D40: 23293 | E40: 13378001 | F40: P | G40: 015 | H40: 3100000 | I40: LUDAPEZ SA | K40: I7238 | M40: ICBC-INDUSTRIAL AND COMMERCIAL BANK OF CHINA | N40: S | O40: E
A41: VAL01 | B41: Valores a depositar | C41: 46153 | D41: 23294 | E41: 13378002 | F41: P | G41: 015 | H41: 3100000 | I41: LUDAPEZ SA | K41: I7238 | M41: ICBC-INDUSTRIAL AND COMMERCIAL BANK OF CHINA | N41: S | O41: E
A42: VAL01 | B42: Valores a depositar | C42: 46153 | D42: 23295 | E42: 13378003 | F42: P | G42: 015 | H42: 3100000 | I42: LUDAPEZ SA | K42: I7238 | M42: ICBC-INDUSTRIAL AND COMMERCIAL BANK OF CHINA | N42: S | O42: E
A43: VAL01 | B43: Valores a depositar | C43: 46153 | D43: 23359 | E43: 65991486 | F43: P | G43: 285 | H43: 10000000 | I43: 27 DE NOVIEMBRE SA | K43: I596 | M43: BANCO MACRO BANSUD S.A. | N43: S | O43: E
A44: VAL01 | B44: Valores a depositar | C44: 46153 | D44: 23360 | E44: 65991495 | F44: P | G44: 285 | H44: 10000000 | I44: 27 DE NOVIEMBRE SA | K44: I596 | M44: BANCO MACRO BANSUD S.A. | N44: S | O44: E
A45: VAL01 | B45: Valores a depositar | C45: 46153 | D45: 23361 | E45: 65991500 | F45: P | G45: 285 | H45: 10000000 | I45: 27 DE NOVIEMBRE SA | K45: I596 | M45: BANCO MACRO BANSUD S.A. | N45: S | O45: E
A46: VAL01 | B46: Valores a depositar | C46: 46153 | D46: 23362 | E46: 65991510 | F46: P | G46: 285 | H46: 10000000 | I46: 27 DE NOVIEMBRE SA | K46: I596 | M46: BANCO MACRO BANSUD S.A. | N46: S | O46: E
A47: VAL01 | B47: Valores a depositar | C47: 46153 | D47: 23363 | E47: 65991522 | F47: P | G47: 285 | H47: 9035234.9 | I47: 27 DE NOVIEMBRE SA | K47: I596 | M47: BANCO MACRO BANSUD S.A. | N47: S | O47: E
A48: VAL01 | B48: Valores a depositar | C48: 46153 | D48: 23381 | E48: 6747 | F48: P | G48: 007 | H48: 11370880 | I48: COMERCIAL INAL 2005 SA | K48: I7222 | M48: BANCO DE GALICIA Y BUENOS AIRES S.A. | N48: S | O48: E
A49: VAL01 | B49: Valores a depositar | C49: 46153 | D49: 23419 | E49: 78055857 | F49: P | G49: 025 | H49: 1227000 | I49: LACAR FISH SA | K49: I7116 | M49: BANCO SANTANDER RIO | N49: S | O49: E
A50: VAL01 | B50: Valores a depositar | C50: 46153 | D50: 23425 | E50: 78055863 | F50: P | G50: 025 | H50: 1325000 | I50: LACAR FISH SA | K50: I7116 | M50: BANCO SANTANDER RIO | N50: S | O50: E
A51: VAL01 | B51: Valores a depositar | C51: 46153 | D51: 23432 | E51: 29057187 | F51: P | G51: 191 | H51: 43000000 | I51: FRIO SUR SRL | K51: I208 | M51: BANCO CREDICOOP COOPERATIVO LIMITADO | N51: S | O51: E
A52: VAL01 | B52: Valores a depositar | C52: 46153 | D52: 23452 | E52: 9487742 | F52: P | G52: 014 | H52: 12289006 | I52: PROYECTOS DEL MAR SRL | K52: I636 | M52: BANCO DE LA PROVINCIA DE BUENOS AIRES | N52: S | O52: E
A53: VAL01 | B53: Valores a depositar | C53: 46153 | D53: 23456 | E53: 14974124 | F53: T | G53: 014 | H53: 990000 | I53: CONGELADOS LOS TANOS S. A. | K53: I7358 | M53: BANCO DE LA PROVINCIA DE BUENOS AIRES
A54: VAL01 | B54: Valores a depositar | C54: 46153 | D54: 23461 | E54: 9583068 | F54: P | G54: 014 | H54: 12938400 | I54: FRIGOSUR SRL | K54: I468 | M54: BANCO DE LA PROVINCIA DE BUENOS AIRES | N54: S | O54: E
A55: VAL01 | B55: Valores a depositar | C55: 46153 | D55: 23469 | E55: 12924512 | F55: P | G55: 014 | H55: 10000000 | I55: LUCRINO MARE SA | K55: I7159 | M55: BANCO DE LA PROVINCIA DE BUENOS AIRES
A56: VAL01 | B56: Valores a depositar | C56: 46153 | D56: 23491 | E56: 4537 | F56: P | G56: 007 | H56: 930000 | I56: MARISQUERIA SANTA RITA SRL | K56: I6 | M56: BANCO DE GALICIA Y BUENOS AIRES S.A. | N56: S | O56: E
A57: VAL01 | B57: Valores a depositar | C57: 46153 | D57: 23495 | E57: 4571 | F57: P | G57: 007 | H57: 1300000 | I57: MARISQUERIA SANTA RITA SRL | K57: I6 | M57: BANCO DE GALICIA Y BUENOS AIRES S.A. | N57: S | O57: E
A58: VAL01 | B58: Valores a depositar | C58: 46153 | D58: 23506 | E58: 9564653 | F58: P | G58: 014 | H58: 2754200 | I58: COOPERATIVA DE TRABAJO DOÑA FRANCISCA LTDA | K58: I7149 | M58: BANCO DE LA PROVINCIA DE BUENOS AIRES | N58: S | O58: E
A59: VAL01 | B59: Valores a depositar | C59: 46153 | D59: 23507 | E59: 9564654 | F59: P | G59: 014 | H59: 4500000 | I59: COOPERATIVA DE TRABAJO DOÑA FRANCISCA LTDA | K59: I7149 | M59: BANCO DE LA PROVINCIA DE BUENOS AIRES | N59: S | O59: E
A60: VAL01 | B60: Valores a depositar | C60: 46153 | D60: 23508 | E60: 9564655 | F60: P | G60: 014 | H60: 4500000 | I60: COOPERATIVA DE TRABAJO DOÑA FRANCISCA LTDA | K60: I7149 | M60: BANCO DE LA PROVINCIA DE BUENOS AIRES | N60: S | O60: E
A61: VAL01 | B61: Valores a depositar | C61: 46153 | D61: 23509 | E61: 9564656 | F61: P | G61: 014 | H61: 4500000 | I61: COOPERATIVA DE TRABAJO DOÑA FRANCISCA LTDA | K61: I7149 | M61: BANCO DE LA PROVINCIA DE BUENOS AIRES | N61: S | O61: E
A62: VAL01 | B62: Valores a depositar | C62: 46153 | D62: 23541 | E62: 697 | F62: P | G62: 027 | H62: 5000000 | I62: COOPERATIVA DE TRABAJO DOÑA FRANCISCA LTDA | K62: I7149 | M62: BANCO SUPERVIELLE S.A. | N62: S | O62: E
A63: VAL01 | B63: Valores a depositar | C63: 46153 | D63: 23542 | E63: 698 | F63: P | G63: 027 | H63: 6756340 | I63: COOPERATIVA DE TRABAJO DOÑA FRANCISCA LTDA | K63: I7149 | M63: BANCO SUPERVIELLE S.A. | N63: S | O63: E
A64: VAL01 | B64: Valores a depositar | C64: 46153 | D64: 23543 | E64: 699 | F64: P | G64: 027 | H64: 5000000 | I64: COOPERATIVA DE TRABAJO DOÑA FRANCISCA LTDA | K64: I7149 | M64: BANCO SUPERVIELLE S.A. | N64: S | O64: E
A65: VAL01 | B65: Valores a depositar | C65: 46153 | D65: 23544 | E65: 700 | F65: P | G65: 027 | H65: 5000000 | I65: COOPERATIVA DE TRABAJO DOÑA FRANCISCA LTDA | K65: I7149 | M65: BANCO SUPERVIELLE S.A. | N65: S | O65: E
A66: VAL01 | B66: Valores a depositar | C66: 46153 | D66: 23545 | E66: 701 | F66: P | G66: 027 | H66: 5000000 | I66: COOPERATIVA DE TRABAJO DOÑA FRANCISCA LTDA | K66: I7149 | M66: BANCO SUPERVIELLE S.A. | N66: S | O66: E
A67: VAL01 | B67: Valores a depositar | C67: 46153 | D67: 23546 | E67: 711 | F67: P | G67: 027 | H67: 5000000 | I67: COOPERATIVA DE TRABAJO DOÑA FRANCISCA LTDA | K67: I7149 | M67: BANCO SUPERVIELLE S.A. | N67: S | O67: E
... A74: VAL01 | B74: Valores a depositar | C74: 46154 | D74: 23426 | E74: 78055864 | F74: P | G74: 025 | H74: 1325000 | I74: LACAR FISH SA | K74: I7116 | M74: BANCO SANTANDER RIO | N74: S | O74: E
A75: VAL01 | B75: Valores a depositar | C75: 46154 | D75: 23470 | E75: 12924513 | F75: P | G75: 014 | H75: 10000000 | I75: LUCRINO MARE SA | K75: I7159 | M75: BANCO DE LA PROVINCIA DE BUENOS AIRES
A76: VAL01 | B76: Valores a depositar | C76: 46154 | D76: 23492 | E76: 4538 | F76: P | G76: 007 | H76: 930000 | I76: MARISQUERIA SANTA RITA SRL | K76: I6 | M76: BANCO DE GALICIA Y BUENOS AIRES S.A. | N76: S | O76: E
A77: VAL01 | B77: Valores a depositar | C77: 46154 | D77: 23496 | E77: 4572 | F77: P | G77: 007 | H77: 1300000 | I77: MARISQUERIA SANTA RITA SRL | K77: I6 | M77: BANCO DE GALICIA Y BUENOS AIRES S.A. | N77: S | O77: E
A78: VAL01 | B78: Valores a depositar | C78: 46154 | D78: 23553 | E78: 78055881 | F78: P | G78: 025 | H78: 500000 | I78: LACAR FISH SA | K78: I7116 | M78: BANCO SANTANDER RIO | N78: S | O78: E
A79: VAL01 | B79: Valores a depositar | C79: 46154 | D79: 23559 | E79: 78055889 | F79: P | G79: 025 | H79: 890000 | I79: LACAR FISH SA | K79: I7116 | M79: BANCO SANTANDER RIO | N79: S | O79: E
A80: VAL01 | B80: Valores a depositar | C80: 46155 | D80: 23296 | E80: 13378005 | F80: P | G80: 015 | H80: 3100000 | I80: LUDAPEZ SA | K80: I7238 | M80: ICBC-INDUSTRIAL AND COMMERCIAL BANK OF CHINA | N80: S | O80: E
A81: VAL01 | B81: Valores a depositar | C81: 46155 | D81: 23402 | E81: 13378020 | F81: P | G81: 015 | H81: 2200000 | I81: LUDAPEZ SA | K81: I7238 | M81: ICBC-INDUSTRIAL AND COMMERCIAL BANK OF CHINA | N81: S | O81: E
A82: VAL01 | B82: Valores a depositar | C82: 46155 | D82: 23471 | E82: 12924514 | F82: P | G82: 014 | H82: 10000000 | I82: LUCRINO MARE SA | K82: I7159 | M82: BANCO DE LA PROVINCIA DE BUENOS AIRES
A83: VAL01 | B83: Valores a depositar | C83: 46155 | D83: 23493 | E83: 4539 | F83: P | G83: 007 | H83: 930000 | I83: MARISQUERIA SANTA RITA SRL | K83: I6 | M83: BANCO DE GALICIA Y BUENOS AIRES S.A. | N83: S | O83: E
A84: VAL01 | B84: Valores a depositar | C84: 46155 | D84: 23497 | E84: 4573 | F84: P | G84: 007 | H84: 1300000 | I84: MARISQUERIA SANTA RITA SRL | K84: I6 | M84: BANCO DE GALICIA Y BUENOS AIRES S.A. | N84: S | O84: E
A85: VAL01 | B85: Valores a depositar | C85: 46155 | D85: 23581 | E85: 1367 | F85: P | G85: 007 | H85: 25000000 | I85: MARDI SA | K85: I227 | M85: BANCO DE GALICIA Y BUENOS AIRES S.A. | N85: S | O85: E
A86: VAL01 | B86: Valores a depositar | C86: 46156 | D86: 23298 | E86: 13378006 | F86: P | G86: 015 | H86: 3100000 | I86: LUDAPEZ SA | K86: I7238 | M86: ICBC-INDUSTRIAL AND COMMERCIAL BANK OF CHINA | N86: S | O86: E
A87: VAL01 | B87: Valores a depositar | C87: 46156 | D87: 23403 | E87: 13378021 | F87: P | G87: 015 | H87: 2200000 | I87: LUDAPEZ SA | K87: I7238 | M87: ICBC-INDUSTRIAL AND COMMERCIAL BANK OF CHINA | N87: S | O87: E
A88: VAL01 | B88: Valores a depositar | C88: 46156 | D88: 23427 | E88: 78055865 | F88: P | G88: 025 | H88: 1325000 | I88: LACAR FISH SA | K88: I7116 | M88: BANCO SANTANDER RIO | N88: S | O88: E
A89: VAL01 | B89: Valores a depositar | C89: 46156 | D89: 23472 | E89: 12924515 | F89: P | G89: 014 | H89: 10000000 | I89: LUCRINO MARE SA | K89: I7159 | M89: BANCO DE LA PROVINCIA DE BUENOS AIRES
A90: VAL01 | B90: Valores a depositar | C90: 46156 | D90: 23481 | E90: 4959 | F90: P | G90: 025 | H90: 3118540 | I90: INDUSTRIAS EL CORSARIO S.A. | K90: I7335 | M90: BANCO SANTANDER RIO | N90: S | O90: E
A91: VAL01 | B91: Valores a depositar | C91: 46156 | D91: 23560 | E91: 78055890 | F91: P | G91: 025 | H91: 890000 | I91: LACAR FISH SA | K91: I7116 | M91: BANCO SANTANDER RIO | N91: S | O91: E
A92: VAL01 | B92: Valores a depositar | C92: 46156 | D92: 23569 | E92: 8055882 | F92: P | G92: 025 | H92: 500000 | I92: LACAR FISH SA | K92: I7116 | M92: BANCO SANTANDER RIO | N92: S | O92: E
A93: VAL01 | B93: Valores a depositar | C93: 46157 | D93: 23404 | E93: 13378022 | F93: P | G93: 015 | H93: 2200000 | I93: LUDAPEZ SA | K93: I7238 | M93: ICBC-INDUSTRIAL AND COMMERCIAL BANK OF CHINA | N93: S | O93: E
A94: VAL01 | B94: Valores a depositar | C94: 46157 | D94: 23428 | E94: 78055866 | F94: P | G94: 025 | H94: 1325000 | I94: LACAR FISH SA | K94: I7116 | M94: BANCO SANTANDER RIO | N94: S | O94: E
A95: VAL01 | B95: Valores a depositar | C95: 46157 | D95: 23443 | E95: 6769 | F95: P | G95: 007 | H95: 17049600 | I95: COMERCIAL INAL 2005 SA | K95: I7222 | M95: BANCO DE GALICIA Y BUENOS AIRES S.A. | N95: S | O95: E
A96: VAL01 | B96: Valores a depositar | C96: 46157 | D96: 23473 | E96: 12924516 | F96: P | G96: 014 | H96: 10000000 | I96: LUCRINO MARE SA | K96: I7159 | M96: BANCO DE LA PROVINCIA DE BUENOS AIRES
A97: VAL01 | B97: Valores a depositar | C97: 46157 | D97: 23479 | E97: 29117288 | F97: P | G97: 191 | H97: 10000000 | I97: COOPERATIVA DE TRABAJO CAÑAMAR LIMITADA | K97: I7310 | M97: BANCO CREDICOOP COOPERATIVO LIMITADO | N97: S | O97: E
A98: VAL01 | B98: Valores a depositar | C98: 46157 | D98: 23494 | E98: 4540 | F98: P | G98: 007 | H98: 891750 | I98: MARISQUERIA SANTA RITA SRL | K98: I6 | M98: BANCO DE GALICIA Y BUENOS AIRES S.A. | N98: S | O98: E
A99: VAL01 | B99: Valores a depositar | C99: 46157 | D99: 23498 | E99: 4574 | F99: P | G99: 007 | H99: 1300000 | I99: MARISQUERIA SANTA RITA SRL | K99: I6 | M99: BANCO DE GALICIA Y BUENOS AIRES S.A. | N99: S | O99: E
A100: VAL01 | B100: Valores a depositar | C100: 46157 | D100: 23549 | E100: 3360 | F100: T | G100: 011 | H100: 2190000 | I100: COOPERATIVA DE TRABAJO CAÑAMAR LIMITADA | K100: I7310 | M100: BANCO DE LA NACION ARGENTINA | N100: S | O100: E
A101: VAL01 | B101: Valores a depositar | C101: 46157 | D101: 23554 | E101: 78055883 | F101: P | G101: 025 | H101: 500000 | I101: LACAR FISH SA | K101: I7116 | M101: BANCO SANTANDER RIO | N101: S | O101: E
A102: VAL01 | B102: Valores a depositar | C102: 46157 | D102: 23561 | E102: 78055891 | F102: P | G102: 025 | H102: 890000 | I102: LACAR FISH SA | K102: I7116 | M102: BANCO SANTANDER RIO | N102: S | O102: E
A103: VAL01 | B103: Valores a depositar | C103: 46157 | D103: 23572 | E103: 122 | F103: P | G103: 007 | H103: 3000261.8 | I103: LUMELL SA | K103: I7253 | M103: BANCO DE GALICIA Y BUENOS AIRES S.A. | N103: S | O103: E
A104: VAL01 | B104: Valores a depositar | C104: 46157 | D104: 23573 | E104: 123 | F104: P | G104: 007 | H104: 3870000 | I104: LUMELL SA | K104: I7253 | M104: BANCO DE GALICIA Y BUENOS AIRES S.A. | N104: S | O104: E
A105: VAL01 | B105: Valores a depositar | C105: 46157 | D105: 23574 | E105: 124 | F105: P | G105: 007 | H105: 4000000 | I105: LUMELL SA | K105: I7253 | M105: BANCO DE GALICIA Y BUENOS AIRES S.A. | N105: S | O105: E
A106: VAL01 | B106: Valores a depositar | C106: 46157 | D106: 23587 | E106: 66486728 | F106: P | G106: 285 | H106: 4528200 | I106: SAORI SA | K106: I7302 | M106: BANCO MACRO BANSUD S.A. | N106: S | O106: E
A107: VAL01 | B107: Valores a depositar | C107: 46157 | D107: 23591 | E107: 61747694 | F107: P | G107: 285 | H107: 7365600 | I107: GUBITI SA | K107: I7325 | M107: BANCO MACRO BANSUD S.A. | N107: N
A108: VAL01 | B108: Valores a depositar | C108: 46157 | D108: 23615 | E108: 4628 | F108: P | G108: 007 | H108: 1300000 | I108: MARISQUERIA SANTA RITA SRL | K108: I6 | M108: BANCO DE GALICIA Y BUENOS AIRES S.A. | N108: S | O108: E
A109: VAL01 | B109: Valores a depositar | C109: 46160 | D109: 23265 | E109: 3436586 | F109: P | G109: 034 | H109: 1800000 | I109: CLUB ATLETICO ALDOSIVI | K109: I7203 | M109: BANCO PATAGONIA S.A. | N109: S | O109: E
A110: VAL01 | B110: Valores a depositar | C110: 46160 | D110: 23266 | E110: 3436587 | F110: P | G110: 034 | H110: 1850000 | I110: CLUB ATLETICO ALDOSIVI | K110: I7203 | M110: BANCO PATAGONIA S.A. | N110: S | O110: E
A111: VAL01 | B111: Valores a depositar | C111: 46160 | D111: 23429 | E111: 78055867 | F111: P | G111: 025 | H111: 1324500 | I111: LACAR FISH SA | K111: I7116 | M111: BANCO SANTANDER RIO | N111: S | O111: E
A112: VAL01 | B112: Valores a depositar | C112: 46160 | D112: 23453 | E112: 9487743 | F112: P | G112: 014 | H112: 12220448 | I112: PROYECTOS DEL MAR SRL | K112: I636 | M112: BANCO DE LA PROVINCIA DE BUENOS AIRES | N112: S | O112: E
A113: VAL01 | B113: Valores a depositar | C113: 46160 | D113: 23474 | E113: 12924517 | F113: P | G113: 014 | H113: 7374980 | I113: LUCRINO MARE SA | K113: I7159 | M113: BANCO DE LA PROVINCIA DE BUENOS AIRES
A114: VAL01 | B114: Valores a depositar | C114: 46160 | D114: 23499 | E114: 4575 | F114: P | G114: 007 | H114: 1300000 | I114: MARISQUERIA SANTA RITA SRL | K114: I6 | M114: BANCO DE GALICIA Y BUENOS AIRES S.A. | N114: S | O114: E
A115: VAL01 | B115: Valores a depositar | C115: 46160 | D115: 23502 | E115: 674 | F115: P | G115: 027 | H115: 4500000 | I115: COOPERATIVA DE TRABAJO DOÑA FRANCISCA LTDA | K115: I7149 | M115: BANCO SUPERVIELLE S.A. | N115: S | O115: E
...
