Workbook

Sheet INSTRUCCIONES
A1: DASHBOARD FINANCIERO — EMPRESA PESQUERA
A2: Guía de uso y estructura del archivo
A6: 📋 ESTRUCTURA DEL ARCHIVO
A7: Hoja | B7: Descripción
A8: INSTRUCCIONES | B8: Esta hoja — guía de uso
A9: CARGA_DIARIA | B9: Acá cargás los datos todos los días (una fila por día)
A10: ACTIVO_CORRIENTE | B10: Desglose diario de activos: bancos, cheques, divisas, créditos, FCI
A11: GASTOS_DIARIOS | B11: Detalle de egresos por sector (13 categorías)
A12: PASIVO_CORRIENTE | B12: Compromisos y deudas a corto plazo
A13: VENCIMIENTOS | B13: Cheques a cobrar y pagar en los próximos 30 días
A14: AJUSTES | B14: Stock a precio de venta, posición fiscal, otras deudas
A15: POSICION_NETA | B15: Hoja de cálculo automática — no modificar
A17: 🎨 CONVENCIÓN DE COLORES
A18: Color | B18: Significado
A19: Texto AZUL | B19: Dato a ingresar manualmente (input)
A20: Texto NEGRO | B20: Fórmula calculada automáticamente — no modificar
A21: Texto VERDE | B21: Vínculo a otra hoja del mismo archivo
A22: Fondo AMARILLO | B22: Celda importante que requiere atención o actualización
A24: 📌 INSTRUCCIONES DE CARGA DIARIA
A25: 1. | B25: Abrir la hoja CARGA_DIARIA
A26: 2. | B26: Ir a la última fila con datos e insertar una nueva fila debajo
A27: 3. | B27: Ingresar la fecha del día en la columna A (formato DD/MM/AAAA)
A28: 4. | B28: Ingresar el tipo de cambio BNA del día en la columna B
A29: 5. | B29: Completar el resto de columnas con los valores en PESOS del día
A30: 6. | B30: Los valores en USD se calculan automáticamente dividiendo por el TC
A31: 7. | B31: La hoja POSICION_NETA se actualiza automáticamente
A33: ⚠️ IMPORTANTE
A34: • | B34: No eliminar ni mover filas de encabezado
A35: • | B35: No modificar las hojas de fórmulas (POSICION_NETA)
A36: • | B36: Siempre cargar valores en PESOS — el dashboard convierte a USD
A37: • | B37: Los cheques en cartera cargar en hoja VENCIMIENTOS con fecha de acreditación
A38: • | B38: Guardar el archivo con Ctrl+S después de cada carga

Sheet CARGA_DIARIA
A1: CARGA DIARIA — POSICIÓN FINANCIERA | Valores en PESOS argentinos (ARS)
A2: FECHA | B2: TIPO DE CAMBIO BNA (ARS/USD) | C2: ACTIVO CORRIENTE (ARS) | J2: GASTOS DEL DÍA POR SECTOR (ARS) | W2: PASIVO CORRIENTE (ARS)
A3: Fecha | B3: TC BNA (ARS/USD) | C3: Efectivo (MI) | D3: Cheques en cartera | E3: Banco Patagonia | F3: Banco Galicia | G3: Banco Francés | H3: Banco Santander | I3: Créditos MI | J3: Proveedores | K3: Aranceles y Cánones | L3: Comercio Exterior | M3: Directores / Accionistas | N3: Empresas del Grupo | O3: Gastos de Buques | P3: Impuestos y Tasas | Q3: RRHH | R3: Servicios Varios | S3: Retiros Particulares | T3: Pago Importaciones | U3: Compra Dólares (CCL) | V3: Pago Préstamos | W3: Otros Gastos | X3: Cheques Emitidos | Y3: Gs. Presup. Próximos | Z3: Préstamos ML (ARS) | AA3: Deuda Proveed. MI | AB3: Deuda Proveed. Ext. (USD) | AC3: Préstamos ME (USD) | AD3: Intereses Proy. (USD) | AE3: Otras Deudas (USD) | AF3: Stock a Precio Venta (USD) | AG3: Posición Fiscal | AH3: Divisas Disp. (ARS eq.) | AI3: Créditos Exterior (ARS eq.) | AJ3: Inversiones FCI
A4: 46148 | B4: 1394 | C4: 0 | D4: 1004100985 | E4: 169968000 | F4: 154116000 | G4: 5631000 | H4: 2000000 | I4: 1157142384 | J4: 164021678 | K4: 0 | L4: 8902350 | M4: 0 | N4: 0 | O4: 0 | P4: =8169453+7200000 -> 15369453 | Q4: 196498507 | R4: 0 | S4: 0 | T4: 0 | U4: 180000000 | V4: 0 | W4: 0 | X4: 1105183352 | Y4: 3123849992 | Z4: 2.0273466e+08 | AA4: 7025155800 | AB4: 1196248 | AC4: 9000000 | AD4: 141199.47 | AE4: =160000+120000 -> 280000 | AF4: 12797568 | AG4: 5582721359 | AH4: 2.680599e+09 | AI4: 8928795828 | AJ4: 67392000
AK5: Pago cuota Galicia
AK6: Cobro exportación USD 80k
AK8: Datos de ejemplo
A9: → NUEVA FECHA | B9: ← Ingresar TC del día
A10: ⚠ Columnas en AMARILLO → valores ya expresados en USD (no se dividen por el tipo de cambio). Todas las demás columnas se ingresan en ARS.
D15: activo corriente | E15: =+D4+E4+F4+G4+H4+I4+AG4+AH4 -> 1.0756279e+10 | F15: =+E15/B4 -> 7716125.4
D16: stock | E16: =+AF4 -> 12797568 | F16: =+E16 -> 12797568
F17: =SUM(F15:F16) -> 20513693

Sheet POSICION_NETA
A1: POSICIÓN FINANCIERA NETA DIARIA | Valores en USD (conversión automática)
A2: ⚠ Hoja de cálculo automática — No modificar. Los datos vienen de CARGA_DIARIA.
A3: Fecha | B3: TC BNA | C3: Activo Corriente (USD) | D3: Gastos del Día (USD) | E3: Pasivo Corriente (USD) | F3: Ajustes + (incluido en Activo) | G3: Ajustes - (incluido en Activo) | H3: POSICIÓN NETA (USD)
A4: =CARGA_DIARIA!A4 -> 46148 | B4: =CARGA_DIARIA!B4 -> 1394 | C4: =IF(CARGA_DIARIA!B4=0,0,(CARGA_DIARIA!C4+CARGA_DIARIA!D4+CARGA_DIARIA!E4+CARGA_DIARIA!F4+CARGA_DIARIA!G4+CARGA_DIARIA!H4+CARGA_DIARIA!I4+CARGA_DIARIA!AG4+CARGA_DIARIA!AH4+CARGA_DIARIA!AI4+CARGA_DIARIA!AJ4)/CARGA_DIARIA!B4+CARGA_DIARIA!AF4) -> 26967200 | D4: =IF(CARGA_DIARIA!B4=0,0,(CARGA_DIARIA!J4+CARGA_DIARIA!K4+CARGA_DIARIA!L4+CARGA_DIARIA!M4+CARGA_DIARIA!N4+CARGA_DIARIA!O4+CARGA_DIARIA!P4+CARGA_DIARIA!Q4+CARGA_DIARIA!R4+CARGA_DIARIA!S4+CARGA_DIARIA!T4+CARGA_DIARIA!U4+CARGA_DIARIA!V4+CARGA_DIARIA!W4)/CARGA_DIARIA!B4) -> 405159.25 | E4: =IF(CARGA_DIARIA!B4=0,0,(CARGA_DIARIA!X4+CARGA_DIARIA!Y4+CARGA_DIARIA!Z4+CARGA_DIARIA!AA4)/CARGA_DIARIA!B4+CARGA_DIARIA!AB4+CARGA_DIARIA!AC4+CARGA_DIARIA!AD4+CARGA_DIARIA!AE4) -> 18836188 | H4: =C4-D4-E4 -> 7725852.8
A5: =CARGA_DIARIA!A5 -> 0 | B5: =CARGA_DIARIA!B5 -> 0 | C5: =IF(CARGA_DIARIA!B5=0,0,(CARGA_DIARIA!C5+CARGA_DIARIA!D5+CARGA_DIARIA!E5+CARGA_DIARIA!F5+CARGA_DIARIA!G5+CARGA_DIARIA!H5+CARGA_DIARIA!I5+CARGA_DIARIA!AG5+CARGA_DIARIA!AH5+CARGA_DIARIA!AI5+CARGA_DIARIA!AJ5)/CARGA_DIARIA!B5+CARGA_DIARIA!AF5) -> 0 | D5: =IF(CARGA_DIARIA!B5=0,0,(CARGA_DIARIA!J5+CARGA_DIARIA!K5+CARGA_DIARIA!L5+CARGA_DIARIA!M5+CARGA_DIARIA!N5+CARGA_DIARIA!O5+CARGA_DIARIA!P5+CARGA_DIARIA!Q5+CARGA_DIARIA!R5+CARGA_DIARIA!S5+CARGA_DIARIA!T5+CARGA_DIARIA!U5+CARGA_DIARIA!V5+CARGA_DIARIA!W5)/CARGA_DIARIA!B5) -> 0 | E5: =IF(CARGA_DIARIA!B5=0,0,(CARGA_DIARIA!X5+CARGA_DIARIA!Y5+CARGA_DIARIA!Z5+CARGA_DIARIA!AA5)/CARGA_DIARIA!B5+CARGA_DIARIA!AB5+CARGA_DIARIA!AC5+CARGA_DIARIA!AD5+CARGA_DIARIA!AE5) -> 0 | H5: =C5-D5-E5 -> 0
A6: =CARGA_DIARIA!A6 -> 0 | B6: =CARGA_DIARIA!B6 -> 0 | C6: =IF(CARGA_DIARIA!B6=0,0,(CARGA_DIARIA!C6+CARGA_DIARIA!D6+CARGA_DIARIA!E6+CARGA_DIARIA!F6+CARGA_DIARIA!G6+CARGA_DIARIA!H6+CARGA_DIARIA!I6+CARGA_DIARIA!AG6+CARGA_DIARIA!AH6+CARGA_DIARIA!AI6+CARGA_DIARIA!AJ6)/CARGA_DIARIA!B6+CARGA_DIARIA!AF6) -> 0 | D6: =IF(CARGA_DIARIA!B6=0,0,(CARGA_DIARIA!J6+CARGA_DIARIA!K6+CARGA_DIARIA!L6+CARGA_DIARIA!M6+CARGA_DIARIA!N6+CARGA_DIARIA!O6+CARGA_DIARIA!P6+CARGA_DIARIA!Q6+CARGA_DIARIA!R6+CARGA_DIARIA!S6+CARGA_DIARIA!T6+CARGA_DIARIA!U6+CARGA_DIARIA!V6+CARGA_DIARIA!W6)/CARGA_DIARIA!B6) -> 0 | E6: =IF(CARGA_DIARIA!B6=0,0,(CARGA_DIARIA!X6+CARGA_DIARIA!Y6+CARGA_DIARIA!Z6+CARGA_DIARIA!AA6)/CARGA_DIARIA!B6+CARGA_DIARIA!AB6+CARGA_DIARIA!AC6+CARGA_DIARIA!AD6+CARGA_DIARIA!AE6) -> 0 | H6: =C6-D6-E6 -> 0
A7: =CARGA_DIARIA!A7 -> 0 | B7: =CARGA_DIARIA!B7 -> 0 | C7: =IF(CARGA_DIARIA!B7=0,0,(CARGA_DIARIA!C7+CARGA_DIARIA!D7+CARGA_DIARIA!E7+CARGA_DIARIA!F7+CARGA_DIARIA!G7+CARGA_DIARIA!H7+CARGA_DIARIA!I7+CARGA_DIARIA!AG7+CARGA_DIARIA!AH7+CARGA_DIARIA!AI7+CARGA_DIARIA!AJ7)/CARGA_DIARIA!B7+CARGA_DIARIA!AF7) -> 0 | D7: =IF(CARGA_DIARIA!B7=0,0,(CARGA_DIARIA!J7+CARGA_DIARIA!K7+CARGA_DIARIA!L7+CARGA_DIARIA!M7+CARGA_DIARIA!N7+CARGA_DIARIA!O7+CARGA_DIARIA!P7+CARGA_DIARIA!Q7+CARGA_DIARIA!R7+CARGA_DIARIA!S7+CARGA_DIARIA!T7+CARGA_DIARIA!U7+CARGA_DIARIA!V7+CARGA_DIARIA!W7)/CARGA_DIARIA!B7) -> 0 | E7: =IF(CARGA_DIARIA!B7=0,0,(CARGA_DIARIA!X7+CARGA_DIARIA!Y7+CARGA_DIARIA!Z7+CARGA_DIARIA!AA7)/CARGA_DIARIA!B7+CARGA_DIARIA!AB7+CARGA_DIARIA!AC7+CARGA_DIARIA!AD7+CARGA_DIARIA!AE7) -> 0 | H7: =C7-D7-E7 -> 0
A8: =CARGA_DIARIA!A8 -> 0 | B8: =CARGA_DIARIA!B8 -> 0 | C8: =IF(CARGA_DIARIA!B8=0,0,(CARGA_DIARIA!C8+CARGA_DIARIA!D8+CARGA_DIARIA!E8+CARGA_DIARIA!F8+CARGA_DIARIA!G8+CARGA_DIARIA!H8+CARGA_DIARIA!I8+CARGA_DIARIA!AG8+CARGA_DIARIA!AH8+CARGA_DIARIA!AI8+CARGA_DIARIA!AJ8)/CARGA_DIARIA!B8+CARGA_DIARIA!AF8) -> 0 | D8: =IF(CARGA_DIARIA!B8=0,0,(CARGA_DIARIA!J8+CARGA_DIARIA!K8+CARGA_DIARIA!L8+CARGA_DIARIA!M8+CARGA_DIARIA!N8+CARGA_DIARIA!O8+CARGA_DIARIA!P8+CARGA_DIARIA!Q8+CARGA_DIARIA!R8+CARGA_DIARIA!S8+CARGA_DIARIA!T8+CARGA_DIARIA!U8+CARGA_DIARIA!V8+CARGA_DIARIA!W8)/CARGA_DIARIA!B8) -> 0 | E8: =IF(CARGA_DIARIA!B8=0,0,(CARGA_DIARIA!X8+CARGA_DIARIA!Y8+CARGA_DIARIA!Z8+CARGA_DIARIA!AA8)/CARGA_DIARIA!B8+CARGA_DIARIA!AB8+CARGA_DIARIA!AC8+CARGA_DIARIA!AD8+CARGA_DIARIA!AE8) -> 0 | H8: =C8-D8-E8 -> 0
A9: Promedio período | C9: =IFERROR(AVERAGE(C4:C8),"-") -> 5393439.9 | D9: =IFERROR(AVERAGE(D4:D8),"-") -> 81031.849 | E9: =IFERROR(AVERAGE(E4:E8),"-") -> 3767237.5 | F9: — | G9: — | H9: =IFERROR(AVERAGE(H4:H8),"-") -> 1545170.6

Sheet VENCIMIENTOS
A1: VENCIMIENTOS — Cheques a cobrar y compromisos de pago próximos
A2: Ingresá cada cheque o compromiso con su fecha exacta. El dashboard lo muestra en el calendario de vencimientos.
A3: Fecha | B3: Tipo | C3: Descripción / Contraparte | D3: Monto (ARS) | E3: TC del día | F3: Monto (USD) | G3: Estado
A4: 46148 | B4: COBRO | C4: Cheque acreditación — Cliente Norte | D4: 42000000 | E4: 1197 | F4: =IFERROR(D4/E4,0) -> 35087.719 | G4: Pendiente
A5: 46149 | B5: PAGO | C5: Proveedor Pescadores del Sur | D5: 87000000 | E5: 1197 | F5: =IFERROR(D5/E5,0) -> 72681.704 | G5: Pendiente
A6: 46150 | B6: COBRO | C6: Cheque — Distribuidora Atlántica | D6: 65000000 | E6: 1197 | F6: =IFERROR(D6/E6,0) -> 54302.423 | G6: Pendiente
A7: 46151 | B7: PAGO | C7: Cuota préstamo Banco Galicia | D7: 48500000 | E7: 1197 | F7: =IFERROR(D7/E7,0) -> 40517.962 | G7: Pendiente
A8: 46152 | B8: COBRO | C8: Cobro exportación (USD 95.000) | D8: 113715000 | E8: 1197 | F8: =IFERROR(D8/E8,0) -> 95000 | G8: Pendiente
A9: 46152 | B9: PAGO | C9: RRHH — sueldos quincena | D9: 96000000 | E9: 1197 | F9: =IFERROR(D9/E9,0) -> 80200.501 | G9: Pendiente
A10: 46154 | B10: PAGO | C10: Arancel / canon mensual | D10: 23000000 | E10: 1197 | F10: =IFERROR(D10/E10,0) -> 19214.703 | G10: Pendiente
A11: 46157 | B11: COBRO | C11: Cheque — Exportadora Patagónica | D11: 145000000 | E11: 1197 | F11: =IFERROR(D11/E11,0) -> 121136.17 | G11: Pendiente
A12: 46162 | B12: PAGO | C12: Deuda proveedor exterior (USD 80.000) | D12: 95760000 | E12: 1197 | F12: =IFERROR(D12/E12,0) -> 80000 | G12: Pendiente

Sheet DIVISAS
A1: DIVISAS DISPONIBLES — Seguimiento diario de posición en USD
A2: Fecha | B2: TC BNA | C2: Patag. (USD) | D2: Francés (USD) | E2: Total USD | F2: Liquidado hoy (USD)
A3: 46140 | B3: 1194 | C3: 285000 | D3: 140000 | E3: =C3+D3 -> 425000 | F3: 87000
A4: 46141 | B4: 1196 | C4: 268000 | D4: 135000 | E4: =C4+D4 -> 403000 | F4: 72000
A5: 46142 | B5: 1197 | C5: 301000 | D5: 148000 | E5: =C5+D5 -> 449000 | F5: 95000
A6: 46144 | B6: 1198.5 | C6: 275000 | D6: 128000 | E6: =C6+D6 -> 403000 | F6: 68000
A7: 46147 | B7: 1197 | C7: 285000 | D7: 140000 | E7: =C7+D7 -> 425000 | F7: 87000

Sheet CREDITOS_EXTERIOR
A1: CRÉDITOS POR VENTAS AL EXTERIOR — Facturas de exportación pendientes de cobro
A2: N° Factura | B2: Cliente (País) | C2: Fecha Factura | D2: Fecha Vto. | E2: Días al vto. | F2: Monto (USD) | G2: TC estimado | H2: ARS equivalente | I2: Estado
A3: EXP-2026-041 | B3: Nordic Fish AS (Noruega) | C3: 46096 | D3: 46157 | E3: =IFERROR(D3-TODAY(),"") -> 9 | F3: 320000 | G3: 1197 | H3: =IFERROR(F3*G3,0) -> 383040000 | I3: Pendiente
A4: EXP-2026-055 | B4: Iberian Seafood SL (España) | C4: 46113 | D4: 46172 | E4: =IFERROR(D4-TODAY(),"") -> 24 | F4: 185000 | G4: 1197 | H4: =IFERROR(F4*G4,0) -> 221445000 | I4: Pendiente
A5: EXP-2026,062 | B5: Ocean Trade LLC (EEUU) | C5: 46122 | D5: 46183 | E5: =IFERROR(D5-TODAY(),"") -> 35 | F5: 240000 | G5: 1197 | H5: =IFERROR(F5*G5,0) -> 287280000 | I5: Pendiente
A6: EXP-2026-071 | B6: Maruha Nichiro (Japón) | C6: 46132 | D6: 46193 | E6: =IFERROR(D6-TODAY(),"") -> 45 | F6: 495000 | G6: 1197 | H6: =IFERROR(F6*G6,0) -> 592515000 | I6: Pendiente
