Workbook

Sheet INSTRUCCIONES
A1: DASHBOARD FINANCIERO — EMPRESA PESQUERA
A2: Guía de uso y estructura del archivo
A6: 📋 ESTRUCTURA DEL ARCHIVO
A7: Hoja | B7: Descripción
A8: INSTRUCCIONES | B8: Esta hoja — guía de uso
A9: CARGA_DIARIA | B9: Acá cargás los datos todos los días (una fila por día)
A10: ACTIVO_CORRIENTE | B10: Desglose diario de activos: bancos, cheques, divisas, créditos, FCI
A11: GASTOS_DIARIOS | B11: Detalle de egresos por sector (13 categorías)
A12: PASIVO_CORRIENTE | B12: Compromisos y deudas a corto plazo
A13: VENCIMIENTOS | B13: Cheques a cobrar y pagar en los próximos 30 días
A14: AJUSTES | B14: Stock a precio de venta, posición fiscal, otras deudas
A15: POSICION_NETA | B15: Hoja de cálculo automática — no modificar
A17: 🎨 CONVENCIÓN DE COLORES
A18: Color | B18: Significado
A19: Texto AZUL | B19: Dato a ingresar manualmente (input)
A20: Texto NEGRO | B20: Fórmula calculada automáticamente — no modificar
A21: Texto VERDE | B21: Vínculo a otra hoja del mismo archivo
A22: Fondo AMARILLO | B22: Celda importante que requiere atención o actualización
A24: 📌 INSTRUCCIONES DE CARGA DIARIA
A25: 1. | B25: Abrir la hoja CARGA_DIARIA
A26: 2. | B26: Ir a la última fila con datos e insertar una nueva fila debajo
A27: 3. | B27: Ingresar la fecha del día en la columna A (formato DD/MM/AAAA)
A28: 4. | B28: Ingresar el tipo de cambio BNA del día en la columna B
A29: 5. | B29: Completar el resto de columnas con los valores en PESOS del día
A30: 6. | B30: Los valores en USD se calculan automáticamente dividiendo por el TC
A31: 7. | B31: La hoja POSICION_NETA se actualiza automáticamente
A33: ⚠️ IMPORTANTE
A34: • | B34: No eliminar ni mover filas de encabezado
A35: • | B35: No modificar las hojas de fórmulas (POSICION_NETA)
A36: • | B36: Siempre cargar valores en PESOS — el dashboard convierte a USD
A37: • | B37: Los cheques en cartera cargar en hoja VENCIMIENTOS con fecha de acreditación
A38: • | B38: Guardar el archivo con Ctrl+S después de cada carga

Sheet CARGA_DIARIA
A1: CARGA DIARIA — POSICIÓN FINANCIERA | Valores en PESOS argentinos (ARS)
A2: FECHA | B2: TIPO DE CAMBIO BNA (ARS/USD) | C2: ACTIVO CORRIENTE (ARS) | J2: GASTOS DEL DÍA POR SECTOR (ARS) | W2: PASIVO CORRIENTE (ARS)
A3: Fecha | B3: TC BNA (ARS/USD) | C3: Efectivo (MI) | D3: Cheques en cartera | E3: Banco Patagonia | F3: Banco Galicia | G3: Banco Francés | H3: Banco Santander | I3: Créditos MI | J3: Proveedores | K3: Aranceles y Cánones | L3: Comercio Exterior | M3: Directores / Accionistas | N3: Empresas del Grupo | O3: Gastos de Buques | P3: Impuestos y Tasas | Q3: RRHH | R3: Servicios Varios | S3: Retiros Particulares | T3: Pago Importaciones | U3: Compra Dólares (CCL) | V3: Pago Préstamos | W3: Otros Gastos | X3: Cheques Emitidos | Y3: Gs. Presup. Próximos | Z3: Préstamos ML (ARS) | AA3: Deuda Proveed. MI | AB3: Deuda Proveed. Ext. (USD) | AC3: Préstamos ME (USD) | AD3: Intereses Proy. (USD) | AE3: Otras Deudas (USD) | AF3: Stock a Precio Venta (USD) | AG3: Posición Fiscal | AH3: Divisas Disp. (ARS eq.) | AI3: Créditos Exterior (ARS eq.) | AJ3: Inversiones FCI
A4: 46029 | B4: 1463 | C4: 0 | D4: 147143953 | E4: -17312000 | F4: 0 | G4: 5368000 | H4: 6913000 | I4: 984848664 | J4: 93118000 | K4: 0 | L4: 0 | M4: 0 | N4: 0 | O4: 0 | P4: 0 | Q4: 331346284 | R4: 0 | S4: 0 | T4: 0 | U4: 0 | V4: 0 | W4: 0 | X4: 396177166 | Y4: 2543380519 | Z4: 220357000 | AA4: 4106866784 | AB4: 2600000 | AC4: 6975000 | AD4: 159934 | AE4: 2044803 | AF4: 6441928 | AG4: 4314967894 | AH4: 6208398504 | AI4: 4836302009 | AJ4: 1972327480
A5: 46030 | B5: 1469 | C5: 0 | D5: 1.4714395e+08 | E5: 103831332 | F5: 0 | G5: 24804818 | H5: 3794000 | I5: 1127668632 | J5: 98556000 | K5: 0 | L5: 0 | M5: 0 | N5: 0 | O5: 0 | P5: 366732120 | Q5: 3010892.1 | R5: 0 | S5: 0 | T5: 45929347 | U5: 0 | V5: 0 | W5: 0 | X5: 3.4308383e+08 | Y5: 2493689353 | Z5: 220357000 | AA5: 4094188807 | AB5: 2600000 | AC5: 6975000 | AD5: 159934 | AE5: 2044803 | AF5: 6480455 | AG5: 4314967894 | AH5: 6110180635 | AI5: 4816967051 | AJ5: 422641035
A6: 46031 | B6: 1455 | C6: 0 | D6: 102302314 | E6: 63095000 | F6: 0 | G6: 14747000 | H6: 12301000 | I6: 996009122 | J6: 2347817 | K6: 0 | L6: 0 | M6: 0 | N6: 0 | O6: 0 | P6: 126421132 | Q6: 7044405 | R6: 0 | S6: 0 | T6: 0 | U6: 0 | V6: 0 | W6: 0 | X6: 5.0635025e+08 | Y6: 1113182008 | Z6: 220357000 | AA6: 4182158189 | AB6: 2600000 | AC6: 6975000 | AD6: 159934 | AE6: 2044803 | AF6: 7740751.2 | AG6: 4314967894 | AH6: 5581783035 | AI6: 4658234880 | AJ6: 422947645
A7: 46034 | B7: 1465.5 | C7: 0 | D7: 1.9119589e+08 | E7: 19902000 | F7: 0 | G7: 1103000 | H7: 309000 | I7: 1129839976 | J7: 38460000 | K7: 0 | L7: 23625223 | M7: 0 | N7: 0 | O7: 0 | P7: 109006535 | Q7: 224149787 | R7: 0 | S7: 0 | T7: 0 | U7: 0 | V7: 0 | W7: 0 | X7: 717079149 | Y7: 944499841 | Z7: 220357000 | AA7: 4087351389 | AB7: 2600000 | AC7: 6975000 | AD7: 159934 | AE7: 2344803 | AF7: 8315409 | AG7: 4314967894 | AH7: 4.4868554e+09 | AI7: 4988005110 | AJ7: 423827578
A8: 46035 | B8: 1462 | C8: 0 | D8: 191195891 | E8: 41915000 | F8: 0 | G8: 15637889 | H8: 0 | I8: 1129839976 | J8: 167756834 | K8: 0 | L8: 39116189 | M8: 0 | N8: 0 | O8: 0 | P8: 15121860 | Q8: 180946598 | R8: 0 | S8: 0 | T8: 0 | U8: 0 | V8: 0 | W8: 0 | X8: 828454859 | Y8: 705798673 | Z8: 220357000 | AA8: 3882411723 | AB8: 2600000 | AC8: 6975000 | AD8: 159934 | AE8: 2344803 | AF8: 8965227.5 | AG8: 4314967894 | AH8: 4284443632 | AI8: 4.7138135e+09 | AJ8: 424124427
A9: 46036 | B9: 1464.5 | C9: 0 | D9: 62480863 | E9: 60536771 | F9: 0 | G9: 25159457 | H9: 0 | I9: 1143603954 | J9: 170000000 | K9: 0 | L9: 0 | M9: 0 | N9: 0 | O9: 0 | P9: 0 | Q9: 183177718 | R9: 0 | S9: 0 | T9: 0 | U9: 0 | V9: 0 | W9: 0 | X9: 938129312 | Y9: 569683193 | Z9: 220357000 | AA9: 3764632228 | AB9: 2600000 | AC9: 6975000 | AD9: 159934 | AE9: 2344803 | AF9: 8783530.6 | AG9: 4314967894 | AH9: 4.0926902e+09 | AI9: 4.672764e+09 | AJ9: 424459423
A10: 46037 | B10: 1450 | C10: 0 | D10: 62480863 | E10: 74751000 | F10: 0 | G10: 9758000 | H10: 0 | I10: 1214275683 | J10: 276864200 | K10: 0 | L10: 1009800 | M10: 0 | N10: 0 | O10: 0 | P10: 0 | Q10: 10591254 | R10: 0 | S10: 0 | T10: 0 | U10: 194000000 | V10: 0 | W10: 0 | X10: 7.6483029e+08 | Y10: 604673438 | Z10: 220357000 | AA10: 3766894667 | AB10: 2600000 | AC10: 6975000 | AD10: 159934 | AE10: 2344803 | AF10: 8886136.3 | AG10: 4314967894 | AH10: 4231934388 | AI10: 4759593100 | AJ10: 1.9461029e+08
A11: 46038 | B11: 1440 | C11: 0 | D11: 170748138 | E11: 164880000 | F11: 0 | G11: -3450000 | H11: 0 | I11: 1096607000 | J11: 1.8091383e+08 | K11: 0 | L11: 2919605 | M11: 0 | N11: 0 | O11: 0 | P11: 7054822 | Q11: 3191483 | R11: 0 | S11: 0 | T11: 0 | U11: 0 | V11: 0 | W11: 0 | X11: 995710009 | Y11: 487074663 | Z11: 220357000 | AA11: 3172758684 | AB11: 2600000 | AC11: 6975000 | AD11: 159934 | AE11: 2344803 | AF11: 9582201.9 | AG11: 4314967894 | AH11: 4.0730687e+09 | AI11: 4577526720 | AJ11: 611311.33
A12: 46041 | B12: 1428 | C12: 0 | D12: 170748138 | E12: 176500595 | F12: 0 | G12: 9812921 | H12: 0 | I12: 1098875342 | J12: 93270575 | K12: 0 | L12: 30686642 | M12: 0 | N12: 0 | O12: 0 | P12: 0 | Q12: 2786622 | R12: 106064322 | S12: 0 | T12: 0 | U12: 0 | V12: 0 | W12: 0 | X12: 727601822 | Y12: 55545741 | Z12: 220357000 | AA12: 3286079509 | AB12: 2600000 | AC12: 6975000 | AD12: 159934 | AE12: 2194803 | AF12: 10991009 | AG12: 4314967894 | AH12: 3.6198033e+09 | AI12: 4647360312 | AJ12: 612693
A13: 46042 | B13: 1428.5 | C13: 0 | D13: 1.3831084e+08 | E13: 73444051 | F13: 0 | G13: 15092051 | H13: 0 | I13: 1039256943 | J13: 173300000 | K13: 0 | L13: 0 | M13: 0 | N13: 0 | O13: 0 | P13: 0 | Q13: 157286696 | R13: 0 | S13: 0 | T13: 0 | U13: 180000000 | V13: 0 | W13: 0 | X13: 763073132 | Y13: 801275230 | Z13: 220357000 | AA13: 3.2430649e+09 | AB13: 2600000 | AC13: 6975000 | AD13: 159934 | AE13: 2194803 | AF13: 11490332 | AG13: 4314967894 | AH13: 3.5524671e+09 | AI13: 4648987539 | AJ13: 613144.98
A14: 46043 | B14: 1432 | C14: 0 | D14: 1.1489068e+08 | E14: 84544429 | F14: 0 | G14: 8979855 | H14: 0 | I14: 1039256943 | J14: 107253172 | K14: 0 | L14: 27735508 | M14: 0 | N14: 0 | O14: 43586760 | P14: 144447864 | Q14: 37176621 | R14: 0 | S14: 0 | T14: 0 | U14: 0 | V14: 0 | W14: 0 | X14: 759957476 | Y14: 624555549 | Z14: 220357000 | AA14: 3592955206 | AB14: 2600000 | AC14: 6975000 | AD14: 159934 | AE14: 2194803 | AF14: 12252881 | AG14: 4314967894 | AH14: 3.5743475e+09 | AI14: 4087129912 | AJ14: 613592.34
A15: 46044 | B15: 1427 | C15: 0 | D15: 61294019 | E15: 4.0495235e+08 | F15: 0 | G15: 8492957.3 | H15: 4032000 | I15: 1039256943 | J15: 133501600 | K15: 0 | L15: 80264892 | M15: 0 | N15: 0 | O15: 0 | P15: 19105502 | Q15: 1046236 | R15: 176000 | S15: 0 | T15: 0 | U15: 0 | V15: 0 | W15: 0 | X15: 6.8531777e+08 | Y15: 570093319 | Z15: 220357000 | AA15: 3.5088838e+09 | AB15: 2600000 | AC15: 6975000 | AD15: 159934 | AE15: 2194803 | AF15: 12482991 | AG15: 4314967894 | AH15: 3.4281362e+09 | AI15: 4072859207 | AJ15: 614057
... A82: 46149 | B82: 1383 | C82: 0 | D82: 1004100985 | E82: 56178000 | F82: 13243000 | G82: 4270000 | H82: 2000000 | I82: 1586995953 | J82: 0 | K82: 0 | L82: 0 | M82: 0 | N82: 0 | O82: 0 | P82: 0 | Q82: 0 | R82: 0 | S82: 0 | T82: 0 | U82: 0 | V82: 0 | W82: 0 | X82: 1.2373028e+09 | Y82: 2896014463 | Z82: 2.0273466e+08 | AA82: 7174765725 | AB82: 1196248.6 | AC82: 9000000 | AD82: 141199.47 | AE82: 280000 | AF82: 12657304 | AG82: 5582721359 | AH82: 2731278746 | AI82: 8858339046 | AJ82: 102471144
A83: 46150 | B83: 1388 | D83: 1026676615 | E83: 160451000 | F83: 50895000 | G83: 2169000 | H83: 1428000 | I83: 1617879590 | J83: 284346273 | L83: 204023840 | P83: 2425645 | Q83: 13418493 | X83: 1738503267 | Y83: 2698378718 | Z83: 2.0273466e+08 | AA83: 6689223249 | AB83: 1196248.6 | AC83: 9000000 | AD83: 141199.47 | AE83: 280000 | AF83: 12737370 | AG83: 5582721359 | AH83: 2088518048 | AI83: 8890364856 | AJ83: 90511582
A84: 46153 | B84: 1389 | D84: 1026676615 | E84: 177905205 | F84: 26207670 | G84: -42250000 | H84: 2000000 | I84: 1897154988 | J84: 60206933 | K84: 86098436 | L84: 46609610 | P84: 49239273 | Q84: 1226584509 | R84: 4462000 | X84: 1697009243 | Y84: 1215298412 | Z84: 2.0273466e+08 | AA84: 6649944967 | AB84: 1196248.6 | AC84: 10000000 | AD84: 141199.47 | AE84: 280000 | AF84: 12946008 | AG84: 5582721359 | AH84: 2272274354 | AI84: 9463757040 | AJ84: 90663001
A85: 46154 | B85: 1391 | D85: 1026676615 | E85: -39733000 | F85: 54938000 | G85: 7516000 | H85: 2000000 | I85: 1897154988 | J85: 350881600 | O85: 4687440 | Q85: 119797908 | X85: 2193914554 | Y85: 1224485195 | Z85: 2.0273466e+08 | AA85: 5996923699 | AB85: 1100365 | AC85: 10000000 | AD85: 141199.47 | AE85: 280000 | AF85: 12953742 | AG85: 5582721359 | AH85: 2.5270541e+09 | AI85: 9477383760 | AJ85: 90673439
A86: 46155 | B86: 1382.5 | D86: 1049061340 | E86: 82398000 | F86: 238635000 | G86: 5524000 | H86: 2000000 | I86: 1871991100 | J86: 194004331 | L86: 6881904 | P86: 4499179 | Q86: 298337009 | U86: 120000000 | X86: 1951558798 | Y86: 991611113 | Z86: 2.0273466e+08 | AA86: 6063339939 | AB86: 1100365 | AC86: 10000000 | AD86: 141199.47 | AE86: 280000 | AF86: 12416677 | AG86: 5582721359 | AH86: 2.3394629e+09 | AI86: 9419470200 | AJ86: 140735000
A87: 46156 | B87: 1386 | D87: =+'[1]CF Dia V1'!$CJ$10 -> 837432835 | E87: =+'[1]CF Dia V1'!$CJ$13 -> 78949000 | F87: =+'[1]CF Dia V1'!$CJ$16 -> 45656000 | G87: =+'[1]CF Dia V1'!$CJ$14 -> 5783000 | H87: =+'[1]CF Dia V1'!$CJ$15 -> 2000000 | I87: =+'[1]CF Dia V1'!$CJ$22 -> 1740123570 | J87: =+'[1]CF Dia V1'!$CJ$43 -> 458483114 | K87: =+'[1]CF Dia V1'!$CJ$45 -> 0 | L87: =+'[1]CF Dia V1'!$CJ$46 -> 14376000 | M87: =+'[1]CF Dia V1'!$CJ$47 -> 0 | N87: =+'[1]CF Dia V1'!$CJ$48 -> 0 | O87: =+'[1]CF Dia V1'!$CJ$49 -> 0 | P87: =+'[1]CF Dia V1'!$CJ$50 -> 0 | Q87: =+'[1]CF Dia V1'!$CJ$51 -> 6873443 | R87: =+'[1]CF Dia V1'!$CJ$53 -> 0 | S87: =+'[1]CF Dia V1'!$CJ$56 -> 0 | T87: =+'[1]CF Dia V1'!$CJ$59 -> 0 | U87: =+'[1]CF Dia V1'!$CJ$60 -> 30000000 | V87: =+'[1]CF Dia V1'!$CJ$68 -> 0 | W87: =+'[1]CF Dia V1'!$CJ$61 -> 0 | X87: =+'[1]CF Dia V1'!$CJ$100 -> 1689393489 | Y87: =+'[1]CF Dia V1'!$CJ$101 -> 990744710 | Z87: =+'[1]CF Dia V1'!$CJ$104 -> 2.0273466e+08 | AA87: =+'[1]CF Dia V1'!$CJ$102 -> 6063777655 | AB87: =+'[1]CF Dia V1'!$CJ$103 -> 1100365 | AC87: =+'[1]CF Dia V1'!$CJ$105 -> 10000000 | AD87: =+'[1]CF Dia V1'!$CJ$106 -> 141199.47 | AE87: =+'[1]CF Dia V1'!$CJ$107 -> 280000 | AF87: =+'[1]CF Dia V1'!$CJ$97 -> 7845303 | AG87: =+'[1]CF Dia V1'!$CJ$98 -> 5582721359 | AH87: =+'[1]CF Dia V1'!$CJ$24+'[1]CF Dia V1'!$CJ$25 -> 3.5648957e+09 | AI87: =+'[1]CF Dia V1'!$CJ$29 -> 8574762042 | AJ87: =+'[1]CF Dia V1'!$CJ$31 -> 1.4029793e+08
A88: 46157 | B88: 1392 | D88: =+'[1]CF Dia V1'!$CK$10 -> 850726335 | E88: =+'[1]CF Dia V1'!$CK$13 -> 55135000 | F88: =+'[1]CF Dia V1'!$CK$16 -> 35083000 | G88: =+'[1]CF Dia V1'!$CK$14 -> 6687413 | H88: =+'[1]CF Dia V1'!$CK$15 -> 2000000 | I88: =+'[1]CF Dia V1'!$CK$22 -> 1726830070 | J88: =+'[1]CF Dia V1'!$CK$43 -> 661233493 | L88: =+'[1]CF Dia V1'!$CK$46 -> 9499387 | P88: =+'[1]CF Dia V1'!$CK$50 -> 9401592 | Q88: =+'[1]CF Dia V1'!$CK$51 -> 10840885 | X88: =+'[1]CF Dia V1'!$CK$100 -> 1583396236 | Y88: =+'[1]CF Dia V1'!$CK$101 -> 771360669 | Z88: =+'[1]CF Dia V1'!$CK$104 -> 2.0273466e+08 | AA88: =+'[1]CF Dia V1'!$CK$102 -> 5851473775 | AB88: =+'[1]CF Dia V1'!$CK$103 -> 1100365 | AC88: =+'[1]CF Dia V1'!$CK$105 -> 10000000 | AD88: 220000 | AE88: =+'[1]CF Dia V1'!$CK$107 -> 280000 | AF88: =+'[1]CF Dia V1'!$CK$97 -> 6352071 | AG88: =+'[1]CF Dia V1'!$CK$98 -> 5582721359 | AH88: =+'[1]CF Dia V1'!$CK$24+'[1]CF Dia V1'!$CK$25 -> 3.3216693e+09 | AI88: =+'[1]CF Dia V1'!$CK$29 -> 8569053168 | AJ88: =+'[1]CF Dia V1'!$CK$31 -> 170372226
A89: 46160 | B89: 1392.5 | D89: 958457035 | E89: 52780000 | F89: 11055319 | G89: 6146000 | H89: =+'[1]CF Dia V1'!$CK$15 -> 2000000 | I89: 1635289293 | J89: 267891646 | P89: 45594750 | Q89: 76176394 | U89: 100000000 | X89: 1537867977 | Y89: 695105278 | Z89: =+'[1]CF Dia V1'!$CK$104 -> 2.0273466e+08 | AA89: 5792810924 | AB89: 1048306.4 | AC89: 10000000 | AD89: 220000 | AE89: 280000 | AF89: 11256611 | AG89: =+'[1]CF Dia V1'!$CK$98 -> 5582721359 | AH89: =+'[1]CF Dia V1'!$CL$24+'[1]CF Dia V1'!$CL$25 -> 2.8193139e+09 | AI89: =+'[1]CF Dia V1'!$CL$29 -> 9272841310 | AJ89: =+'[1]CF Dia V1'!$CL$31 -> 1.8661942e+08
A90: 46161 | B90: 1390 | D90: 1007436112 | E90: 57028000 | F90: 256616000 | G90: 25612301 | H90: 2000000 | I90: 1583330883 | J90: =+'[1]CF Dia V1'!$CM$43 -> 345281349 | L90: =+'[1]CF Dia V1'!$CM$46 -> 8048613 | Q90: =+'[1]CF Dia V1'!$CM$51 -> 77515155 | U90: 30000000 | X90: 2531313482 | Y90: 824238787 | Z90: =+Z89 -> 2.0273466e+08 | AA90: 6003601474 | AB90: =+AB89 -> 1048306.4 | AC90: 10000000 | AD90: 220000 | AE90: 280000 | AF90: 9237646.3 | AG90: =+AG89 -> 5582721359 | AH90: =+'[1]CF Dia V1'!$CM$24+'[1]CF Dia V1'!$CM$25 -> 2.7330969e+09 | AI90: =+'[1]CF Dia V1'!$CM$29 -> 9256193480 | AJ90: =+'[1]CF Dia V1'!$CM$31 -> 186701425
A91: =+'[1]CF Dia V1'!$CN$1 -> 46162 | B91: =+'[1]CF Dia V1'!$CN$2 -> 1395.5 | D91: =+'[1]CF Dia V1'!$CN$10 -> 747534542 | E91: =+'[1]CF Dia V1'!$CN$13 -> 209536000 | F91: =+'[1]CF Dia V1'!$CN$16 -> 1.5237856e+08 | G91: =+'[1]CF Dia V1'!$CN$14 -> 60202000 | H91: =+'[1]CF Dia V1'!$CN$15 -> 2000000 | I91: =+'[1]CF Dia V1'!$CN$22 -> 1628502061 | J91: =+'[1]CF Dia V1'!$CN$43 -> 434891710 | L91: =+'[1]CF Dia V1'!$CN$46 -> 0 | O91: =+'[1]CF Dia V1'!$CN$50 -> 8039538 | U91: =+'[1]CF Dia V1'!$CN$60 -> 110000000 | X91: =+'[1]CF Dia V1'!$CN$100 -> 2211799335 | Y91: =+'[1]CF Dia V1'!$CN$101 -> 886288208 | Z91: =+Z90 -> 2.0273466e+08 | AA91: =+'[1]CF Dia V1'!$CN$102 -> 6003847969 | AB91: =+AB90 -> 1048306.4 | AC91: =+AC90 -> 10000000 | AD91: =+AD90 -> 220000 | AE91: =+AE90 -> 280000 | AF91: =+'[1]CF Dia V1'!$CN$97 -> 6348809 | AG91: =+AG90 -> 5582721359 | AH91: =+'[1]CF Dia V1'!$CN$24+'[1]CF Dia V1'!$CN$25 -> 2.9791712e+09 | AI91: =+'[1]CF Dia V1'!$CN$29 -> 9.0989265e+09 | AJ91: =+'[1]CF Dia V1'!$CN$31 -> 1.8678328e+08
A92: =+'[1]CF Dia V1'!$CO$1 -> 46163 | B92: =+B91 -> 1395.5 | D92: =+'[1]CF Dia V1'!$CO$10 -> 935271863 | E92: =+'[1]CF Dia V1'!$CO$13 -> 164501000 | F92: =+'[1]CF Dia V1'!$CO$16 -> 109500000 | G92: =+'[1]CF Dia V1'!$CO$14 -> 9150000 | H92: =+H91 -> 2000000 | I92: =+'[1]CF Dia V1'!$CO$22 -> 1642654898 | J92: =+'[1]CF Dia V1'!$CO$43 -> 327757232 | L92: =+'[1]CF Dia V1'!$CO$46 -> 0 | O92: =+'[1]CF Dia V1'!$CO$49 -> 85437900 | P92: =+'[1]CF Dia V1'!$CO$50 -> 59668977 | Q92: =+'[1]CF Dia V1'!$CO$51 -> 80898077 | X92: =+'[1]CF Dia V1'!$CO$100 -> 2022241225 | Y92: =+'[1]CF Dia V1'!$CO$101 -> 821747346 | Z92: =+Z91 -> 2.0273466e+08 | AA92: =+'[1]CF Dia V1'!$CO$102 -> 6263281746 | AB92: =+AB91 -> 1048306.4 | AC92: =+AC91 -> 10000000 | AD92: =+AD91 -> 220000 | AE92: =+AE91 -> 280000 | AF92: =+'[1]CF Dia V1'!$CO$97 -> 5162809 | AG92: =+AG91 -> 5582721359 | AH92: =+'[1]CF Dia V1'!$CO$24+'[1]CF Dia V1'!$CO$25 -> 2.8774722e+09 | AI92: =+'[1]CF Dia V1'!$CO$29 -> 9.0989265e+09 | AJ92: =+'[1]CF Dia V1'!$CO$31 -> 1.8687428e+08
A93: =+'[1]CF Dia V1'!$CP$1 -> 46164 | B93: =+'[1]CF Dia V1'!$CP$2 -> 1390 | D93: =+'[1]CF Dia V1'!$CP$10 -> 901607908 | E93: =+'[1]CF Dia V1'!$CP$13 -> -12018000 | F93: =+'[1]CF Dia V1'!$CP$16 -> 31400000 | G93: =+'[1]CF Dia V1'!$CP$14 -> 9062000 | H93: =+'[1]CF Dia V1'!$CP$15 -> 2876000 | I93: =+'[1]CF Dia V1'!$CP$22 -> 1143093119 | J93: =+'[1]CF Dia V1'!$CP$43 -> 350616029 | L93: =+'[1]CF Dia V1'!$CP$46 -> 0 | O93: =+'[1]CF Dia V1'!$CP$49 -> 948120 | P93: =+'[1]CF Dia V1'!$CP$50 -> 21504816 | Q93: =+'[1]CF Dia V1'!$CP$51 -> 271146305 | X93: =+'[1]CF Dia V1'!$CP$100 -> 2.2309233e+09 | Y93: =+'[1]CF Dia V1'!$CP$101 -> 970095427 | Z93: =+'[1]CF Dia V1'!$CP$104 -> 2.0273466e+08 | AA93: =+'[1]CF Dia V1'!$CP$102 -> 5815616379 | AB93: =+AB92 -> 1048306.4 | AC93: =+AC92 -> 10000000 | AD93: =+AD92 -> 220000 | AE93: =+AE92 -> 280000 | AF93: =+'[1]CF Dia V1'!$CP$97 -> 4784062 | AG93: =+AG92 -> 5582721359 | AH93: =+'[1]CF Dia V1'!$CP$24+'[1]CF Dia V1'!$CP$25 -> 3010733050 | AI93: =+'[1]CF Dia V1'!$CP$29 -> 9293453820 | AJ93: =+'[1]CF Dia V1'!$CP$31 -> 1.8696528e+08
A94: 46168 | B94: =+'[1]CF Dia V1'!$CQ$2 -> 1392 | D94: =+'[1]CF Dia V1'!$CQ$10 -> 1224537171 | E94: =+'[1]CF Dia V1'!$CQ$13 -> 149182000 | F94: =+'[1]CF Dia V1'!$CQ$16 -> 52639000 | G94: =+'[1]CF Dia V1'!$CQ$14 -> 9150000 | H94: =+'[1]CF Dia V1'!$CQ$15 -> 2000000 | I94: =+'[1]CF Dia V1'!$CQ$22 -> 1190510533 | J94: =+'[1]CF Dia V1'!$CQ$43 -> 418065530 | L94: =+'[1]CF Dia V1'!$CQ$46 -> 18256232 | O94: =+'[1]CF Dia V1'!$CQ$49 -> 4500474 | Q94: =+'[1]CF Dia V1'!$CQ$51 -> 36096372 | X94: =+'[1]CF Dia V1'!$CQ$100 -> 1816083018 | Y94: =+'[1]CF Dia V1'!$CQ$101 -> 851827495 | Z94: =+Z93 -> 2.0273466e+08 | AA94: =+'[1]CF Dia V1'!$CQ$102 -> 5807216200 | AB94: =+AB93 -> 1048306.4 | AC94: =+AC93 -> 10000000 | AD94: =+AD93 -> 220000 | AE94: =+AE93 -> 280000 | AF94: =+'[1]CF Dia V1'!$CQ$97 -> 4873216 | AG94: =+AG93 -> 5582721359 | AH94: =+'[1]CF Dia V1'!$CQ$24+'[1]CF Dia V1'!$CQ$25 -> 3.3752674e+09 | AI94: =+'[1]CF Dia V1'!$CQ$29 -> 9433283328 | AJ94: =+'[1]CF Dia V1'!$CQ$31 -> 2.3338884e+08
A95: =+'[1]CF Dia V1'!$CR$1 -> 46169 | B95: =+'[1]CF Dia V1'!$CR$2 -> 1406 | D95: =+D94 -> 1224537171 | E95: =+'[1]CF Dia V1'!$CR$13 -> 183468000 | F95: =+'[1]CF Dia V1'!$CR$16 -> 87439376 | G95: =+G94 -> 9150000 | H95: =+H94 -> 2000000 | I95: =+'[1]CF Dia V1'!$CR$22 -> 1190510533 | J95: =+'[1]CF Dia V1'!$CR$43 -> 471654657 | L95: =+'[1]CF Dia V1'!$CR$46 -> 1649700 | Q95: =+'[1]CF Dia V1'!$CR$51 -> 46281564 | U95: =+'[1]CF Dia V1'!$CR$60 -> 29000000 | X95: =+'[1]CF Dia V1'!$CR$100 -> 1437358611 | Y95: =+'[1]CF Dia V1'!$CR$101 -> 786178943 | Z95: =+Z94 -> 2.0273466e+08 | AA95: =+'[1]CF Dia V1'!$CR$102 -> 5719924121 | AB95: =+AB94 -> 1048306.4 | AC95: =+AC94 -> 10000000 | AD95: =+AD94 -> 220000 | AE95: =+AE94 -> 280000 | AF95: =+'[1]CF Dia V1'!$CR$97 -> 6457477 | AG95: =+AG94 -> 5582721359 | AH95: =+'[1]CF Dia V1'!$CR$24+'[1]CF Dia V1'!$CR$25 -> 4.7760327e+09 | AI95: =+'[1]CF Dia V1'!$CR$29 -> 7743577338 | AJ95: =+'[1]CF Dia V1'!$CR$31 -> 2.4209525e+08
A96: 46170 | B96: 1408 | D96: =+'[1]CF Dia V1'!$CS$10 -> 1224537171 | E96: =+'[1]CF Dia V1'!$CS$13 -> 139852000 | F96: =+'[1]CF Dia V1'!$CS$16 -> 165500000 | G96: =+'[1]CF Dia V1'!$CS$14 -> 13379850 | H96: 2000000 | I96: =+'[1]CF Dia V1'!$CS$22 -> 1290599938 | J96: =+'[1]CF Dia V1'!$CS$43+'[1]CF Dia V1'!$CS$44 -> 457355720 | L96: =+'[1]CF Dia V1'!$CS$46 -> 90081817 | Q96: =+'[1]CF Dia V1'!$CS$51 -> 104935725 | X96: =+'[1]CF Dia V1'!$CS$100 -> 1452001433 | Y96: =+'[1]CF Dia V1'!$CS$101 -> 809592824 | Z96: =+Z95 -> 2.0273466e+08 | AA96: =+'[1]CF Dia V1'!$CS$102 -> 4896254184 | AB96: =+AB95 -> 1048306.4 | AC96: =+AC95 -> 10000000 | AD96: =+AD95 -> 220000 | AE96: =+AE95 -> 280000 | AF96: =+'[1]CF Dia V1'!$CS$97 -> 6316844 | AG96: =+AG95 -> 5582721359 | AH96: =+'[1]CF Dia V1'!$CS$24+'[1]CF Dia V1'!$CS$25 -> 4.659497e+09 | AI96: =+'[1]CF Dia V1'!$CS$29 -> 7917403648 | AJ96: =+'[1]CF Dia V1'!$CS$31 -> 2.4220163e+08
A97: 46171 | B97: 1406.5 | D97: =+'[1]CF Dia V1'!$CT$10 -> 1340551975 | E97: =+'[1]CF Dia V1'!$CT$13 -> -33045000 | F97: =+'[1]CF Dia V1'!$CT$16 -> 35632000 | G97: =+'[1]CF Dia V1'!$CT$14 -> 13378000 | H97: 2000000 | I97: =+'[1]CF Dia V1'!$CT$22 -> 1250668537 | J97: =+'[1]CF Dia V1'!$CT$43+'[1]CF Dia V1'!$CT$44 -> 447130211 | Q97: =+'[1]CF Dia V1'!$CT$51 -> 69975466 | X97: =+'[1]CF Dia V1'!$CT$100 -> 1377152179 | Y97: =+'[1]CF Dia V1'!$CT$101 -> 898433033 | Z97: =+Z96 -> 2.0273466e+08 | AA97: =+'[1]CF Dia V1'!$CT$102 -> 4628913889 | AB97: =+AB96 -> 1048306.4 | AC97: =+AC96 -> 10000000 | AD97: =+AD96 -> 220000 | AE97: =+AE96 -> 280000 | AF97: =+'[1]CF Dia V1'!$CT$97 -> 35688 | AG97: =+AG96 -> 5582721359 | AH97: =+'[1]CF Dia V1'!$CT$24+'[1]CF Dia V1'!$CT$25 -> 4.3574672e+09 | AI97: =+'[1]CF Dia V1'!$CT$29 -> 7908968914 | AJ97: =+'[1]CF Dia V1'!$CT$31 -> 2.4230821e+08
A98: 46174 | B98: 1406 | D98: =+'[1]CF Dia V1'!$CU$10 -> 1366573012 | E98: 310683000 | F98: =+'[1]CF Dia V1'!$CU$16 -> 447324554 | G98: =+'[1]CF Dia V1'!$CU$14 -> 13146882 | H98: =+H97 -> 2000000 | I98: =+'[1]CF Dia V1'!$CU$22 -> 1213336989 | J98: =+'[1]CF Dia V1'!$CU$43 -> 325345795 | L98: =+'[1]CF Dia V1'!$CU$46 -> 116687046 | Q98: =+'[1]CF Dia V1'!$CU$51 -> 5414532 | X98: =+'[1]CF Dia V1'!$CU$100 -> 1213908811 | Y98: =+'[1]CF Dia V1'!$CU$101 -> 3753759654 | Z98: =+'[1]CF Dia V1'!$CU$104 -> 1.9101677e+08 | AA98: =+'[1]CF Dia V1'!$CU$102 -> 4562436968 | AB98: =+'[1]CF Dia V1'!$CU$103 -> 1028533.4 | AC98: =+AC97 -> 10000000 | AD98: =+AD97 -> 220000 | AE98: =+AE97 -> 280000 | AF98: =+'[1]CF Dia V1'!$CU$97 -> 7045070 | AG98: =+'[1]CF Dia V1'!$CU$98 -> 5582721359 | AH98: =+'[1]CF Dia V1'!$CU$24+'[1]CF Dia V1'!$CU$25 -> 4.4391961e+09 | AI98: =+'[1]CF Dia V1'!$CU$29 -> 8951903580 | AJ98: =+'[1]CF Dia V1'!$CU$31 -> 2.7867305e+08
A99: 46175 | B99: 1419 | D99: =+'[1]CF Dia V1'!$CV$10 -> 1366573012 | E99: =+'[1]CF Dia V1'!$CV$13 -> 62158000 | F99: =+'[1]CF Dia V1'!$CV$16 -> 90927000 | G99: =+'[1]CF Dia V1'!$CV$14 -> 9121127 | H99: =+H98 -> 2000000 | I99: =+'[1]CF Dia V1'!$CV$22 -> 1533043002 | J99: =+'[1]CF Dia V1'!$CV$43 -> 365000923 | Q99: =+'[1]CF Dia V1'!$CV$51 -> 80000000 | X99: =+'[1]CF Dia V1'!$CV$100 -> 1507567585 | Y99: =+'[1]CF Dia V1'!$CV$101 -> 4031972319 | Z99: =+'[1]CF Dia V1'!$CV$104 -> 1.9101677e+08 | AA99: =+'[1]CF Dia V1'!$CV$102 -> 4496965997 | AB99: =+AB98 -> 1028533.4 | AC99: =+AC98 -> 10000000 | AD99: =+AD98 -> 220000 | AE99: =+AE98 -> 280000 | AF99: =+'[1]CF Dia V1'!$CV$97 -> 8074763 | AG99: =+AG98 -> 5582721359 | AH99: =+'[1]CF Dia V1'!$CV$24+'[1]CF Dia V1'!$CV$25 -> 4.4802413e+09 | AI99: =+'[1]CF Dia V1'!$CV$29 -> 8676102303 | AJ99: =+'[1]CF Dia V1'!$CV$31 -> 2.8579827e+08
A100: 46176 | B100: 1424.5 | D100: =+'[1]CF Dia V1'!$CW$10 -> 1366573012 | E100: =+'[1]CF Dia V1'!$CW$13 -> 193021000 | F100: =+'[1]CF Dia V1'!$CW$16 -> 120900000 | G100: =+'[1]CF Dia V1'!$CW$14 -> 3910000 | H100: =+H99 -> 2000000 | I100: =+'[1]CF Dia V1'!$CW$22 -> 1582834654 | J100: =+'[1]CF Dia V1'!$CW$43 -> 214487540 | Q100: =+'[1]CF Dia V1'!$CW$51 -> 178059700 | T100: =+'[1]CF Dia V1'!$CW$59 -> 11508455 | U100: =+'[1]CF Dia V1'!$CW$60 -> 100000000 | X100: =+'[1]CF Dia V1'!$CW$100 -> 1512097058 | Y100: =+'[1]CF Dia V1'!$CW$101 -> 3816902319 | Z100: =+Z99 -> 1.9101677e+08 | AA100: =+'[1]CF Dia V1'!$CW$102 -> 4472804706 | AB100: =+AB99 -> 1028533.4 | AC100: =+AC99 -> 10000000 | AD100: =+AD99 -> 220000 | AE100: =+AE99 -> 280000 | AF100: =+'[1]CF Dia V1'!$CW$97 -> 8485763 | AG100: =+AG99 -> 5582721359 | AH100: =+'[1]CF Dia V1'!$CW$24+'[1]CF Dia V1'!$CW$25 -> 4.5662692e+09 | AI100: =+'[1]CF Dia V1'!$CW$29 -> 8.7097306e+09 | AJ100: =+'[1]CF Dia V1'!$CW$31 -> 2.8592274e+08
A101: 46177 | B101: 1430 | D101: =+'[1]CF Dia V1'!$CX$10 -> 1366573012 | E101: =+'[1]CF Dia V1'!$CX$13 -> 97642000 | F101: =+'[1]CF Dia V1'!$CX$16 -> 13500000 | G101: =+'[1]CF Dia V1'!$CX$14 -> 5149000 | H101: =+H100 -> 2000000 | I101: =+'[1]CF Dia V1'!$CX$22 -> 1733927373 | J101: =+'[1]CF Dia V1'!$CX$43 -> 135000000 | L101: =+'[1]CF Dia V1'!$CX$46 -> 3892372 | P101: =+'[1]CF Dia V1'!$CX$50 -> 11667763 | Q101: =+'[1]CF Dia V1'!$CX$51 -> 481974372 | X101: =+'[1]CF Dia V1'!$CX$100 -> 1485119936 | Y101: =+'[1]CF Dia V1'!$CX$101 -> 3427374844 | Z101: =+Z100 -> 1.9101677e+08 | AA101: =+'[1]CF Dia V1'!$CX$102 -> 4799416274 | AB101: =+AB100 -> 1028533.4 | AC101: =+AC100 -> 10000000 | AD101: =+AD100 -> 220000 | AE101: =+AE100 -> 280000 | AF101: =+'[1]CF Dia V1'!$CX$97 -> 8825768 | AG101: =+AG100 -> 5582721359 | AH101: =+'[1]CF Dia V1'!$CX$24+'[1]CF Dia V1'!$CX$25 -> 4.9306105e+09 | AI101: =+'[1]CF Dia V1'!$CX$29 -> 8743351760 | AJ101: =+'[1]CF Dia V1'!$CX$31 -> 2.8604565e+08
A102: 46178 | B102: 1434 | D102: =+'[1]CF Dia V1'!$CY$10 -> 1366573012 | E102: =+'[1]CF Dia V1'!$CY$13 -> 2.7264047e+08 | F102: =+'[1]CF Dia V1'!$CY$16 -> 20650975 | G102: =+'[1]CF Dia V1'!$CY$14 -> 16335000 | H102: =+H101 -> 2000000 | I102: =+'[1]CF Dia V1'!$CY$22 -> 1654368586 | J102: =+'[1]CF Dia V1'!$CY$43 -> 440719000 | Q102: =+'[1]CF Dia V1'!$CY$51 -> 83213406 | T102: =+'[1]CF Dia V1'!$CY$59 -> 10652000 | X102: =+'[1]CF Dia V1'!$CY$100 -> 1499323745 | Y102: =+'[1]CF Dia V1'!$CY$101 -> 3574582194 | Z102: =+Z101 -> 1.9101677e+08 | AA102: =+'[1]CF Dia V1'!$CY$102 -> 4744842059 | AB102: =+AB101 -> 1028533.4 | AC102: =+AC101 -> 10000000 | AD102: =+AD101 -> 220000 | AE102: =+AE101 -> 280000 | AF102: =+'[1]CF Dia V1'!$CY$97 -> 10993000 | AG102: =+AG101 -> 5582721359 | AH102: =+'[1]CF Dia V1'!$CY$24+'[1]CF Dia V1'!$CY$25 -> 4.8576236e+09 | AI102: =+'[1]CF Dia V1'!$CY$29 -> 7931454000 | AJ102: =+'[1]CF Dia V1'!$CY$31 -> 2.6415992e+08
A103: 46181 | B103: 1440 | D103: =+'[1]CF Dia V1'!$CZ$10 -> 1366573012 | E103: =+'[1]CF Dia V1'!$CZ$13 -> 82078000 | F103: =+'[1]CF Dia V1'!$CZ$16 -> 19099000 | G103: =+'[1]CF Dia V1'!$CZ$14 -> -55055000 | H103: =+H102 -> 2000000 | I103: =+'[1]CF Dia V1'!$CZ$22 -> 2504434234 | J103: =+'[1]CF Dia V1'!$CZ$43 -> 464435608 | L103: =+'[1]CF Dia V1'!$CZ$46 -> 126723515 | Q103: =+'[1]CF Dia V1'!$CZ$51 -> 8388083 | U103: =+'[1]CF Dia V1'!$CZ$60 -> 100000000 | X103: =+'[1]CF Dia V1'!$CZ$100 -> 1122265222 | Y103: =+'[1]CF Dia V1'!$CZ$101 -> 3203368814 | Z103: =+Z102 -> 1.9101677e+08 | AA103: =+'[1]CF Dia V1'!$CZ$102 -> 5023890065 | AB103: 1202456 | AC103: =+AC102 -> 10000000 | AD103: =+AD102 -> 220000 | AE103: =+AE102 -> 280000 | AF103: =+'[1]CF Dia V1'!$CZ$97 -> 10901124 | AG103: =+AG102 -> 5582721359 | AH103: =+'[1]CF Dia V1'!$CZ$24+'[1]CF Dia V1'!$CZ$25 -> 4.7756018e+09 | AI103: =+'[1]CF Dia V1'!$CZ$29 -> 8096941440 | AJ103: =+'[1]CF Dia V1'!$CZ$31 -> 278518000
A104: 46182 | B104: =+'[1]CF Dia V1'!$DA$2 -> 1442 | D104: =+D103 -> 1366573012 | E104: =+'[1]CF Dia V1'!$DA$13 -> 158003000 | F104: =+'[1]CF Dia V1'!$DA$16 -> 83500000 | G104: =+'[1]CF Dia V1'!$DA$14 -> 3455000 | H104: =+H103 -> 2000000 | I104: =+'[1]CF Dia V1'!$DA$22 -> 2504434234 | J104: =+'[1]CF Dia V1'!$DA$43 -> 26208000 | P104: =+'[1]CF Dia V1'!$DA$50 -> 230621763 | Q104: =+'[1]CF Dia V1'!$DA$51 -> 999147178 | X104: =+'[1]CF Dia V1'!$DA$100 -> 1442191789 | Y104: =+'[1]CF Dia V1'!$DA$101 -> 2351933757 | Z104: =+Z103 -> 1.9101677e+08 | AA104: =+'[1]CF Dia V1'!$DA$102 -> 5.3296562e+09 | AB104: =+AB103 -> 1202456 | AC104: =+AC103 -> 10000000 | AD104: =+AD103 -> 220000 | AE104: =+AE103 -> 280000 | AF104: =+'[1]CF Dia V1'!$DA$97 -> 10661367 | AG104: =+AG103 -> 5582721359 | AH104: =+'[1]CF Dia V1'!$DA$24+'[1]CF Dia V1'!$DA$25 -> 4.2778097e+09 | AI104: =+'[1]CF Dia V1'!$DA$29 -> 8051598786 | AJ104: =+'[1]CF Dia V1'!$DA$31 -> 278638000
A105: 46183 | B105: 1444 | D105: =+D104 -> 1366573012 | E105: =+'[1]CF Dia V1'!$DB$13 -> 2.823776e+08 | F105: =+'[1]CF Dia V1'!$DB$16 -> 404000000 | G105: =+G104 -> 3455000 | H105: =+H104 -> 2000000 | I105: =+'[1]CF Dia V1'!$DB$22 -> 2519698829 | J105: =+'[1]CF Dia V1'!$DB$43 -> 49230696 | L105: =+'[1]CF Dia V1'!$DB$46 -> 176339266 | P105: =+'[1]CF Dia V1'!$DB$50 -> 124006883 | Q105: =+'[1]CF Dia V1'!$DB$51 -> 413477248 | U105: =+'[1]CF Dia V1'!$DB$60 -> 60000000 | X105: =+'[1]CF Dia V1'!$DB$100 -> 2069933438 | Y105: =+'[1]CF Dia V1'!$DB$101 -> 2032148193 | Z105: =+Z104 -> 1.9101677e+08 | AA105: =+'[1]CF Dia V1'!$DB$102 -> 5465695997 | AB105: =+AB104 -> 1202456 | AC105: =+AC104 -> 10000000 | AD105: =+AD104 -> 220000 | AE105: =+AE104 -> 280000 | AF105: =+'[1]CF Dia V1'!$DB$97 -> 9665367 | AG105: =+AG104 -> 5582721359 | AH105: =+'[1]CF Dia V1'!$DB$24+'[1]CF Dia V1'!$DB$25 -> 3295069376 | AI105: =+'[1]CF Dia V1'!$DB$29 -> 8062766052 | AJ105: =+'[1]CF Dia V1'!$DB$31 -> 178714000
A106: 46185 | B106: 1444 | D106: =+'[1]CF Dia V1'!$DD$10 -> 1778551709 | E106: =+'[1]CF Dia V1'!$DD$13 -> 1.4093515e+08 | F106: =+'[1]CF Dia V1'!$DD$16 -> 290571568 | G106: =+'[1]CF Dia V1'!$DD$14 -> 6748560 | H106: 2000000 | I106: =+'[1]CF Dia V1'!$DD$22 -> 2018496354 | J106: =+'[1]CF Dia V1'!$DD$43 -> 422611775 | P106: =+'[1]CF Dia V1'!$DD$50 -> 285064171 | Q106: =+'[1]CF Dia V1'!$DD$51 -> 306986818 | X106: =+'[1]CF Dia V1'!$DD$100 -> 1873319205 | Y106: =+'[1]CF Dia V1'!$DD$101 -> 1563095825 | Z106: =+Z105 -> 1.9101677e+08 | AA106: =+'[1]CF Dia V1'!$DD$102 -> 5589564137 | AB106: =+AB105 -> 1202456 | AC106: =+AC105 -> 10000000 | AD106: =+AD105 -> 220000 | AE106: =+AE105 -> 280000 | AF106: =+'[1]CF Dia V1'!$DD$97 -> 11289324 | AG106: =+AG105 -> 5582721359 | AH106: =+'[1]CF Dia V1'!$DD$24+'[1]CF Dia V1'!$DD$25 -> 4.0563256e+09 | AI106: =+'[1]CF Dia V1'!$DD$29 -> 7951640144 | AJ106: =+'[1]CF Dia V1'!$DD$31 -> 1.9405327e+08
A107: 46189 | B107: 1427 | D107: =+'[1]CF Dia V1'!$DE$10 -> 2268029215 | E107: =+'[1]CF Dia V1'!$DE$13 -> 3.0148266e+08 | F107: =+'[1]CF Dia V1'!$DE$16 -> 47500000 | G107: =+'[1]CF Dia V1'!$DE$14 -> -5900000 | H107: 2000000 | I107: =+'[1]CF Dia V1'!$DE$22 -> 1530537822 | J107: =+'[1]CF Dia V1'!$DE$43 -> 334335700 | L107: =+'[1]CF Dia V1'!$DE$46 -> 188300000 | P107: =+'[1]CF Dia V1'!$DE$50 -> 36765809 | Q107: =+'[1]CF Dia V1'!$DE$51 -> 7627147 | X107: =+'[1]CF Dia V1'!$DE$100 -> 1870852101 | Y107: =+'[1]CF Dia V1'!$DE$101 -> 1693922893 | Z107: =+Z106 -> 1.9101677e+08 | AA107: =+'[1]CF Dia V1'!$DE$102 -> 5589072977 | AB107: =+AB106 -> 1202456 | AC107: =+AC106 -> 10000000 | AD107: =+AD106 -> 220000 | AE107: =+AE106 -> 280000 | AF107: =+'[1]CF Dia V1'!$DE$97 -> 14799324 | AG107: =+AG106 -> 5582721359 | AH107: =+'[1]CF Dia V1'!$DE$24+'[1]CF Dia V1'!$DE$25 -> 3.269438e+09 | AI107: =+'[1]CF Dia V1'!$DE$29 -> 7858026652 | AJ107: =+'[1]CF Dia V1'!$DE$31 -> 1.9438939e+08
A108: 46190 | B108: 1427 | D108: =+'[1]CF Dia V1'!$DF$10 -> 2383852953 | E108: =+'[1]CF Dia V1'!$DF$13 -> 2.0810978e+08 | F108: =+'[1]CF Dia V1'!$DF$16 -> 2.4451089e+08 | G108: =+'[1]CF Dia V1'!$DF$14 -> 2048000 | H108: 2000000 | I108: =+'[1]CF Dia V1'!$DF$22 -> 1958536678 | J108: =+'[1]CF Dia V1'!$DF$43 -> 170816222 | P108: =+'[1]CF Dia V1'!$DF$50 -> 14467604 | Q108: =+'[1]CF Dia V1'!$DF$51 -> 485193438 | X108: =+'[1]CF Dia V1'!$DF$100 -> 1779143763 | Y108: =+'[1]CF Dia V1'!$DF$101 -> 1922736439 | Z108: =+Z107 -> 1.9101677e+08 | AA108: =+'[1]CF Dia V1'!$DF$102 -> 5527488705 | AB108: =+AB107 -> 1202456 | AC108: =+AC107 -> 10000000 | AD108: =+AD107 -> 220000 | AE108: =+AE107 -> 280000 | AF108: =+'[1]CF Dia V1'!$DF$97 -> 16047536 | AG108: =+AG107 -> 5582721359 | AH108: =+'[1]CF Dia V1'!$DF$24+'[1]CF Dia V1'!$DF$25 -> 2.9667426e+09 | AI108: =+'[1]CF Dia V1'!$DF$29 -> 6821722128 | AJ108: =+'[1]CF Dia V1'!$DF$31 -> 1.9447405e+08
A109: 46191 | B109: 1437 | D109: =+'[1]CF Dia V1'!$DG$10 -> 2754644903 | E109: =+'[1]CF Dia V1'!$DG$13 -> 89606949 | F109: =+'[1]CF Dia V1'!$DG$16 -> 73309028 | G109: =+'[1]CF Dia V1'!$DG$14 -> 2278000 | H109: =+H108 -> 2000000 | I109: =+'[1]CF Dia V1'!$DG$22 -> 2024387793 | J109: =+'[1]CF Dia V1'!$DG$43 -> 358580004 | L109: =+'[1]CF Dia V1'!$DG$46 -> 5545144 | O109: =+'[1]CF Dia V1'!$DG$49 -> 2338696 | P109: =+'[1]CF Dia V1'!$DG$50 -> 39867750 | Q109: =+'[1]CF Dia V1'!$DG$51 -> 400228697 | X109: =+'[1]CF Dia V1'!$DG$100 -> 1808281690 | Y109: =+'[1]CF Dia V1'!$DG$101 -> 1818368308 | Z109: =+Z108 -> 1.9101677e+08 | AA109: =+'[1]CF Dia V1'!$DG$102 -> 5520255928 | AB109: =+AB108 -> 1202456 | AC109: =+AC108 -> 10000000 | AD109: =+AD108 -> 220000 | AE109: =+AE108 -> 280000 | AF109: =+'[1]CF Dia V1'!$DG$97 -> 14300536 | AG109: =+AG108 -> 5582721359 | AH109: =+'[1]CF Dia V1'!$DG$24+'[1]CF Dia V1'!$DG$25 -> 2.5914907e+09 | AI109: =+'[1]CF Dia V1'!$DG$29 -> 6869526768 | AJ109: =+'[1]CF Dia V1'!$DG$31 -> 2.2757316e+08
A110: 46192 | B110: 1445.5 | D110: =+'[1]CF Dia V1'!$DH$10 -> 2925974238 | E110: =+'[1]CF Dia V1'!$DH$13 -> 2.0358042e+08 | F110: =+'[1]CF Dia V1'!$DH$16 -> 54206881 | G110: =+'[1]CF Dia V1'!$DH$14 -> 2278000 | H110: =+H109 -> 2000000 | I110: =+'[1]CF Dia V1'!$DH$22 -> 1778382352 | J110: =+'[1]CF Dia V1'!$DH$43 -> 338308627 | P110: =+'[1]CF Dia V1'!$DH$50 -> 2260244 | Q110: =+'[1]CF Dia V1'!$DH$51 -> 276513565 | T110: =+'[1]CF Dia V1'!$DH$59 -> 20225097 | X110: =+'[1]CF Dia V1'!$DH$100 -> 2498492954 | Y110: =+'[1]CF Dia V1'!$DH$101 -> 1822504420 | Z110: =+Z109 -> 1.9101677e+08 | AA110: =+'[1]CF Dia V1'!$DH$102 -> 4582166979 | AB110: =+AB109 -> 1202456 | AC110: =+AC109 -> 10000000 | AD110: =+AD109 -> 220000 | AE110: =+AE109 -> 280000 | AF110: =+'[1]CF Dia V1'!$DH$97 -> 16958536 | AG110: =+AG109 -> 5582721359 | AH110: =+'[1]CF Dia V1'!$DH$25+'[1]CF Dia V1'!$DH$24 -> 1.78301e+09 | AI110: =+'[1]CF Dia V1'!$DH$29 -> 6910160712 | AJ110: =+'[1]CF Dia V1'!$DH$31 -> 2.476801e+08
A111: 46195 | B111: 1460 | D111: =+'[1]CF Dia V1'!$DI$10 -> 2857745373 | E111: =+'[1]CF Dia V1'!$DI$13 -> 117700000 | F111: =+'[1]CF Dia V1'!$DI$16 -> 6125000 | G111: =+'[1]CF Dia V1'!$DI$14 -> 9744000 | H111: 2000000 | I111: =+'[1]CF Dia V1'!$DI$22 -> 1893455465 | J111: =+'[1]CF Dia V1'!$DI$43 -> 261423124 | L111: =+'[1]CF Dia V1'!$DI$46 -> 37652420 | O111: =+'[1]CF Dia V1'!$DI$49 -> 32173206 | P111: =+'[1]CF Dia V1'!$DI$50 -> 181228924 | Q111: =+'[1]CF Dia V1'!$DI$51 -> 73756788 | X111: =+'[1]CF Dia V1'!$DI$100 -> 2739960274 | Y111: =+'[1]CF Dia V1'!$DI$101 -> 1289294374 | Z111: =+Z110 -> 1.9101677e+08 | AA111: =+'[1]CF Dia V1'!$DI$102 -> 5211327530 | AB111: =+AB110 -> 1202456 | AC111: =+AC110 -> 10000000 | AD111: =+AD110 -> 220000 | AE111: =+AE110 -> 280000 | AF111: =+'[1]CF Dia V1'!$DI$97 -> 15445491 | AG111: =+AG110 -> 5582721359 | AH111: =+'[1]CF Dia V1'!$DI$24+'[1]CF Dia V1'!$DI$25 -> 1.4772977e+09 | AI111: =+'[1]CF Dia V1'!$DI$29 -> 7565003140 | AJ111: =+'[1]CF Dia V1'!$DI$31 -> 2.8104343e+08
A112: 46196 | B112: =+'[1]CF Dia V1'!$DJ$2 -> 1455 | D112: =+'[1]CF Dia V1'!$DJ$10 -> 2857745373 | E112: =+'[1]CF Dia V1'!$DJ$13 -> 100303523 | F112: =+'[1]CF Dia V1'!$DJ$16 -> 71567307 | G112: =+'[1]CF Dia V1'!$DJ$14 -> 53463000 | H112: 2000000 | I112: =+'[1]CF Dia V1'!$DJ$22 -> 1919655916 | J112: =+'[1]CF Dia V1'!$DJ$43 -> 314210003 | O112: =+'[1]CF Dia V1'!$DJ$49 -> 4300218 | P112: =+'[1]CF Dia V1'!$DJ$50 -> 18585962 | Q112: =+'[1]CF Dia V1'!$DJ$51 -> 226841660 | X112: =+'[1]CF Dia V1'!$DJ$100 -> 2.4069397e+09 | Y112: =+'[1]CF Dia V1'!$DJ$101 -> 1280496204 | Z112: =+'[1]CF Dia V1'!$DJ$104 -> 1.9101677e+08 | AA112: =+'[1]CF Dia V1'!$DJ$102 -> 5270740211 | AB112: =+AB111 -> 1202456 | AC112: =+AC111 -> 10000000 | AD112: =+AD111 -> 220000 | AE112: =+AE111 -> 280000 | AF112: =+'[1]CF Dia V1'!$DJ$97 -> 16753719 | AG112: =+AG111 -> 5582721359 | AH112: =+'[1]CF Dia V1'!$DJ$24+'[1]CF Dia V1'!$DJ$25 -> 8.1056253e+08 | AI112: =+'[1]CF Dia V1'!$DJ$29 -> 7476198855 | AJ112: =+'[1]CF Dia V1'!$DJ$31 -> 2.8716696e+08
A113: 46197 | B113: 1467 | D113: =+'[1]CF Dia V1'!$DK$10 -> 3181470816 | E113: =+'[1]CF Dia V1'!$DK$13 -> 160135000 | F113: =+'[1]CF Dia V1'!$DK$16 -> 2.3154374e+08 | G113: =+'[1]CF Dia V1'!$DK$14 -> 9168000 | H113: 2000000 | I113: =+'[1]CF Dia V1'!$DK$22 -> 1559790968 | J113: =+'[1]CF Dia V1'!$DK$43 -> 367400000 | L113: =+'[1]CF Dia V1'!$DK$46 -> 101923754 | O113: =+'[1]CF Dia V1'!$DK$49 -> 848120 | P113: =+'[1]CF Dia V1'!$DK$51 -> 86200000 | T113: =+'[1]CF Dia V1'!$DK$59 -> 5007874 | X113: =+'[1]CF Dia V1'!$DK$100 -> 2067308483 | Y113: =+'[1]CF Dia V1'!$DK$101 -> 1268841000 | Z113: =+Z112 -> 1.9101677e+08 | AA113: =+'[1]CF Dia V1'!$DK$102 -> 5270740211 | AB113: =+AB112 -> 1202456 | AC113: =+AC112 -> 10000000 | AD113: =+AD112 -> 220000 | AE113: =+AE112 -> 280000 | AF113: =+'[1]CF Dia V1'!$DK$97 -> 16767719 | AG113: =+AG111 -> 5582721359 | AH113: =+'[1]CF Dia V1'!$DK$24+'[1]CF Dia V1'!$DK$25 -> 1084503222 | AI113: =+'[1]CF Dia V1'!$DK$29 -> 7537858227 | AJ113: =+'[1]CF Dia V1'!$DK$31 -> 2.8729051e+08
A114: 46198 | B114: 1474 | D114: 1.9962483e+09 | E114: 1.8947764e+08 | F114: 13000000 | G114: 9000000 | H114: 2000000 | I114: 2201287040 | J114: 328739914 | Q114: 77822000 | T114: 2473400 | X114: 2252502815 | Y114: 1849298006 | Z114: =+Z113 -> 1.9101677e+08 | AA114: 5652402569 | AB114: =+AB113 -> 1202456 | AC114: =+AC113 -> 10000000 | AD114: =+AD113 -> 220000 | AE114: =+AE113 -> 280000 | AF114: 22041872 | AG114: =+AG113 -> 5582721359 | AH114: =+'[1]CF Dia V1'!$DL$25+'[1]CF Dia V1'!$DL$24 -> 1089678084 | AI114: =+'[1]CF Dia V1'!$DL$29 -> 7573826194 | AJ114: =+AJ115-132000 -> 2.8740939e+08
A115: 46199 | B115: 1475 | D115: 1.9962483e+09 | E115: 35716000 | F115: 17000000 | G115: 8881000 | H115: 2000000 | I115: 1596541079 | J115: 356978533 | L115: 19769384 | Q115: 244986993 | X115: 1895524281 | Y115: 1498128349 | Z115: =+Z114 -> 1.9101677e+08 | AA115: 5654402569 | AB115: =+AB114 -> 1202456 | AC115: =+AC114 -> 10000000 | AD115: =+AD114 -> 220000 | AE115: =+AE114 -> 280000 | AF115: 22898816 | AG115: =+AG114 -> 5582721359 | AH115: =+'[1]CF Dia V1'!$DM$24+'[1]CF Dia V1'!$DM$25 -> 7.7675885e+08 | AI115: =+'[1]CF Dia V1'!$DM$29 -> 7831182100 | AJ115: 2.8754139e+08
A116: 46202 | B116: 1470 | D116: 2062068387 | E116: 117229000 | F116: 7900000 | G116: 9391000 | H116: 4000000 | I116: 1504677115 | J116: 388893963 | L116: 3476320 | Q116: 131413281 | X116: 1651744072 | Y116: 1540652029 | Z116: =+Z115 -> 1.9101677e+08 | AA116: 5279024308 | AB116: =+AB115 -> 1202456 | AC116: =+AC115 -> 10000000 | AD116: =+AD115 -> 220000 | AE116: =+AE115 -> 280000 | AF116: 23016845 | AG116: =+AG115 -> 5582721359 | AH116: =+'[1]CF Dia V1'!$DN$24 -> 489502650 | AI116: =+'[1]CF Dia V1'!$DN$29 -> 7378079940 | AJ116: 2.8793856e+08
A117: 46203 | B117: =+'[1]CF Dia V1'!$DO$2 -> 1472.5 | D117: =+'[1]CF Dia V1'!$DO$10 -> 1711500000 | E117: =+'[1]CF Dia V1'!$DO$13 -> 28000000 | F117: =+'[1]CF Dia V1'!$DO$16 -> 440698000 | G117: =+'[1]CF Dia V1'!$DO$14 -> 915753000 | H117: 2000000 | I117: =+'[1]CF Dia V1'!$DO$22 -> 1484574186 | J117: =+'[1]CF Dia V1'!$DO$43 -> 402585340 | Q117: =+'[1]CF Dia V1'!$DO$51 -> 286700000 | X117: =+'[1]CF Dia V1'!$DO$100 -> 1523565364 | Y117: =+'[1]CF Dia V1'!$DO$101 -> 1548338237 | Z117: =+Z116 -> 1.9101677e+08 | AA117: =+'[1]CF Dia V1'!$DO$102 -> 4515567562 | AB117: =+AB116 -> 1202456 | AC117: 11000000 | AD117: 220000 | AE117: 280000 | AF117: =+'[1]CF Dia V1'!$DO$97 -> 18385776 | AG117: =+AG116 -> 5582721359 | AH117: =+'[1]CF Dia V1'!$DO$24 -> 5.6358898e+08 | AI117: =+'[1]CF Dia V1'!$DO$29 -> 7390642420 | AJ117: =+'[1]CF Dia V1'!$DO$31 -> 2.8807015e+08
A118: =+A117+1 -> 46204 | B118: 1478 | D118: 1125285355 | E118: 133431000 | F118: 194411000 | G118: 765543000 | H118: 2056000 | I118: 1318333295 | J118: 138995655 | K118: 0 | L118: 27336455 | O118: 12112493 | P118: 0 | Q118: 374832103 | T118: 135000000 | X118: 1764312348 | Y118: 10335065772 | Z118: =+Z117 -> 1.9101677e+08 | AA118: 5871902805 | AB118: =+'[1]CF Dia V1'!$DP$103 -> 1202456 | AC118: 11000000 | AD118: =+AD117 -> 220000 | AE118: =+AE117 -> 280000 | AF118: 22844186 | AG118: =+AG117 -> 5582721359 | AH118: 689979174 | AI118: 7418247536 | AJ118: =393405193.67-166000 -> 3.9323919e+08
A119: =+A118+1 -> 46205 | B119: 1485 | D119: 882676831 | E119: 139754000 | F119: 83519000 | G119: 15486000 | H119: 2000000 | I119: 1622364000 | J119: 274802850 | K119: 0 | L119: 27522945 | O119: 0 | P119: 5935500 | Q119: 382074274 | T119: 0 | U119: 150000000 | X119: 1498341393 | Y119: 10166250620 | Z119: =+Z118 -> 1.9101677e+08 | AA119: 5881436983 | AB119: =+AB118 -> 1202456 | AC119: 11000000 | AD119: =+AD118 -> 220000 | AE119: =+AE118 -> 280000 | AF119: 23156749 | AG119: =+AG118 -> 5582721359 | AH119: 726211035 | AI119: 7453381320 | AJ119: =+AJ118+166000 -> 3.9340519e+08
A120: =+A119+1 -> 46206 | B120: 1488 | D120: 882676831 | E120: 126675000 | F120: 8419000 | G120: 4548000 | H120: 4216000 | I120: 1569388000 | J120: 195622428 | K120: 92000000 | L120: 13665793 | O120: 1649700 | P120: 0 | Q120: 669764196 | T120: 0 | X120: 1376748551 | Y120: 10339004575 | Z120: =+Z119 -> 1.9101677e+08 | AA120: 6776677353 | AB120: =+AB119 -> 1202456 | AC120: 13000000 | AD120: =+AD119 -> 220000 | AE120: =+AE119 -> 280000 | AF120: 23957046 | AG120: =+AG119 -> 5582721359 | AH120: 1664113728 | AI120: 6664479696 | AJ120: =+AJ119+166000+2976377030 -> 3.3699482e+09
A121: 46209 | B121: 1488 | D121: 771170000 | E121: 83297000 | F121: 98419000 | G121: 9936000 | H121: 2000000 | I121: 1856001304 | J121: 276944944 | K121: 0 | L121: =36926240+395000 -> 37321240 | O121: 0 | P121: 22230805 | Q121: 541318193 | T121: 0 | X121: 1133889539 | Y121: 9516661103 | Z121: =+Z120 -> 1.9101677e+08 | AA121: 6813117204 | AB121: =+AB120 -> 1202456 | AC121: 13000000 | AD121: =+AD120 -> 220000 | AE121: =+AE120 -> 280000 | AF121: 25312662 | AG121: =+AG120 -> 5582721359 | AH121: 1715995452 | AI121: 6901344000 | AJ121: 2.0792517e+09
A122: 46210 | B122: 1487.5 | D122: 719567000 | E122: 69274000 | F122: 5250000 | G122: 9768000 | H122: 2000000 | I122: 1856001304 | J122: 209944020 | K122: 0 | L122: 0 | O122: 13083368 | P122: 0 | Q122: 472703154 | T122: 0 | X122: 951204240 | Y122: 9099829904 | Z122: =+Z121 -> 1.9101677e+08 | AA122: 6788103710 | AB122: =+AB121 -> 1202456 | AC122: 13000000 | AD122: =+AD121 -> 220000 | AE122: =+AE121 -> 280000 | AF122: 23937361 | AG122: =+AG121 -> 5582721359 | AH122: 1.9383073e+09 | AI122: 6.6772819e+09 | AJ122: 1.1798017e+09
A123: 46216 | B123: 1487 | D123: 555384000 | E123: 58325000 | F123: 370184000 | G123: 10032000 | H123: 9230000 | I123: 2571413000 | J123: 45552363 | K123: 86098436 | L123: 77436970 | O123: 0 | P123: 1529909959 | Q123: 20620000 | T123: 200000000 | X123: 1762595312 | Y123: 7644138345 | Z123: =+Z122 -> 1.9101677e+08 | AA123: 7533822534 | AB123: =+AB122 -> 1202456 | AC123: 13000000 | AD123: =+AD122 -> 220000 | AE123: =+AE122 -> 280000 | AF123: 23509904 | AG123: =+AG122 -> 5582721359 | AH123: 2.3486046e+09 | AI123: 6236537480 | AJ123: 0
A124: 46217 | B124: 1482.5 | D124: 830423000 | E124: 50596000 | F124: 80140000 | G124: 2430000 | H124: 2000000 | I124: 2203125000 | J124: 143874200 | K124: 0 | L124: 1683000 | O124: 0 | P124: 20496778 | Q124: 705899379 | T124: 0 | X124: 1606905322 | Y124: 7380278144 | Z124: =+Z123 -> 1.9101677e+08 | AA124: 7604369244 | AB124: =+AB123 -> 1202456 | AC124: 13000000 | AD124: =+AD123 -> 220000 | AE124: =+AE123 -> 280000 | AF124: 23509904 | AG124: =+AG123 -> 5582721359 | AH124: 4.5754819e+09 | AI124: 6217664300 | AJ124: 0
A125: 46218 | B125: 1473 | D125: 756052000 | E125: 6541000 | F125: 3088000 | G125: 7444000 | H125: 3088000 | I125: 2046863680 | J125: 333100000 | L125: 0 | O125: 0 | Q125: 677274401 | T125: 150000000 | X125: 2134226423 | Y125: 6568919472 | Z125: =+Z124 -> 1.9101677e+08 | AA125: 6908538321 | AB125: =+AB124 -> 1202456 | AC125: 13000000 | AD125: 220000 | AE125: =+AE124 -> 280000 | AF125: 23509904 | AG125: 5582721359 | AH125: 2.9835687e+09 | AI125: 5794512441 | AJ125: 0
A126: 46219 | B126: 1466 | D126: 849000000 | E126: 205418000 | F126: 2000000 | G126: 61862000 | H126: 2000000 | I126: 2046083000 | J126: 140554920 | L126: 0 | O126: 1649700 | Q126: 549746310 | T126: 58209514 | X126: 2001950789 | Y126: 6759511608 | Z126: =+Z125 -> 1.9101677e+08 | AA126: 7078036047 | AB126: =+AB125 -> 1202456 | AC126: =+AC125 -> 13000000 | AD126: =+AD125 -> 220000 | AE126: =+AE125 -> 280000 | AF126: 37132677 | AG126: 5582721359 | AH126: 3.1422283e+09 | AI126: 5766975722 | AJ126: 0
A127: =+A126+1 -> 46220 | B127: 1471 | D127: 666226000 | E127: 15591000 | F127: 2000000 | G127: 6224000 | H127: 2000000 | I127: 1694000000 | J127: 192226025 | L127: 907000 | O127: 0 | P127: 10174295 | Q127: 590333238 | T127: 4886552 | X127: 1907894000 | Y127: 5908971466 | Z127: =+Z126 -> 1.9101677e+08 | AA127: 8558992064 | AB127: =+AB126 -> 1202456 | AC127: =+AC126 -> 13000000 | AD127: =+AD126 -> 220000 | AE127: =+AE126 -> 280000 | AF127: 39333489 | AG127: 5582721359 | AH127: 2.8521239e+09 | AI127: 5224721336 | AJ127: 0
A128: =+A127+3 -> 46223 | B128: 1476 | D128: 666226000 | E128: 70613000 | F128: 2000000 | G128: 6329000 | H128: 2000000 | I128: 1988759421 | J128: 473703223 | L128: =11438845+3990742 -> 15429587 | O128: 14050924 | Q128: 442204464 | T128: 0 | X128: 1.6260271e+09 | Y128: 5433625574 | Z128: =+Z127 -> 1.9101677e+08 | AA128: 7.2333358e+09 | AB128: =+AB127 -> 1202456 | AC128: =+AC127 -> 13000000 | AD128: =+AD127 -> 220000 | AE128: =+AE127 -> 280000 | AF128: 37750136 | AG128: 5582721359 | AH128: 2.1964148e+09 | AI128: 6367443336 | AJ128: 0
A129: =+A128+1 -> 46224 | B129: 1476 | D129: 621193000 | E129: 128688000 | F129: 40590000 | G129: 12142000 | H129: 2074000 | I129: 2118627004 | J129: =141500000+50000000 -> 191500000 | L129: 0 | O129: 219172267 | P129: 730387742 | Q129: 61547402 | T129: 17800000 | X129: 4424937079 | Y129: 4087557678 | Z129: =+Z128 -> 1.9101677e+08 | AA129: 6.0616963e+09 | AB129: =+AB128 -> 1202456 | AC129: =+AC128 -> 13000000 | AD129: =+AD128 -> 220000 | AE129: =+AE128 -> 280000 | AF129: 38406149 | AG129: 5582721359 | AH129: 1872711900 | AI129: 6213471444
A130: =+A129+1 -> 46225 | B130: 1476 | D130: 653090000 | E130: 33319000 | F130: 50100000 | G130: 7246000 | H130: 1822000 | I130: 2086488000 | J130: 280000000 | L130: 34500000 | O130: 28903620 | P130: 12241836 | Q130: 80606574 | T130: 0 | V130: 50000000 | X130: 4.1132753e+09 | Y130: 4087557678 | Z130: =+Z129 -> 1.9101677e+08 | AA130: 6.0616963e+09 | AB130: =+AB129 -> 1202456 | AC130: =+AC129 -> 13000000 | AD130: =+AD129 -> 220000 | AE130: =+AE129 -> 280000 | AF130: 37496797 | AG130: 5582721359 | AH130: 1368728748 | AI130: 6134099544
A131: =+A130+1 -> 46226 | B131: 1477 | D131: 628000000 | E131: 77297000 | F131: 525000 | G131: 16817000 | H131: 1983000 | I131: 2086488000 | J131: 171450003 | L131: 4347345 | O131: 0 | P131: 0 | Q131: 441658963 | T131: 0 | X131: 4265423536 | Y131: 9854637743 | Z131: =+Z130 -> 1.9101677e+08 | AA131: 6041673039 | AB131: =+AB130 -> 1202456 | AC131: =+AC130 -> 13000000 | AD131: =+AD130 -> 220000 | AE131: =+AE130 -> 280000 | AF131: 37496797 | AG131: 5582721359 | AH131: 967622579 | AI131: 6251743687
A132: =+A131+1 -> 46227 | B132: 1487.5 | D132: 628000000 | E132: 195404000 | F132: 525000 | G132: 17336000 | H132: 3716000 | I132: 2086488000 | J132: 506146983 | L132: 0 | O132: 0 | P132: 0 | Q132: 272415178 | T132: 0 | X132: 3909877844 | Y132: 4087557678 | Z132: =+Z131 -> 1.9101677e+08 | AA132: 6191397303 | AB132: =+AB131 -> 1202456 | AC132: =+AC131 -> 13000000 | AD132: =+AD131 -> 220000 | AE132: =+AE131 -> 280000 | AF132: 37496797 | AG132: 5582721359 | AH132: 9.7450141e+08 | AI132: 5.0959682e+09
A133: 46230 | B133: 1491.5 | D133: 327306000 | E133: 186327000 | F133: 1500000 | G133: 15082000 | H133: 2293000 | I133: 2936104000 | J133: =167790943+162047173 -> 329838116 | L133: 47219345 | O133: 0 | P133: =24745500+17332851 -> 42078351 | Q133: 305121545 | T133: 0 | X133: 3279423678 | Y133: 9097212715 | Z133: =+Z132 -> 1.9101677e+08 | AA133: 6110866783 | AB133: =+AB132 -> 1202456 | AC133: =+AC132 -> 13000000 | AD133: =+AD132 -> 220000 | AE133: =+AE132 -> 280000 | AF133: 35774253 | AG133: 5582721359 | AH133: 1.1610149e+09 | AI133: 6.9729012e+09
A134: 46231 | B134: 1493.5 | D134: 327306000 | E134: 123895000 | F134: 50000000 | G134: 11173000 | H134: 2500000 | I134: 2506159000 | J134: 441385646 | L134: 0 | O134: 0 | P134: 0 | Q134: 15629452 | T134: 0 | X134: 2828008580 | Y134: 9105488614 | Z134: =+Z133 -> 1.9101677e+08 | AA134: 6157032317 | AB134: =+AB133 -> 1202456 | AC134: 14000000 | AD134: =+AD133 -> 220000 | AE134: =+AE133 -> 280000 | AF134: 38106922 | AG134: 5582721359 | AH134: 6.6208767e+08 | AI134: 6.9822514e+09 | AJ134: 0
A135: 46232 | B135: 1493.5 | D135: 297100000 | E135: 99046000 | F135: 54000000 | G135: 1181000 | H135: 3128000 | I135: 2604210000 | J135: 379474769 | L135: 0 | O135: 0 | P135: 10064924 | Q135: 127556749 | T135: 0 | X135: 2517270830 | Y135: 9079261502 | Z135: =+Z134 -> 1.9101677e+08 | AA135: 6429893546 | AB135: =+AB134 -> 1202456 | AC135: 14000000 | AD135: =+AD134 -> 220000 | AE135: =+AE134 -> 280000 | AF135: 38176752 | AG135: 5582721359 | AH135: 661342709 | AI135: 7.3138622e+09 | AJ135: 1040000000
A136: =+A135+1 -> 46233 | B136: 1496 | D136: 210937000 | E136: 192928000 | F136: 59648000 | G136: 11177000 | H136: 2021000 | I136: 2604210000 | J136: 891913205 | L136: 3137520 | X136: 2581219963 | Y136: 12522717049 | Z136: 1.9101677e+08 | AA136: 5027656217 | AB136: 1202456 | AC136: 14000000 | AD136: =+AD135 -> 220000 | AE136: 280000 | AF136: 38547163 | AG136: 5582721359 | AH136: 1497575288 | AI136: 7119538800
A137: =+A136+1 -> 46234 | B137: 1487 | D137: 210937000 | E137: 16112000 | F137: 59000000 | G137: 16610000 | H137: 2020000 | I137: 2658759000 | J137: 625560946 | L137: 34421036 | P137: 82464937 | X137: 1826772888 | Y137: 12395831076 | Z137: 1.9101677e+08 | AA137: 5027656217 | AB137: 1202456 | AC137: 14000000 | AD137: =+AD136 -> 220000 | AE137: 280000 | AF137: 38817227 | AG137: 5582721359 | AH137: 1277002886 | AI137: 7076707350 | AJ137: 540751074
A138: 46237 | B138: 1486.5 | D138: 301470000 | E138: 117229000 | F138: 60000000 | G138: 16161000 | H138: 1018000 | I138: 2377791000 | J138: 217459686 | L138: 27025263 | Q138: 86600000 | X138: 1629882981 | Y138: 11839582661 | Z138: 1.7932612e+08 | AA138: 5.9282762e+09 | AB138: 1202456 | AC138: 14000000 | AD138: 245288.77 | AE138: 280000 | AF138: 40484466 | AG138: 5582721359 | AH138: 7.3991578e+08 | AI138: 7.5378676e+09 | AJ138: 0
A139: 46238 | B139: 1490 | D139: =+'[1]CF Dia V1'!$EK$10 -> 441400000 | E139: =+'[1]CF Dia V1'!$EK$13 -> 122574000 | F139: =+'[1]CF Dia V1'!$EK$16 -> 95000000 | G139: =+'[1]CF Dia V1'!$EK$14 -> 13304000 | H139: =+'[1]CF Dia V1'!$EK$15 -> 2000000 | I139: =+'[1]CF Dia V1'!$EK$22 -> 2297663244 | J139: =+'[1]CF Dia V1'!$EK$43 -> 307499246 | L139: =+'[1]CF Dia V1'!$EK$46 -> 14574830 | Q139: =+'[1]CF Dia V1'!$EK$51 -> 108710771 | U139: 200000000 | X139: =+'[1]CF Dia V1'!$EK$100 -> 1325990325 | Y139: =+'[1]CF Dia V1'!$EK$101 -> 11905007831 | Z139: =+Z138 -> 1.7932612e+08 | AA139: =+'[1]CF Dia V1'!$EK$102 -> 6084858000 | AB139: =+AB138 -> 1202456 | AC139: 15000000 | AD139: =+AD138 -> 245288.77 | AE139: =+AE138 -> 280000 | AF139: =+'[1]CF Dia V1'!$EK$97 -> 34675582 | AG139: =+AG138 -> 5582721359 | AH139: =+'[1]CF Dia V1'!$EK$24+'[1]CF Dia V1'!$EK$25 -> 766642250 | AI139: =+'[1]CF Dia V1'!$EK$29 -> 7389960450
A140: =+A139+1 -> 46239 | B140: 1494 | D140: 436600000 | E140: 28496000 | F140: 102000000 | G140: 23733000 | H140: 285672000 | I140: 2179756902 | J140: 315965760 | L140: 225000 | P140: 0 | Q140: 415848270 | U140: 33500000 | X140: 1295381406 | Y140: 11681248760 | Z140: =+Z139 -> 1.7932612e+08 | AA140: 7767195087 | AB140: =+AB139 -> 1202456 | AC140: 15000000 | AD140: =+AD139 -> 245288.77 | AE140: 280000 | AF140: 37087543 | AG140: =+AG139 -> 5582721359 | AH140: =+'[1]CF Dia V1'!$EL$24+'[1]CF Dia V1'!$EL$25 -> 1666262682 | AI140: =+'[1]CF Dia V1'!$EL$29 -> 7409799270 | AJ140: =+'[1]CF Dia V1'!$EL$31 -> 999458000
A141: =+A140+1 -> 46240 | B141: 1493.5 | D141: 390836716 | E141: -162200000 | F141: 115000000 | G141: 878000 | H141: 3480000 | I141: 2068918000 | J141: 135200000 | L141: 30702000 | P141: 22272345 | Q141: 947816714 | U141: 0 | X141: 2575252725 | Y141: 10958704076 | Z141: =+Z140 -> 1.7932612e+08 | AA141: 8029413003 | AB141: =+AB140 -> 1202456 | AC141: 15000000 | AD141: =+AD140 -> 245288.77 | AE141: 280000 | AF141: 36888391 | AG141: =+AG140 -> 5582721359 | AH141: =+'[1]CF Dia V1'!$EM$24+'[1]CF Dia V1'!$EM$25 -> 1.8680265e+09 | AI141: =+'[1]CF Dia V1'!$EM$29 -> 7.4875144e+09
A142: =+A141+1 -> 46241 | B142: 1493.5 | D142: 266873000 | E142: 93043000 | F142: 68000000 | G142: 840000 | H142: 2932000 | I142: 2353065000 | J142: 224992975 | L142: 0 | P142: 51452643 | Q142: 121486987 | U142: 0 | X142: 2295479847 | Y142: 10892663458 | Z142: =+Z141 -> 1.7932612e+08 | AA142: 8081657101 | AB142: =+AB141 -> 1202456 | AC142: 15000000 | AD142: =+AD141 -> 245288.77 | AE142: 280000 | AF142: 33210575 | AG142: =+AG141 -> 5582721359 | AH142: =+'[1]CF Dia V1'!$EN$24+'[1]CF Dia V1'!$EN$25 -> 1181259929 | AI142: =+'[1]CF Dia V1'!$EN$29 -> 7.4875144e+09
A143: 46244 | B143: 1495.5 | D143: 766520000 | E143: 218766000 | F143: 1585000000 | G143: -9300000 | H143: 2000000 | I143: 2596698170 | J143: 30805698 | L143: 0 | P143: 1388467872 | Q143: 530075264 | U143: 0 | X143: 1408813874 | Y143: 7808517200 | Z143: =+Z142 -> 1.7932612e+08 | AA143: 8083336327 | AB143: =+AB142 -> 1202456 | AC143: 16000000 | AD143: =+AD142 -> 245288.77 | AE143: 280000 | AF143: 33904451 | AG143: =+AG142 -> 5582721359 | AH143: =+'[1]CF Dia V1'!$EO$24+'[1]CF Dia V1'!$EO$25 -> 6.5673342e+08 | AI143: =+'[1]CF Dia V1'!$EO$29 -> 7.4939281e+09
A144: 46245 | B144: 1495 | D144: 481253000 | E144: =+'[1]CF Dia V1'!$EP$13 -> 98247000 | F144: =+'[1]CF Dia V1'!$EP$16 -> 71200000 | G144: =+'[1]CF Dia V1'!$EP$14 -> -9279000 | H144: =+'[1]CF Dia V1'!$EP$15 -> 2000000 | I144: =+'[1]CF Dia V1'!$EP$22 -> 2124014967 | J144: =+'[1]CF Dia V1'!$EP$43 -> 26925000 | P144: =+'[1]CF Dia V1'!$EP$50 -> 10592000 | Q144: =+'[1]CF Dia V1'!$EP$51 -> 166523884 | T144: =+'[1]CF Dia V1'!$EP$59 -> 15741079 | U144: =+'[1]CF Dia V1'!$EP$60 -> 230000000 | X144: =+'[1]CF Dia V1'!$EP$100 -> 1451818208 | Y144: =+'[1]CF Dia V1'!$EP$101 -> 7793890781 | Z144: =+Z143 -> 1.7932612e+08 | AA144: =+'[1]CF Dia V1'!$EP$102 -> 8316978266 | AB144: =+AB143 -> 1202456 | AC144: =+AC143 -> 16000000 | AD144: =+AD143 -> 245288.77 | AE144: =+AE143 -> 280000 | AF144: =+'[1]CF Dia V1'!$EP$97 -> 33977535 | AG144: =+AG143 -> 5582721359 | AH144: =+'[1]CF Dia V1'!$EP$24+'[1]CF Dia V1'!$EP$25 -> 1169194650 | AI144: =+'[1]CF Dia V1'!$EP$29 -> 7347099760
A145: 46247 | B145: 1490.5 | D145: 416151000 | E145: -17616000 | F145: 86071000 | G145: 6835000 | H145: 5147000 | I145: 1922934000 | J145: 285000002 | L145: 11953410 | P145: 6189916 | Q145: 142015347 | U145: 50000000 | X145: 1191559852 | Y145: 9351103483 | Z145: =+Z144 -> 1.7932612e+08 | AA145: 8683893033 | AB145: =+AB144 -> 1202456 | AC145: =+AC144 -> 16000000 | AD145: =+AD144 -> 245288.77 | AE145: =+AE144 -> 280000 | AF145: 32411352 | AG145: =+AG144 -> 5582721359 | AH145: =+'[1]CF Dia V1'!$ER$24+'[1]CF Dia V1'!$ER$25 -> 2.2416004e+09 | AI145: =+'[1]CF Dia V1'!$ER$29 -> 7.1427994e+09
A146: 46248 | B146: 1488.5 | D146: 290253000 | E146: 224553000 | F146: 86071000 | G146: 15740000 | H146: 3533000 | I146: 1637573000 | J146: 644058175 | L146: =14794057+1334000 -> 16128057 | P146: 17576906 | Q146: 523853458 | X146: 1225604256 | Y146: 8816725589 | Z146: =+Z145 -> 1.7932612e+08 | AA146: 6804950184 | AB146: =+AB145 -> 1202456 | AC146: =+AC145 -> 16000000 | AD146: =+AD145 -> 245288.77 | AE146: =+AE145 -> 280000 | AF146: 32294565 | AG146: =+AG145 -> 5582721359 | AH146: =+'[1]CF Dia V1'!$ES$24+'[1]CF Dia V1'!$ES$25 -> 2.0993223e+09 | AI146: =+'[1]CF Dia V1'!$ES$29 -> 7.8245459e+09
A147: 46252 | B147: 1485 | D147: =+'[1]CF Dia V1'!$ET$10 -> 290253000 | E147: =+'[1]CF Dia V1'!$ET$13 -> 132315000 | F147: =+'[1]CF Dia V1'!$ET$16 -> 77700000 | G147: 15400000 | H147: 2787000 | I147: =+'[1]CF Dia V1'!$ET$22 -> 2028061000 | J147: =+'[1]CF Dia V1'!$ET$43 -> 258816904 | L147: =+'[1]CF Dia V1'!$ET$46 -> 170517366 | P147: =+'[1]CF Dia V1'!$ET$50 -> 10174295 | Q147: =+'[1]CF Dia V1'!$ET$51 -> 2789923 | X147: =+'[1]CF Dia V1'!$ET$100 -> 965630051 | Y147: =+'[1]CF Dia V1'!$ET$101 -> 8041036677 | Z147: =+Z146 -> 1.7932612e+08 | AA147: =+'[1]CF Dia V1'!$ET$102 -> 6960719090 | AB147: 1562000 | AC147: 16000000 | AD147: =+AD146 -> 245288.77 | AE147: =+AE146 -> 280000 | AF147: =+'[1]CF Dia V1'!$ET$97 -> 33167572 | AG147: =+AG146 -> 5582721359 | AH147: =+'[1]CF Dia V1'!$ET$24+'[1]CF Dia V1'!$ET$25 -> 1360047645 | AI147: =+'[1]CF Dia V1'!$ET$29 -> 9529757325
A148: 46253 | B148: 1490 | D148: =+'[1]CF Dia V1'!$EU$10 -> 636298000 | E148: =+'[1]CF Dia V1'!$EU$13 -> 15444000 | F148: =+'[1]CF Dia V1'!$EU$16 -> 1700000 | G148: =+'[1]CF Dia V1'!$EU$14 -> 15400000 | H148: =+'[1]CF Dia V1'!$EU$15 -> 1981000 | I148: =+'[1]CF Dia V1'!$EU$22 -> 1578577000 | J148: =+'[1]CF Dia V1'!$EU$43 -> 332793215 | L148: =+'[1]CF Dia V1'!$EU$46 -> 107087250 | Q148: =+'[1]CF Dia V1'!$EU$51 -> 565997992 | X148: =+'[1]CF Dia V1'!$EU$100 -> 666408280 | Y148: =+'[1]CF Dia V1'!$EU$101 -> 7680124907 | Z148: =+Z147 -> 1.7932612e+08 | AA148: =+'[1]CF Dia V1'!$EU$102 -> 7307278803 | AB148: =+AB147 -> 1562000 | AC148: =+AC147 -> 16000000 | AD148: =+AD147 -> 245288.77 | AE148: =+AE147 -> 280000 | AF148: =+'[1]CF Dia V1'!$EU$97 -> 32207178 | AG148: =+AG147 -> 5582721359 | AH148: =+'[1]CF Dia V1'!$EU$24+'[1]CF Dia V1'!$EU$25 -> 1371440700 | AI148: =+'[1]CF Dia V1'!$EU$29 -> 9416998170
A149: 46254 | B149: 1494 | D149: 652234000 | E149: 106188000 | F149: 23454000 | G149: 5373000 | H149: 887898000 | I149: 1562105837 | J149: 497678816 | L149: 4951414 | P149: 0 | Q149: 45507216 | X149: 900747754 | Y149: 7370445877 | Z149: =+Z148 -> 1.7932612e+08 | AA149: 6456273353 | AB149: =+AB148 -> 1562000 | AC149: 16800000 | AD149: =+AD148 -> 245288.77 | AE149: =+AE148 -> 280000 | AF149: =+'[1]CF Dia V1'!$EV$97 -> 35762062 | AG149: =+AG148 -> 5582721359 | AH149: =+'[1]CF Dia V1'!$EV$24+'[1]CF Dia V1'!$EV$25 -> 789543144 | AI149: =+'[1]CF Dia V1'!$EV$29 -> 9477118782
A150: 46255 | B150: 1494 | D150: 842000000 | E150: 48084000 | F150: 22551000 | G150: 30000000 | H150: 277343000 | I150: 1556464612 | J150: 369070003 | L150: 0 | P150: 935838954 | Q150: 17791074 | X150: 556318566 | Y150: 6558923582 | Z150: =+Z149 -> 1.7932612e+08 | AA150: 6755356465 | AB150: =+AB149 -> 1562000 | AC150: 16800000 | AD150: =+AD149 -> 245288.77 | AE150: =+AE149 -> 280000 | AF150: =+'[1]CF Dia V1'!$EW$97 -> 34024200 | AG150: =+AG149 -> 5582721359 | AH150: =+'[1]CF Dia V1'!$EW$24+'[1]CF Dia V1'!$EW$25 -> 989775000 | AI150: =+'[1]CF Dia V1'!$EW$29 -> 9477118782
A151: 46258 | B151: 1494 | D151: =+'[1]CF Dia V1'!$EX$10 -> 808785000 | E151: =+'[1]CF Dia V1'!$EX$13 -> -149731000 | F151: =+'[1]CF Dia V1'!$EX$16 -> 22000000 | G151: =+'[1]CF Dia V1'!$EX$14 -> 853000 | H151: =+'[1]CF Dia V1'!$EX$15 -> 277343000 | I151: =+'[1]CF Dia V1'!$EX$22 -> 1179389844 | J151: =+'[1]CF Dia V1'!$EX$43 -> 306425692 | L151: =+'[1]CF Dia V1'!$EX$46 -> 46132000 | P151: =+'[1]CF Dia V1'!$EX$50 -> 20950945 | Q151: =+'[1]CF Dia V1'!$EX$51 -> 107854200 | X151: =+'[1]CF Dia V1'!$EX$100 -> 5.1263787e+08 | Y151: =+'[1]CF Dia V1'!$EX$101 -> 6504858243 | Z151: =+Z150 -> 1.7932612e+08 | AA151: =+'[1]CF Dia V1'!$EX$102 -> 8284777830 | AB151: =+AB150 -> 1562000 | AC151: 17800000 | AD151: =+AD150 -> 245288.77 | AE151: =+AE150 -> 280000 | AF151: =+'[1]CF Dia V1'!$EX$97 -> 34329322 | AG151: =+AG150 -> 5582721359 | AH151: =+'[1]CF Dia V1'!$EX$24 -> 171460404 | AI151: =+'[1]CF Dia V1'!$EX$29 -> 9505917126 | AJ151: =+'[1]CF Dia V1'!$EX$31 -> 1191838968
A152: 46259 | B152: 1505 | D152: =+'[1]CF Dia V1'!$EY$10 -> 822623000 | E152: =+'[1]CF Dia V1'!$EY$13 -> 141038000 | F152: =+'[1]CF Dia V1'!$EY$16 -> 24000000 | G152: =+'[1]CF Dia V1'!$EY$14 -> 2397000 | H152: =+'[1]CF Dia V1'!$EY$15 -> 7343000 | I152: =+'[1]CF Dia V1'!$EY$22 -> 1165551444 | J152: =+'[1]CF Dia V1'!$EY$43 -> 57614176 | L152: =+'[1]CF Dia V1'!$EY$46 -> 158407969 | O152: =+'[1]CF Dia V1'!$EY$49 -> 7495412 | Q152: =+'[1]CF Dia V1'!$EY$51 -> 20850000 | X152: =+'[1]CF Dia V1'!$EY$100 -> 609168000 | Y152: =+'[1]CF Dia V1'!$EY$101 -> 6923980045 | Z152: =+Z151 -> 1.7932612e+08 | AA152: =+'[1]CF Dia V1'!$EY$102 -> 7816267342 | AB152: =+AB151 -> 1562000 | AC152: =+AC151 -> 17800000 | AD152: =+AD151 -> 245288.77 | AE152: =+AE151 -> 280000 | AF152: =+'[1]CF Dia V1'!$EY$97 -> 35001310 | AG152: =+AG151 -> 5582721359 | AH152: =+'[1]CF Dia V1'!$EY$24 -> 610691375 | AI152: =+'[1]CF Dia V1'!$EY$29 -> 9291260475 | AJ152: =+'[1]CF Dia V1'!$EY$31 -> 692194923
A153: =+A152+1 -> 46260 | B153: 1508 | D153: 503000000 | E153: 249951000 | F153: 980000000 | G153: 2219000 | H153: 5524000 | I153: 1165000000 | J153: 235962163 | L153: 5123717 | O153: 4487184 | P153: 236749728 | Q153: 229759453 | X153: 944817063 | Y153: 6433854244 | Z153: =+Z152 -> 1.7932612e+08 | AA153: 8.0277765e+09 | AB153: =+AB152 -> 1562000 | AC153: =+AC152 -> 17800000 | AD153: =+AD152 -> 245288.77 | AE153: =+AE152 -> 280000 | AF153: =+'[1]CF Dia V1'!$EZ$97 -> 32475209 | AG153: =+AG152 -> 5582721359 | AH153: =+'[1]CF Dia V1'!$EZ$24+'[1]CF Dia V1'!$EZ$25 -> 700488620 | AI153: =+'[1]CF Dia V1'!$EZ$29 -> 9349600000 | AJ153: =+'[1]CF Dia V1'!$EZ$31 -> 342368000
A154: =+A153+1 -> 46261 | B154: 1510 | D154: 108000000 | E154: 139773000 | F154: 983000000 | G154: 2547000 | H154: 5524000 | I154: 1502000000 | J154: 213862279 | L154: 14148020 | O154: 2199600 | Q154: 121642988 | X154: 786422165 | Y154: 6553854244 | Z154: =+Z153 -> 1.7932612e+08 | AA154: 7969027248 | AB154: =+AB153 -> 1562000 | AC154: =+AC153 -> 17800000 | AD154: =+AD153 -> 245288.77 | AE154: =+AE153 -> 280000 | AF154: =+'[1]CF Dia V1'!$FA$97 -> 32880196 | AG154: =+AG153 -> 5582721359 | AH154: =+'[1]CF Dia V1'!$FA$24+'[1]CF Dia V1'!$FA$25 -> 2367378000 | AI154: =+'[1]CF Dia V1'!$FA$29 -> 8568276050
A155: =+A154+1 -> 46262 | B155: 1510 | D155: 144000000 | E155: 27615107 | F155: 623000000 | G155: 1948000 | H155: 5422000 | I155: 1411612000 | J155: 316999977 | L155: 0 | Q155: 318251478 | X155: 786422165 | Y155: 6886479895 | Z155: =+Z154 -> 1.7932612e+08 | AA155: =+AA154 -> 7969027248 | AB155: =+AB154 -> 1562000 | AC155: =+AC154 -> 17800000 | AD155: =+AD154 -> 245288.77 | AE155: =+AE154 -> 280000 | AF155: =+'[1]CF Dia V1'!$FB$97 -> 32912551 | AG155: =+AG154 -> 5582721359 | AH155: =+'[1]CF Dia V1'!$FB$24+'[1]CF Dia V1'!$FB$25 -> 2809468250 | AI155: =+'[1]CF Dia V1'!$FB$29 -> 8519420000
A156: =+A155+3 -> 46265 | B156: 1510.5 | D156: 0 | E156: 274849000 | F156: 3924000 | G156: 9554000 | H156: 969000 | I156: 1387349000 | J156: 332625651 | L156: 11135485 | Q156: 213884973 | X156: 726565688 | Y156: 13577822892 | Z156: =+Z155 -> 1.7932612e+08 | AA156: 7678749522 | AB156: =+AB155 -> 1562000 | AC156: =+AC155 -> 17800000 | AD156: =+AD155 -> 245288.77 | AE156: =+AE155 -> 280000 | AF156: =+'[1]CF Dia V1'!$FC$97 -> 33013997 | AG156: =+AG155 -> 5582721359 | AH156: =+'[1]CF Dia V1'!$FC$24+'[1]CF Dia V1'!$FC$25 -> 3150338073 | AI156: =+'[1]CF Dia V1'!$FC$29 -> 8712974856
A157: 46266 | B157: 1506 | D157: 16000000 | E157: =+'[1]CF Dia V1'!$FD$13 -> 604000 | F157: =+F156 -> 3924000 | G157: =+'[1]CF Dia V1'!$FD$14 -> 8107000 | H157: =+'[1]CF Dia V1'!$FD$15 -> 2967000 | I157: =+'[1]CF Dia V1'!$FD$22 -> 1387349000 | J157: =+'[1]CF Dia V1'!$FD$43 -> 181112077 | L157: =+'[1]CF Dia V1'!$FD$46 -> 51477136 | Q157: =+'[1]CF Dia V1'!$FD$51 -> 169418024 | U157: =+'[1]CF Dia V1'!$FD$60 -> 180000000 | X157: =+'[1]CF Dia V1'!$FD$100 -> 706516864 | Y157: =+'[1]CF Dia V1'!$FD$101 -> 13329945213 | Z157: =+Z156 -> 1.7932612e+08 | AA157: =+'[1]CF Dia V1'!$FD$102 -> 7550543000 | AB157: =+AB156 -> 1562000 | AC157: =+AC156 -> 17800000 | AD157: =+AD156 -> 245288.77 | AE157: =+AE156 -> 280000 | AF157: =+'[1]CF Dia V1'!$FD$97 -> 34505020 | AG157: =+AG156 -> 5582721359 | AH157: =+'[1]CF Dia V1'!$FD$24+'[1]CF Dia V1'!$FD$25 -> 3039638112 | AI157: =+'[1]CF Dia V1'!$FD$29 -> 8628895068
A158: =+A157+1 -> 46267 | B158: 1509 | D158: 37490000 | E158: 340432000 | F158: 3821000 | G158: 3760000 | H158: 118000 | I158: 1422868000 | J158: 274322161 | L158: 52009050 | P158: 0 | Q158: 167270769 | U158: 85000000 | X158: 1.6455693e+09 | Y158: 13225547662 | Z158: =+Z157 -> 1.7932612e+08 | AA158: 7550543000 | AB158: =+AB157 -> 1562000 | AC158: =+AC157 -> 17800000 | AD158: =+AD157 -> 245288.77 | AE158: =+AE157 -> 280000 | AF158: =+'[1]CF Dia V1'!$FE$97 -> 36005239 | AG158: =+AG157 -> 5582721359 | AH158: =+'[1]CF Dia V1'!$FE$24+'[1]CF Dia V1'!$FE$25 -> 2647628022 | AI158: =+'[1]CF Dia V1'!$FE$29 -> 8734117653
A159: =+A158+1 -> 46268 | B159: 1509 | D159: 190280000 | E159: 190272000 | F159: 3821000 | G159: 4220000 | H159: 594000 | I159: 1127963988 | J159: 178000000 | L159: 17421610 | P159: 8931568 | Q159: 172415674 | U159: 0 | X159: 1.4589731e+09 | Y159: 13058165815 | Z159: =+Z158 -> 1.7932612e+08 | AA159: 7127444966 | AB159: =+AB158 -> 1562000 | AC159: =+AC158 -> 17800000 | AD159: =+AD158 -> 245288.77 | AE159: =+AE158 -> 280000 | AF159: =+'[1]CF Dia V1'!$FF$97 -> 33243349 | AG159: =+AG158 -> 5582721359 | AH159: =+'[1]CF Dia V1'!$FF$24+'[1]CF Dia V1'!$FF$25 -> 2870717073 | AI159: =+'[1]CF Dia V1'!$FF$29 -> 8097476589
A160: =+'[1]CF Dia V1'!$FG$1 -> 46269 | B160: =+'[1]CF Dia V1'!$FG$2 -> 1505.5 | D160: =+'[1]CF Dia V1'!$FG$10 -> 190280000 | E160: =+'[1]CF Dia V1'!$FG$13 -> 58017000 | F160: =+'[1]CF Dia V1'!$FG$16 -> 3821000 | G160: =+'[1]CF Dia V1'!$FG$14 -> 44344000 | H160: =+'[1]CF Dia V1'!$FG$15 -> 2203000 | I160: =+'[1]CF Dia V1'!$FG$22 -> 1127963988 | J160: =+'[1]CF Dia V1'!$FG$43 -> 45290335 | Q160: =+'[1]CF Dia V1'!$FG$51 -> 688777988 | V160: =+'[1]CF Dia V1'!$FG$73 -> 130500000 | X160: =+'[1]CF Dia V1'!$FG$100 -> 1504790455 | Y160: =+'[1]CF Dia V1'!$FG$101 -> 12353842398 | Z160: =+Z159 -> 1.7932612e+08 | AA160: =+AA159 -> 7127444966 | AB160: =+AB159 -> 1562000 | AC160: =+AC159 -> 17800000 | AD160: =+AD159 -> 245288.77 | AE160: =+AE159 -> 280000 | AF160: =+'[1]CF Dia V1'!$FG$97 -> 32031098 | AG160: =+AG159 -> 5582721359 | AH160: =+'[1]CF Dia V1'!$FG$24+'[1]CF Dia V1'!$FG$25 -> 3085793240 | AI160: =+'[1]CF Dia V1'!$FG$29 -> 8070931302
A161: 46272 | B161: 1504 | D161: =+'[1]CF Dia V1'!$FH$10 -> 204000000 | E161: =+'[1]CF Dia V1'!$FH$13 -> 113928000 | F161: =+'[1]CF Dia V1'!$FH$16 -> 4016000 | G161: =+'[1]CF Dia V1'!$FH$14 -> 41937000 | H161: =+'[1]CF Dia V1'!$FH$15 -> 3370000 | I161: =+'[1]CF Dia V1'!$FH$22 -> 1386769447 | J161: =+'[1]CF Dia V1'!$FH$43 -> 336815052 | L161: =+'[1]CF Dia V1'!$FH$46 -> 212885656 | P161: =+'[1]CF Dia V1'!$FH$50 -> 12611780 | Q161: =+'[1]CF Dia V1'!$FH$51 -> 338853719 | X161: =+'[1]CF Dia V1'!$FH$100 -> 1248071376 | Y161: =+'[1]CF Dia V1'!$FH$101 -> 11735279712 | Z161: =+Z160 -> 1.7932612e+08 | AA161: =+'[1]CF Dia V1'!$FH$102 -> 6.953976e+09 | AB161: =+'[1]CF Dia V1'!$FH$103 -> 1745997.6 | AC161: =+AC160 -> 17800000 | AD161: =+AD160 -> 245288.77 | AE161: =+PRESTAMOS_USD!G22 -> 325287.76 | AF161: =+'[1]CF Dia V1'!$FH$97 -> 31412097 | AG161: =+AG160 -> 5582721359 | AH161: =+'[1]CF Dia V1'!$FH$24+'[1]CF Dia V1'!$FH$25 -> 1292460896 | AI161: =+'[1]CF Dia V1'!$FH$29 -> 9475210528 | AJ161: =+'[1]CF Dia V1'!$FH$31 -> 1507317626
A162: 46273 | B162: 1509 | D162: =+'[1]CF Dia V1'!$FI$10 -> 415424000 | E162: =+'[1]CF Dia V1'!$FI$13 -> 164014000 | F162: =+'[1]CF Dia V1'!$FI$16 -> 4441000 | G162: =+'[1]CF Dia V1'!$FI$14 -> 4649000 | H162: =+'[1]CF Dia V1'!$FI$15 -> 12518000 | I162: =+'[1]CF Dia V1'!$FI$22 -> 1142598325 | J162: =+'[1]CF Dia V1'!$FI$43 -> 424319420 | L162: =+'[1]CF Dia V1'!$FI$46 -> 19575338 | P162: =+'[1]CF Dia V1'!$FI$50 -> 31902411 | Q162: =+'[1]CF Dia V1'!$FI$51 -> 156151989 | U162: =+'[1]CF Dia V1'!$FI$59 -> 160000000 | X162: =+'[1]CF Dia V1'!$FI$100 -> 865293563 | Y162: =+'[1]CF Dia V1'!$FI$101 -> 11387545619 | Z162: =+Z161 -> 1.7932612e+08 | AA162: =+'[1]CF Dia V1'!$FI$102 -> 6960467958 | AB162: =+AB161 -> 1745997.6 | AC162: =+AC161 -> 17800000 | AD162: =+AD161 -> 245288.77 | AE162: =+AE161 -> 325287.76 | AF162: =+'[1]CF Dia V1'!$FI$97 -> 32336779 | AG162: =+AG161 -> 5582721359 | AH162: =+'[1]CF Dia V1'!$FI$24+'[1]CF Dia V1'!$FI$25 -> 1311847641 | AI162: =+'[1]CF Dia V1'!$FI$29 -> 9314471508 | AJ162: =+'[1]CF Dia V1'!$FI$31 -> 607633370
A163: 46274 | B163: 1505.5 | D163: =+'[1]CF Dia V1'!$FJ$10 -> 306408000 | E163: =+'[1]CF Dia V1'!$FJ$13 -> 83668000 | F163: =+'[1]CF Dia V1'!$FJ$16 -> 39458000 | G163: =+'[1]CF Dia V1'!$FJ$14 -> 7582000 | H163: =+'[1]CF Dia V1'!$FJ$15 -> 12518000 | I163: =+'[1]CF Dia V1'!$FJ$22 -> 896745000 | J163: =+'[1]CF Dia V1'!$FJ$43 -> 2939544 | P163: =+'[1]CF Dia V1'!$FJ$50 -> 2227081286 | Q163: =+'[1]CF Dia V1'!$FJ$51 -> 257288219 | X163: =+'[1]CF Dia V1'!$FJ$100 -> 989741585 | Y163: =+'[1]CF Dia V1'!$FJ$101 -> 8774851720 | Z163: =+Z162 -> 1.7932612e+08 | AA163: =+'[1]CF Dia V1'!$FJ$102 -> 6796061384 | AB163: =+AB162 -> 1745997.6 | AC163: =+AC162 -> 17800000 | AD163: =+AD162 -> 245288.77 | AE163: =+AE162 -> 325287.76 | AF163: =+'[1]CF Dia V1'!$FJ$97 -> 33644452 | AG163: =+AG162 -> 5582721359 | AH163: =+'[1]CF Dia V1'!$FJ$24+'[1]CF Dia V1'!$FJ$25 -> 5.7591894e+09 | AI163: =+'[1]CF Dia V1'!$FJ$29 -> 8877075365
A164: 46275 | B164: 1513 | D164: =+'[1]CF Dia V1'!$FK$10 -> 197414000 | E164: =+'[1]CF Dia V1'!$FK$13 -> 29553000 | F164: =+'[1]CF Dia V1'!$FK$16 -> 33460000 | G164: =+'[1]CF Dia V1'!$FK$14 -> 10200000 | H164: =+'[1]CF Dia V1'!$FK$15 -> 5230000 | I164: =+'[1]CF Dia V1'!$FK$22 -> 896745000 | J164: =+'[1]CF Dia V1'!$FK$43 -> 63214078 | P164: =+'[1]CF Dia V1'!$FK$50 -> 159022936 | Q164: =+'[1]CF Dia V1'!$FK$51 -> 564628974 | X164: =+'[1]CF Dia V1'!$FK$100 -> 1.4518654e+09 | Y164: =+'[1]CF Dia V1'!$FK$101 -> 7581875038 | Z164: =+Z163 -> 1.7932612e+08 | AA164: =+'[1]CF Dia V1'!$FK$102 -> 7878950730 | AB164: =+AB163 -> 1745997.6 | AC164: =+AC163 -> 17800000 | AD164: =+AD163 -> 245288.77 | AE164: =+AE163 -> 325287.76 | AF164: =+'[1]CF Dia V1'!$FK$97 -> 30931429 | AG164: =+AG163 -> 5582721359 | AH164: =+'[1]CF Dia V1'!$FK$24+'[1]CF Dia V1'!$FK$25 -> 3718071921 | AI164: =+'[1]CF Dia V1'!$FK$29 -> 9498361329
A165: 46276 | B165: =+'[1]CF Dia V1'!$FL$2 -> 1509 | D165: =+'[1]CF Dia V1'!$FL$10 -> 358410581 | E165: =+'[1]CF Dia V1'!$FL$13 -> 58387000 | F165: =+'[1]CF Dia V1'!$FL$16 -> 3800000 | G165: =+'[1]CF Dia V1'!$FL$14 -> 6513000 | H165: =+'[1]CF Dia V1'!$FL$15 -> 4141000 | I165: =+'[1]CF Dia V1'!$FL$22 -> 1107000000 | J165: =+'[1]CF Dia V1'!$FL$43 -> 121593571 | L165: =+'[1]CF Dia V1'!$FL$46 -> 6074370 | P165: =+'[1]CF Dia V1'!$FL$49 -> 2199600 | Q165: =+'[1]CF Dia V1'!$FL$51 -> 516948396 | X165: =+'[1]CF Dia V1'!$FL$100 -> 1852178279 | Y165: =+'[1]CF Dia V1'!$FL$101 -> 7471140512 | Z165: =+Z164 -> 1.7932612e+08 | AA165: =+'[1]CF Dia V1'!$FL$102 -> 7301555646 | AB165: =+AB164 -> 1745997.6 | AC165: =+AC164 -> 17800000 | AD165: =+AD164 -> 245288.77 | AE165: =+AE164 -> 325287.76 | AF165: =+'[1]CF Dia V1'!$FL$97 -> 31810522 | AG165: =+AG164 -> 5582721359 | AH165: =+'[1]CF Dia V1'!$FL$24+'[1]CF Dia V1'!$FL$25 -> 3014877879 | AI165: =+'[1]CF Dia V1'!$FL$29 -> 9129388131
A166: 46279 | B166: 1505 | D166: =+'[1]CF Dia V1'!$FM$10 -> 257838877 | E166: =+'[1]CF Dia V1'!$FM$13 -> 64789000 | F166: =+'[1]CF Dia V1'!$FM$16 -> 3807000 | G166: =+'[1]CF Dia V1'!$FM$14 -> 6569000 | H166: =+'[1]CF Dia V1'!$FM$15 -> 3637000 | I166: =+'[1]CF Dia V1'!$FM$22 -> 1107165633 | J166: =+'[1]CF Dia V1'!$FM$43 -> 421929408 | P166: =+'[1]CF Dia V1'!$FM$50 -> 11201980 | Q166: =+'[1]CF Dia V1'!$FM$51 -> 240753608 | X166: =+'[1]CF Dia V1'!$FM$100 -> 1779462460 | Y166: =+'[1]CF Dia V1'!$FM$101 -> 6505310688 | Z166: =+Z165 -> 1.7932612e+08 | AA166: =+'[1]CF Dia V1'!$FM$102 -> 7447795635 | AB166: =+AB165 -> 1745997.6 | AC166: =+AC165 -> 17800000 | AD166: =+AD165 -> 245288.77 | AE166: =+AE165 -> 325287.76 | AF166: =+'[1]CF Dia V1'!$FM$97 -> 32543316 | AG166: =+AG165 -> 5582721359 | AH166: =+'[1]CF Dia V1'!$FM$24+'[1]CF Dia V1'!$FM$25 -> 2414214000 | AI166: =+'[1]CF Dia V1'!$FM$29 -> 9117288213
...

Sheet CREDITOS_EXTERIOR
A1: CRÉDITOS POR VENTAS AL EXTERIOR — Facturas de exportación pendientes de cobro
A2: N° Factura | B2: Cliente (País) | C2: Fecha Factura | D2: Fecha Vto. | E2: Días al vto. | F2: Monto (USD) | G2: TC estimado | H2: ARS equivalente | I2: Estado
A3: EXP-2026-041 | B3: Nordic Fish AS (Noruega) | C3: 46096 | D3: 46157 | E3: =IFERROR(D3-TODAY(),"") -> -164 | F3: 320000 | G3: 1197 | H3: =IFERROR(F3*G3,0) -> 383040000 | I3: Pendiente
A4: EXP-2026-055 | B4: Iberian Seafood SL (España) | C4: 46113 | D4: 46172 | E4: =IFERROR(D4-TODAY(),"") -> -149 | F4: 185000 | G4: 1197 | H4: =IFERROR(F4*G4,0) -> 221445000 | I4: Pendiente
A5: EXP-2026,062 | B5: Ocean Trade LLC (EEUU) | C5: 46122 | D5: 46183 | E5: =IFERROR(D5-TODAY(),"") -> -138 | F5: 240000 | G5: 1197 | H5: =IFERROR(F5*G5,0) -> 287280000 | I5: Pendiente
A6: EXP-2026-071 | B6: Maruha Nichiro (Japón) | C6: 46132 | D6: 46193 | E6: =IFERROR(D6-TODAY(),"") -> -128 | F6: 495000 | G6: 1197 | H6: =IFERROR(F6*G6,0) -> 592515000 | I6: Pendiente

Sheet DIVISAS
A1: DIVISAS DISPONIBLES — Seguimiento diario de posición en USD
A2: Fecha | B2: TC BNA | C2: Patag. (USD) | D2: Francés (USD) | E2: Total USD | F2: Liquidado hoy (USD)
A3: 46140 | B3: 1194 | C3: 285000 | D3: 140000 | E3: =C3+D3 -> 425000 | F3: 87000
A4: 46141 | B4: 1196 | C4: 268000 | D4: 135000 | E4: =C4+D4 -> 403000 | F4: 72000
A5: 46142 | B5: 1197 | C5: 301000 | D5: 148000 | E5: =C5+D5 -> 449000 | F5: 95000
A6: 46144 | B6: 1198.5 | C6: 275000 | D6: 128000 | E6: =C6+D6 -> 403000 | F6: 68000
A7: 46147 | B7: 1197 | C7: 285000 | D7: 140000 | E7: =C7+D7 -> 425000 | F7: 87000

Sheet VENCIMIENTOS
A1: VENCIMIENTOS — Cheques a cobrar y compromisos de pago próximos
A2: Ingresá cada cheque o compromiso con su fecha exacta. El dashboard lo muestra en el calendario de vencimientos.
A3: Fecha | B3: Tipo | C3: Descripción / Contraparte | D3: Monto (ARS) | E3: TC del día | F3: Monto (USD) | G3: Estado
A4: 46148 | B4: COBRO | C4: Cheque acreditación — Cliente Norte | D4: 42000000 | E4: 1197 | F4: =IFERROR(D4/E4,0) -> 35087.719 | G4: Pendiente
A5: 46149 | B5: PAGO | C5: Proveedor Pescadores del Sur | D5: 87000000 | E5: 1197 | F5: =IFERROR(D5/E5,0) -> 72681.704 | G5: Pendiente
A6: 46150 | B6: COBRO | C6: Cheque — Distribuidora Atlántica | D6: 65000000 | E6: 1197 | F6: =IFERROR(D6/E6,0) -> 54302.423 | G6: Pendiente
A7: 46151 | B7: PAGO | C7: Cuota préstamo Banco Galicia | D7: 48500000 | E7: 1197 | F7: =IFERROR(D7/E7,0) -> 40517.962 | G7: Pendiente
A8: 46152 | B8: COBRO | C8: Cobro exportación (USD 95.000) | D8: 113715000 | E8: 1197 | F8: =IFERROR(D8/E8,0) -> 95000 | G8: Pendiente
A9: 46152 | B9: PAGO | C9: RRHH — sueldos quincena | D9: 96000000 | E9: 1197 | F9: =IFERROR(D9/E9,0) -> 80200.501 | G9: Pendiente
A10: 46154 | B10: PAGO | C10: Arancel / canon mensual | D10: 23000000 | E10: 1197 | F10: =IFERROR(D10/E10,0) -> 19214.703 | G10: Pendiente
A11: 46157 | B11: COBRO | C11: Cheque — Exportadora Patagónica | D11: 145000000 | E11: 1197 | F11: =IFERROR(D11/E11,0) -> 121136.17 | G11: Pendiente
A12: 46162 | B12: PAGO | C12: Deuda proveedor exterior (USD 80.000) | D12: 95760000 | E12: 1197 | F12: =IFERROR(D12/E12,0) -> 80000 | G12: Pendiente

Sheet POSICION_NETA
A1: POSICIÓN FINANCIERA NETA DIARIA | Valores en USD (conversión automática)
A2: ⚠ Hoja de cálculo automática — No modificar. Los datos vienen de CARGA_DIARIA.
A3: Fecha | B3: TC BNA | C3: Activo Corriente (USD) | D3: Gastos del Día (USD) | E3: Pasivo Corriente (USD) | F3: Ajustes + (incluido en Activo) | G3: Ajustes - (incluido en Activo) | H3: POSICIÓN NETA (USD)
A4: =IF(CARGA_DIARIA!A4="","",CARGA_DIARIA!A4) -> 46029 | B4: =IF(CARGA_DIARIA!A4="","",CARGA_DIARIA!B4) -> 1463 | C4: =IF(CARGA_DIARIA!A4="","",IF(CARGA_DIARIA!B4=0,0,(CARGA_DIARIA!C4+CARGA_DIARIA!D4+CARGA_DIARIA!E4+CARGA_DIARIA!F4+CARGA_DIARIA!G4+CARGA_DIARIA!H4+CARGA_DIARIA!I4+CARGA_DIARIA!AG4+CARGA_DIARIA!AH4+CARGA_DIARIA!AI4+CARGA_DIARIA!AJ4)/CARGA_DIARIA!B4+CARGA_DIARIA!AF4)) -> 19059124 | D4: =IF(CARGA_DIARIA!A4="","",IF(CARGA_DIARIA!B4=0,0,(CARGA_DIARIA!J4+CARGA_DIARIA!K4+CARGA_DIARIA!L4+CARGA_DIARIA!M4+CARGA_DIARIA!N4+CARGA_DIARIA!O4+CARGA_DIARIA!P4+CARGA_DIARIA!Q4+CARGA_DIARIA!R4+CARGA_DIARIA!S4+CARGA_DIARIA!T4+CARGA_DIARIA!U4+CARGA_DIARIA!V4+CARGA_DIARIA!W4)/CARGA_DIARIA!B4)) -> 290132.8 | E4: =IF(CARGA_DIARIA!A4="","",IF(CARGA_DIARIA!B4=0,0,(CARGA_DIARIA!X4+CARGA_DIARIA!Y4+CARGA_DIARIA!Z4+CARGA_DIARIA!AA4)/CARGA_DIARIA!B4+CARGA_DIARIA!AB4+CARGA_DIARIA!AC4+CARGA_DIARIA!AD4+CARGA_DIARIA!AE4)) -> 16746778 | F4: — | G4: — | H4: =IF(CARGA_DIARIA!A4="","",C4-D4-E4) -> 2022212.7
A5: =IF(CARGA_DIARIA!A5="","",CARGA_DIARIA!A5) -> 46030 | B5: =IF(CARGA_DIARIA!A5="","",CARGA_DIARIA!B5) -> 1469 | C5: =IF(CARGA_DIARIA!A5="","",IF(CARGA_DIARIA!B5=0,0,(CARGA_DIARIA!C5+CARGA_DIARIA!D5+CARGA_DIARIA!E5+CARGA_DIARIA!F5+CARGA_DIARIA!G5+CARGA_DIARIA!H5+CARGA_DIARIA!I5+CARGA_DIARIA!AG5+CARGA_DIARIA!AH5+CARGA_DIARIA!AI5+CARGA_DIARIA!AJ5)/CARGA_DIARIA!B5+CARGA_DIARIA!AF5)) -> 18101966 | D5: =IF(CARGA_DIARIA!A5="","",IF(CARGA_DIARIA!B5=0,0,(CARGA_DIARIA!J5+CARGA_DIARIA!K5+CARGA_DIARIA!L5+CARGA_DIARIA!M5+CARGA_DIARIA!N5+CARGA_DIARIA!O5+CARGA_DIARIA!P5+CARGA_DIARIA!Q5+CARGA_DIARIA!R5+CARGA_DIARIA!S5+CARGA_DIARIA!T5+CARGA_DIARIA!U5+CARGA_DIARIA!V5+CARGA_DIARIA!W5)/CARGA_DIARIA!B5)) -> 350053.34 | E5: =IF(CARGA_DIARIA!A5="","",IF(CARGA_DIARIA!B5=0,0,(CARGA_DIARIA!X5+CARGA_DIARIA!Y5+CARGA_DIARIA!Z5+CARGA_DIARIA!AA5)/CARGA_DIARIA!B5+CARGA_DIARIA!AB5+CARGA_DIARIA!AC5+CARGA_DIARIA!AD5+CARGA_DIARIA!AE5)) -> 16647892 | F5: — | G5: — | H5: =IF(CARGA_DIARIA!A5="","",C5-D5-E5) -> 1104020.9
A6: =IF(CARGA_DIARIA!A6="","",CARGA_DIARIA!A6) -> 46031 | B6: =IF(CARGA_DIARIA!A6="","",CARGA_DIARIA!B6) -> 1455 | C6: =IF(CARGA_DIARIA!A6="","",IF(CARGA_DIARIA!B6=0,0,(CARGA_DIARIA!C6+CARGA_DIARIA!D6+CARGA_DIARIA!E6+CARGA_DIARIA!F6+CARGA_DIARIA!G6+CARGA_DIARIA!H6+CARGA_DIARIA!I6+CARGA_DIARIA!AG6+CARGA_DIARIA!AH6+CARGA_DIARIA!AI6+CARGA_DIARIA!AJ6)/CARGA_DIARIA!B6+CARGA_DIARIA!AF6)) -> 18851671 | D6: =IF(CARGA_DIARIA!A6="","",IF(CARGA_DIARIA!B6=0,0,(CARGA_DIARIA!J6+CARGA_DIARIA!K6+CARGA_DIARIA!L6+CARGA_DIARIA!M6+CARGA_DIARIA!N6+CARGA_DIARIA!O6+CARGA_DIARIA!P6+CARGA_DIARIA!Q6+CARGA_DIARIA!R6+CARGA_DIARIA!S6+CARGA_DIARIA!T6+CARGA_DIARIA!U6+CARGA_DIARIA!V6+CARGA_DIARIA!W6)/CARGA_DIARIA!B6)) -> 93342.511 | E6: =IF(CARGA_DIARIA!A6="","",IF(CARGA_DIARIA!B6=0,0,(CARGA_DIARIA!X6+CARGA_DIARIA!Y6+CARGA_DIARIA!Z6+CARGA_DIARIA!AA6)/CARGA_DIARIA!B6+CARGA_DIARIA!AB6+CARGA_DIARIA!AC6+CARGA_DIARIA!AD6+CARGA_DIARIA!AE6)) -> 15918601 | F6: — | G6: — | H6: =IF(CARGA_DIARIA!A6="","",C6-D6-E6) -> 2839727
A7: =IF(CARGA_DIARIA!A7="","",CARGA_DIARIA!A7) -> 46034 | B7: =IF(CARGA_DIARIA!A7="","",CARGA_DIARIA!B7) -> 1465.5 | C7: =IF(CARGA_DIARIA!A7="","",IF(CARGA_DIARIA!B7=0,0,(CARGA_DIARIA!C7+CARGA_DIARIA!D7+CARGA_DIARIA!E7+CARGA_DIARIA!F7+CARGA_DIARIA!G7+CARGA_DIARIA!H7+CARGA_DIARIA!I7+CARGA_DIARIA!AG7+CARGA_DIARIA!AH7+CARGA_DIARIA!AI7+CARGA_DIARIA!AJ7)/CARGA_DIARIA!B7+CARGA_DIARIA!AF7)) -> 18930220 | D7: =IF(CARGA_DIARIA!A7="","",IF(CARGA_DIARIA!B7=0,0,(CARGA_DIARIA!J7+CARGA_DIARIA!K7+CARGA_DIARIA!L7+CARGA_DIARIA!M7+CARGA_DIARIA!N7+CARGA_DIARIA!O7+CARGA_DIARIA!P7+CARGA_DIARIA!Q7+CARGA_DIARIA!R7+CARGA_DIARIA!S7+CARGA_DIARIA!T7+CARGA_DIARIA!U7+CARGA_DIARIA!V7+CARGA_DIARIA!W7)/CARGA_DIARIA!B7)) -> 269697.4 | E7: =IF(CARGA_DIARIA!A7="","",IF(CARGA_DIARIA!B7=0,0,(CARGA_DIARIA!X7+CARGA_DIARIA!Y7+CARGA_DIARIA!Z7+CARGA_DIARIA!AA7)/CARGA_DIARIA!B7+CARGA_DIARIA!AB7+CARGA_DIARIA!AC7+CARGA_DIARIA!AD7+CARGA_DIARIA!AE7)) -> 16152946 | F7: — | G7: — | H7: =IF(CARGA_DIARIA!A7="","",C7-D7-E7) -> 2507577.1
A8: =IF(CARGA_DIARIA!A8="","",CARGA_DIARIA!A8) -> 46035 | B8: =IF(CARGA_DIARIA!A8="","",CARGA_DIARIA!B8) -> 1462 | C8: =IF(CARGA_DIARIA!A8="","",IF(CARGA_DIARIA!B8=0,0,(CARGA_DIARIA!C8+CARGA_DIARIA!D8+CARGA_DIARIA!E8+CARGA_DIARIA!F8+CARGA_DIARIA!G8+CARGA_DIARIA!H8+CARGA_DIARIA!I8+CARGA_DIARIA!AG8+CARGA_DIARIA!AH8+CARGA_DIARIA!AI8+CARGA_DIARIA!AJ8)/CARGA_DIARIA!B8+CARGA_DIARIA!AF8)) -> 19304446 | D8: =IF(CARGA_DIARIA!A8="","",IF(CARGA_DIARIA!B8=0,0,(CARGA_DIARIA!J8+CARGA_DIARIA!K8+CARGA_DIARIA!L8+CARGA_DIARIA!M8+CARGA_DIARIA!N8+CARGA_DIARIA!O8+CARGA_DIARIA!P8+CARGA_DIARIA!Q8+CARGA_DIARIA!R8+CARGA_DIARIA!S8+CARGA_DIARIA!T8+CARGA_DIARIA!U8+CARGA_DIARIA!V8+CARGA_DIARIA!W8)/CARGA_DIARIA!B8)) -> 275609.77 | E8: =IF(CARGA_DIARIA!A8="","",IF(CARGA_DIARIA!B8=0,0,(CARGA_DIARIA!X8+CARGA_DIARIA!Y8+CARGA_DIARIA!Z8+CARGA_DIARIA!AA8)/CARGA_DIARIA!B8+CARGA_DIARIA!AB8+CARGA_DIARIA!AC8+CARGA_DIARIA!AD8+CARGA_DIARIA!AE8)) -> 15935429 | F8: — | G8: — | H8: =IF(CARGA_DIARIA!A8="","",C8-D8-E8) -> 3093407.3
A9: =IF(CARGA_DIARIA!A9="","",CARGA_DIARIA!A9) -> 46036 | B9: =IF(CARGA_DIARIA!A9="","",CARGA_DIARIA!B9) -> 1464.5 | C9: =IF(CARGA_DIARIA!A9="","",IF(CARGA_DIARIA!B9=0,0,(CARGA_DIARIA!C9+CARGA_DIARIA!D9+CARGA_DIARIA!E9+CARGA_DIARIA!F9+CARGA_DIARIA!G9+CARGA_DIARIA!H9+CARGA_DIARIA!I9+CARGA_DIARIA!AG9+CARGA_DIARIA!AH9+CARGA_DIARIA!AI9+CARGA_DIARIA!AJ9)/CARGA_DIARIA!B9+CARGA_DIARIA!AF9)) -> 18887090 | D9: =IF(CARGA_DIARIA!A9="","",IF(CARGA_DIARIA!B9=0,0,(CARGA_DIARIA!J9+CARGA_DIARIA!K9+CARGA_DIARIA!L9+CARGA_DIARIA!M9+CARGA_DIARIA!N9+CARGA_DIARIA!O9+CARGA_DIARIA!P9+CARGA_DIARIA!Q9+CARGA_DIARIA!R9+CARGA_DIARIA!S9+CARGA_DIARIA!T9+CARGA_DIARIA!U9+CARGA_DIARIA!V9+CARGA_DIARIA!W9)/CARGA_DIARIA!B9)) -> 241159.25 | E9: =IF(CARGA_DIARIA!A9="","",IF(CARGA_DIARIA!B9=0,0,(CARGA_DIARIA!X9+CARGA_DIARIA!Y9+CARGA_DIARIA!Z9+CARGA_DIARIA!AA9)/CARGA_DIARIA!B9+CARGA_DIARIA!AB9+CARGA_DIARIA!AC9+CARGA_DIARIA!AD9+CARGA_DIARIA!AE9)) -> 15830370 | F9: — | G9: — | H9: =IF(CARGA_DIARIA!A9="","",C9-D9-E9) -> 2815560.9
A10: =IF(CARGA_DIARIA!A10="","",CARGA_DIARIA!A10) -> 46037 | B10: =IF(CARGA_DIARIA!A10="","",CARGA_DIARIA!B10) -> 1450 | C10: =IF(CARGA_DIARIA!A10="","",IF(CARGA_DIARIA!B10=0,0,(CARGA_DIARIA!C10+CARGA_DIARIA!D10+CARGA_DIARIA!E10+CARGA_DIARIA!F10+CARGA_DIARIA!G10+CARGA_DIARIA!H10+CARGA_DIARIA!I10+CARGA_DIARIA!AG10+CARGA_DIARIA!AH10+CARGA_DIARIA!AI10+CARGA_DIARIA!AJ10)/CARGA_DIARIA!B10+CARGA_DIARIA!AF10)) -> 19136047 | D10: =IF(CARGA_DIARIA!A10="","",IF(CARGA_DIARIA!B10=0,0,(CARGA_DIARIA!J10+CARGA_DIARIA!K10+CARGA_DIARIA!L10+CARGA_DIARIA!M10+CARGA_DIARIA!N10+CARGA_DIARIA!O10+CARGA_DIARIA!P10+CARGA_DIARIA!Q10+CARGA_DIARIA!R10+CARGA_DIARIA!S10+CARGA_DIARIA!T10+CARGA_DIARIA!U10+CARGA_DIARIA!V10+CARGA_DIARIA!W10)/CARGA_DIARIA!B10)) -> 332734.66 | E10: =IF(CARGA_DIARIA!A10="","",IF(CARGA_DIARIA!B10=0,0,(CARGA_DIARIA!X10+CARGA_DIARIA!Y10+CARGA_DIARIA!Z10+CARGA_DIARIA!AA10)/CARGA_DIARIA!B10+CARGA_DIARIA!AB10+CARGA_DIARIA!AC10+CARGA_DIARIA!AD10+CARGA_DIARIA!AE10)) -> 15774051 | F10: — | G10: — | H10: =IF(CARGA_DIARIA!A10="","",C10-D10-E10) -> 3029261.8
A11: =IF(CARGA_DIARIA!A11="","",CARGA_DIARIA!A11) -> 46038 | B11: =IF(CARGA_DIARIA!A11="","",CARGA_DIARIA!B11) -> 1440 | C11: =IF(CARGA_DIARIA!A11="","",IF(CARGA_DIARIA!B11=0,0,(CARGA_DIARIA!C11+CARGA_DIARIA!D11+CARGA_DIARIA!E11+CARGA_DIARIA!F11+CARGA_DIARIA!G11+CARGA_DIARIA!H11+CARGA_DIARIA!I11+CARGA_DIARIA!AG11+CARGA_DIARIA!AH11+CARGA_DIARIA!AI11+CARGA_DIARIA!AJ11)/CARGA_DIARIA!B11+CARGA_DIARIA!AF11)) -> 19578702 | D11: =IF(CARGA_DIARIA!A11="","",IF(CARGA_DIARIA!B11=0,0,(CARGA_DIARIA!J11+CARGA_DIARIA!K11+CARGA_DIARIA!L11+CARGA_DIARIA!M11+CARGA_DIARIA!N11+CARGA_DIARIA!O11+CARGA_DIARIA!P11+CARGA_DIARIA!Q11+CARGA_DIARIA!R11+CARGA_DIARIA!S11+CARGA_DIARIA!T11+CARGA_DIARIA!U11+CARGA_DIARIA!V11+CARGA_DIARIA!W11)/CARGA_DIARIA!B11)) -> 134777.6 | E11: =IF(CARGA_DIARIA!A11="","",IF(CARGA_DIARIA!B11=0,0,(CARGA_DIARIA!X11+CARGA_DIARIA!Y11+CARGA_DIARIA!Z11+CARGA_DIARIA!AA11)/CARGA_DIARIA!B11+CARGA_DIARIA!AB11+CARGA_DIARIA!AC11+CARGA_DIARIA!AD11+CARGA_DIARIA!AE11)) -> 15465779 | F11: — | G11: — | H11: =IF(CARGA_DIARIA!A11="","",C11-D11-E11) -> 3978145.2
A12: =IF(CARGA_DIARIA!A12="","",CARGA_DIARIA!A12) -> 46041 | B12: =IF(CARGA_DIARIA!A12="","",CARGA_DIARIA!B12) -> 1428 | C12: =IF(CARGA_DIARIA!A12="","",IF(CARGA_DIARIA!B12=0,0,(CARGA_DIARIA!C12+CARGA_DIARIA!D12+CARGA_DIARIA!E12+CARGA_DIARIA!F12+CARGA_DIARIA!G12+CARGA_DIARIA!H12+CARGA_DIARIA!I12+CARGA_DIARIA!AG12+CARGA_DIARIA!AH12+CARGA_DIARIA!AI12+CARGA_DIARIA!AJ12)/CARGA_DIARIA!B12+CARGA_DIARIA!AF12)) -> 20822019 | D12: =IF(CARGA_DIARIA!A12="","",IF(CARGA_DIARIA!B12=0,0,(CARGA_DIARIA!J12+CARGA_DIARIA!K12+CARGA_DIARIA!L12+CARGA_DIARIA!M12+CARGA_DIARIA!N12+CARGA_DIARIA!O12+CARGA_DIARIA!P12+CARGA_DIARIA!Q12+CARGA_DIARIA!R12+CARGA_DIARIA!S12+CARGA_DIARIA!T12+CARGA_DIARIA!U12+CARGA_DIARIA!V12+CARGA_DIARIA!W12)/CARGA_DIARIA!B12)) -> 163030.93 | E12: =IF(CARGA_DIARIA!A12="","",IF(CARGA_DIARIA!B12=0,0,(CARGA_DIARIA!X12+CARGA_DIARIA!Y12+CARGA_DIARIA!Z12+CARGA_DIARIA!AA12)/CARGA_DIARIA!B12+CARGA_DIARIA!AB12+CARGA_DIARIA!AC12+CARGA_DIARIA!AD12+CARGA_DIARIA!AE12)) -> 14933647 | F12: — | G12: — | H12: =IF(CARGA_DIARIA!A12="","",C12-D12-E12) -> 5725340.2
A13: =IF(CARGA_DIARIA!A13="","",CARGA_DIARIA!A13) -> 46042 | B13: =IF(CARGA_DIARIA!A13="","",CARGA_DIARIA!B13) -> 1428.5 | C13: =IF(CARGA_DIARIA!A13="","",IF(CARGA_DIARIA!B13=0,0,(CARGA_DIARIA!C13+CARGA_DIARIA!D13+CARGA_DIARIA!E13+CARGA_DIARIA!F13+CARGA_DIARIA!G13+CARGA_DIARIA!H13+CARGA_DIARIA!I13+CARGA_DIARIA!AG13+CARGA_DIARIA!AH13+CARGA_DIARIA!AI13+CARGA_DIARIA!AJ13)/CARGA_DIARIA!B13+CARGA_DIARIA!AF13)) -> 21139012 | D13: =IF(CARGA_DIARIA!A13="","",IF(CARGA_DIARIA!B13=0,0,(CARGA_DIARIA!J13+CARGA_DIARIA!K13+CARGA_DIARIA!L13+CARGA_DIARIA!M13+CARGA_DIARIA!N13+CARGA_DIARIA!O13+CARGA_DIARIA!P13+CARGA_DIARIA!Q13+CARGA_DIARIA!R13+CARGA_DIARIA!S13+CARGA_DIARIA!T13+CARGA_DIARIA!U13+CARGA_DIARIA!V13+CARGA_DIARIA!W13)/CARGA_DIARIA!B13)) -> 357428.56 | E13: =IF(CARGA_DIARIA!A13="","",IF(CARGA_DIARIA!B13=0,0,(CARGA_DIARIA!X13+CARGA_DIARIA!Y13+CARGA_DIARIA!Z13+CARGA_DIARIA!AA13)/CARGA_DIARIA!B13+CARGA_DIARIA!AB13+CARGA_DIARIA!AC13+CARGA_DIARIA!AD13+CARGA_DIARIA!AE13)) -> 15449352 | F13: — | G13: — | H13: =IF(CARGA_DIARIA!A13="","",C13-D13-E13) -> 5332231.7
A14: =IF(CARGA_DIARIA!A14="","",CARGA_DIARIA!A14) -> 46043 | B14: =IF(CARGA_DIARIA!A14="","",CARGA_DIARIA!B14) -> 1432 | C14: =IF(CARGA_DIARIA!A14="","",IF(CARGA_DIARIA!B14=0,0,(CARGA_DIARIA!C14+CARGA_DIARIA!D14+CARGA_DIARIA!E14+CARGA_DIARIA!F14+CARGA_DIARIA!G14+CARGA_DIARIA!H14+CARGA_DIARIA!I14+CARGA_DIARIA!AG14+CARGA_DIARIA!AH14+CARGA_DIARIA!AI14+CARGA_DIARIA!AJ14)/CARGA_DIARIA!B14+CARGA_DIARIA!AF14)) -> 21488028 | D14: =IF(CARGA_DIARIA!A14="","",IF(CARGA_DIARIA!B14=0,0,(CARGA_DIARIA!J14+CARGA_DIARIA!K14+CARGA_DIARIA!L14+CARGA_DIARIA!M14+CARGA_DIARIA!N14+CARGA_DIARIA!O14+CARGA_DIARIA!P14+CARGA_DIARIA!Q14+CARGA_DIARIA!R14+CARGA_DIARIA!S14+CARGA_DIARIA!T14+CARGA_DIARIA!U14+CARGA_DIARIA!V14+CARGA_DIARIA!W14)/CARGA_DIARIA!B14)) -> 251536.26 | E14: =IF(CARGA_DIARIA!A14="","",IF(CARGA_DIARIA!B14=0,0,(CARGA_DIARIA!X14+CARGA_DIARIA!Y14+CARGA_DIARIA!Z14+CARGA_DIARIA!AA14)/CARGA_DIARIA!B14+CARGA_DIARIA!AB14+CARGA_DIARIA!AC14+CARGA_DIARIA!AD14+CARGA_DIARIA!AE14)) -> 15559503 | F14: — | G14: — | H14: =IF(CARGA_DIARIA!A14="","",C14-D14-E14) -> 5676988.7
A15: =IF(CARGA_DIARIA!A15="","",CARGA_DIARIA!A15) -> 46044 | B15: =IF(CARGA_DIARIA!A15="","",CARGA_DIARIA!B15) -> 1427 | C15: =IF(CARGA_DIARIA!A15="","",IF(CARGA_DIARIA!B15=0,0,(CARGA_DIARIA!C15+CARGA_DIARIA!D15+CARGA_DIARIA!E15+CARGA_DIARIA!F15+CARGA_DIARIA!G15+CARGA_DIARIA!H15+CARGA_DIARIA!I15+CARGA_DIARIA!AG15+CARGA_DIARIA!AH15+CARGA_DIARIA!AI15+CARGA_DIARIA!AJ15)/CARGA_DIARIA!B15+CARGA_DIARIA!AF15)) -> 21827494 | D15: =IF(CARGA_DIARIA!A15="","",IF(CARGA_DIARIA!B15=0,0,(CARGA_DIARIA!J15+CARGA_DIARIA!K15+CARGA_DIARIA!L15+CARGA_DIARIA!M15+CARGA_DIARIA!N15+CARGA_DIARIA!O15+CARGA_DIARIA!P15+CARGA_DIARIA!Q15+CARGA_DIARIA!R15+CARGA_DIARIA!S15+CARGA_DIARIA!T15+CARGA_DIARIA!U15+CARGA_DIARIA!V15+CARGA_DIARIA!W15)/CARGA_DIARIA!B15)) -> 164046.41 | E15: =IF(CARGA_DIARIA!A15="","",IF(CARGA_DIARIA!B15=0,0,(CARGA_DIARIA!X15+CARGA_DIARIA!Y15+CARGA_DIARIA!Z15+CARGA_DIARIA!AA15)/CARGA_DIARIA!B15+CARGA_DIARIA!AB15+CARGA_DIARIA!AC15+CARGA_DIARIA!AD15+CARGA_DIARIA!AE15)) -> 15422836 | F15: — | G15: — | H15: =IF(CARGA_DIARIA!A15="","",C15-D15-E15) -> 6240611.7
... A117: =IF(CARGA_DIARIA!A117="","",CARGA_DIARIA!A117) -> 46203 | B117: =IF(CARGA_DIARIA!A117="","",CARGA_DIARIA!B117) -> 1472.5 | C117: =IF(CARGA_DIARIA!A117="","",IF(CARGA_DIARIA!B117=0,0,(CARGA_DIARIA!C117+CARGA_DIARIA!D117+CARGA_DIARIA!E117+CARGA_DIARIA!F117+CARGA_DIARIA!G117+CARGA_DIARIA!H117+CARGA_DIARIA!I117+CARGA_DIARIA!AG117+CARGA_DIARIA!AH117+CARGA_DIARIA!AI117+CARGA_DIARIA!AJ117)/CARGA_DIARIA!B117+CARGA_DIARIA!AF117)) -> 30886658 | D117: =IF(CARGA_DIARIA!A117="","",IF(CARGA_DIARIA!B117=0,0,(CARGA_DIARIA!J117+CARGA_DIARIA!K117+CARGA_DIARIA!L117+CARGA_DIARIA!M117+CARGA_DIARIA!N117+CARGA_DIARIA!O117+CARGA_DIARIA!P117+CARGA_DIARIA!Q117+CARGA_DIARIA!R117+CARGA_DIARIA!S117+CARGA_DIARIA!T117+CARGA_DIARIA!U117+CARGA_DIARIA!V117+CARGA_DIARIA!W117)/CARGA_DIARIA!B117)) -> 468105.49 | E117: =IF(CARGA_DIARIA!A117="","",IF(CARGA_DIARIA!B117=0,0,(CARGA_DIARIA!X117+CARGA_DIARIA!Y117+CARGA_DIARIA!Z117+CARGA_DIARIA!AA117)/CARGA_DIARIA!B117+CARGA_DIARIA!AB117+CARGA_DIARIA!AC117+CARGA_DIARIA!AD117+CARGA_DIARIA!AE117)) -> 17984961 | F117: — | G117: — | H117: =IF(CARGA_DIARIA!A117="","",C117-D117-E117) -> 12433592
A118: =IF(CARGA_DIARIA!B118="","",CARGA_DIARIA!B118) -> 1478 | B118: =IF(CARGA_DIARIA!B118="","",CARGA_DIARIA!#REF!) -> #REF! | C118: =IF(CARGA_DIARIA!B118="","",IF(CARGA_DIARIA!#REF!=0,0,(CARGA_DIARIA!C118+CARGA_DIARIA!D118+CARGA_DIARIA!E118+CARGA_DIARIA!F118+CARGA_DIARIA!G118+CARGA_DIARIA!H118+CARGA_DIARIA!I118+CARGA_DIARIA!AG118+CARGA_DIARIA!AH118+CARGA_DIARIA!AI118+CARGA_DIARIA!AJ118)/CARGA_DIARIA!#REF!+CARGA_DIARIA!AF118)) -> #REF! | D118: =IF(CARGA_DIARIA!B118="","",IF(CARGA_DIARIA!#REF!=0,0,(CARGA_DIARIA!J118+CARGA_DIARIA!K118+CARGA_DIARIA!L118+CARGA_DIARIA!M118+CARGA_DIARIA!N118+CARGA_DIARIA!O118+CARGA_DIARIA!P118+CARGA_DIARIA!Q118+CARGA_DIARIA!R118+CARGA_DIARIA!S118+CARGA_DIARIA!T118+CARGA_DIARIA!U118+CARGA_DIARIA!V118+CARGA_DIARIA!W118)/CARGA_DIARIA!#REF!)) -> #REF! | E118: =IF(CARGA_DIARIA!B118="","",IF(CARGA_DIARIA!#REF!=0,0,(CARGA_DIARIA!X118+CARGA_DIARIA!Y118+CARGA_DIARIA!Z118+CARGA_DIARIA!AA118)/CARGA_DIARIA!#REF!+CARGA_DIARIA!AB118+CARGA_DIARIA!AC118+CARGA_DIARIA!AD118+CARGA_DIARIA!AE118)) -> #REF! | F118: — | G118: — | H118: =IF(CARGA_DIARIA!B118="","",C118-D118-E118) -> #REF!
A119: =IF(CARGA_DIARIA!B119="","",CARGA_DIARIA!B119) -> 1485 | B119: =IF(CARGA_DIARIA!B119="","",CARGA_DIARIA!#REF!) -> #REF! | C119: =IF(CARGA_DIARIA!B119="","",IF(CARGA_DIARIA!#REF!=0,0,(CARGA_DIARIA!C119+CARGA_DIARIA!D119+CARGA_DIARIA!E119+CARGA_DIARIA!F119+CARGA_DIARIA!G119+CARGA_DIARIA!H119+CARGA_DIARIA!I119+CARGA_DIARIA!AG119+CARGA_DIARIA!AH119+CARGA_DIARIA!AI119+CARGA_DIARIA!AJ119)/CARGA_DIARIA!#REF!+CARGA_DIARIA!AF119)) -> #REF! | D119: =IF(CARGA_DIARIA!B119="","",IF(CARGA_DIARIA!#REF!=0,0,(CARGA_DIARIA!J119+CARGA_DIARIA!K119+CARGA_DIARIA!L119+CARGA_DIARIA!M119+CARGA_DIARIA!N119+CARGA_DIARIA!O119+CARGA_DIARIA!P119+CARGA_DIARIA!Q119+CARGA_DIARIA!R119+CARGA_DIARIA!S119+CARGA_DIARIA!T119+CARGA_DIARIA!U119+CARGA_DIARIA!V119+CARGA_DIARIA!W119)/CARGA_DIARIA!#REF!)) -> #REF! | E119: =IF(CARGA_DIARIA!B119="","",IF(CARGA_DIARIA!#REF!=0,0,(CARGA_DIARIA!X119+CARGA_DIARIA!Y119+CARGA_DIARIA!Z119+CARGA_DIARIA!AA119)/CARGA_DIARIA!#REF!+CARGA_DIARIA!AB119+CARGA_DIARIA!AC119+CARGA_DIARIA!AD119+CARGA_DIARIA!AE119)) -> #REF! | F119: — | G119: — | H119: =IF(CARGA_DIARIA!B119="","",C119-D119-E119) -> #REF!
A120: =IF(CARGA_DIARIA!B120="","",CARGA_DIARIA!B120) -> 1488 | B120: =IF(CARGA_DIARIA!B120="","",CARGA_DIARIA!#REF!) -> #REF! | C120: =IF(CARGA_DIARIA!B120="","",IF(CARGA_DIARIA!#REF!=0,0,(CARGA_DIARIA!C120+CARGA_DIARIA!D120+CARGA_DIARIA!E120+CARGA_DIARIA!F120+CARGA_DIARIA!G120+CARGA_DIARIA!H120+CARGA_DIARIA!I120+CARGA_DIARIA!AG120+CARGA_DIARIA!AH120+CARGA_DIARIA!AI120+CARGA_DIARIA!AJ120)/CARGA_DIARIA!#REF!+CARGA_DIARIA!AF120)) -> #REF! | D120: =IF(CARGA_DIARIA!B120="","",IF(CARGA_DIARIA!#REF!=0,0,(CARGA_DIARIA!J120+CARGA_DIARIA!K120+CARGA_DIARIA!L120+CARGA_DIARIA!M120+CARGA_DIARIA!N120+CARGA_DIARIA!O120+CARGA_DIARIA!P120+CARGA_DIARIA!Q120+CARGA_DIARIA!R120+CARGA_DIARIA!S120+CARGA_DIARIA!T120+CARGA_DIARIA!U120+CARGA_DIARIA!V120+CARGA_DIARIA!W120)/CARGA_DIARIA!#REF!)) -> #REF! | E120: =IF(CARGA_DIARIA!B120="","",IF(CARGA_DIARIA!#REF!=0,0,(CARGA_DIARIA!X120+CARGA_DIARIA!Y120+CARGA_DIARIA!Z120+CARGA_DIARIA!AA120)/CARGA_DIARIA!#REF!+CARGA_DIARIA!AB120+CARGA_DIARIA!AC120+CARGA_DIARIA!AD120+CARGA_DIARIA!AE120)) -> #REF! | F120: — | G120: — | H120: =IF(CARGA_DIARIA!B120="","",C120-D120-E120) -> #REF!
A121: =IF(CARGA_DIARIA!B121="","",CARGA_DIARIA!B121) -> 1488 | B121: =IF(CARGA_DIARIA!B121="","",CARGA_DIARIA!#REF!) -> #REF! | C121: =IF(CARGA_DIARIA!B121="","",IF(CARGA_DIARIA!#REF!=0,0,(CARGA_DIARIA!C121+CARGA_DIARIA!D121+CARGA_DIARIA!E121+CARGA_DIARIA!F121+CARGA_DIARIA!G121+CARGA_DIARIA!H121+CARGA_DIARIA!I121+CARGA_DIARIA!AG121+CARGA_DIARIA!AH121+CARGA_DIARIA!AI121+CARGA_DIARIA!AJ121)/CARGA_DIARIA!#REF!+CARGA_DIARIA!AF121)) -> #REF! | D121: =IF(CARGA_DIARIA!B121="","",IF(CARGA_DIARIA!#REF!=0,0,(CARGA_DIARIA!J121+CARGA_DIARIA!K121+CARGA_DIARIA!L121+CARGA_DIARIA!M121+CARGA_DIARIA!N121+CARGA_DIARIA!O121+CARGA_DIARIA!P121+CARGA_DIARIA!Q121+CARGA_DIARIA!R121+CARGA_DIARIA!S121+CARGA_DIARIA!T121+CARGA_DIARIA!U121+CARGA_DIARIA!V121+CARGA_DIARIA!W121)/CARGA_DIARIA!#REF!)) -> #REF! | E121: =IF(CARGA_DIARIA!B121="","",IF(CARGA_DIARIA!#REF!=0,0,(CARGA_DIARIA!X121+CARGA_DIARIA!Y121+CARGA_DIARIA!Z121+CARGA_DIARIA!AA121)/CARGA_DIARIA!#REF!+CARGA_DIARIA!AB121+CARGA_DIARIA!AC121+CARGA_DIARIA!AD121+CARGA_DIARIA!AE121)) -> #REF! | F121: — | G121: — | H121: =IF(CARGA_DIARIA!B121="","",C121-D121-E121) -> #REF!
A122: =IF(CARGA_DIARIA!B122="","",CARGA_DIARIA!B122) -> 1487.5 | B122: =IF(CARGA_DIARIA!B122="","",CARGA_DIARIA!#REF!) -> #REF! | C122: =IF(CARGA_DIARIA!B122="","",IF(CARGA_DIARIA!#REF!=0,0,(CARGA_DIARIA!C122+CARGA_DIARIA!D122+CARGA_DIARIA!E122+CARGA_DIARIA!F122+CARGA_DIARIA!G122+CARGA_DIARIA!H122+CARGA_DIARIA!I122+CARGA_DIARIA!AG122+CARGA_DIARIA!AH122+CARGA_DIARIA!AI122+CARGA_DIARIA!AJ122)/CARGA_DIARIA!#REF!+CARGA_DIARIA!AF122)) -> #REF! | D122: =IF(CARGA_DIARIA!B122="","",IF(CARGA_DIARIA!#REF!=0,0,(CARGA_DIARIA!J122+CARGA_DIARIA!K122+CARGA_DIARIA!L122+CARGA_DIARIA!M122+CARGA_DIARIA!N122+CARGA_DIARIA!O122+CARGA_DIARIA!P122+CARGA_DIARIA!Q122+CARGA_DIARIA!R122+CARGA_DIARIA!S122+CARGA_DIARIA!T122+CARGA_DIARIA!U122+CARGA_DIARIA!V122+CARGA_DIARIA!W122)/CARGA_DIARIA!#REF!)) -> #REF! | E122: =IF(CARGA_DIARIA!B122="","",IF(CARGA_DIARIA!#REF!=0,0,(CARGA_DIARIA!X122+CARGA_DIARIA!Y122+CARGA_DIARIA!Z122+CARGA_DIARIA!AA122)/CARGA_DIARIA!#REF!+CARGA_DIARIA!AB122+CARGA_DIARIA!AC122+CARGA_DIARIA!AD122+CARGA_DIARIA!AE122)) -> #REF! | F122: — | G122: — | H122: =IF(CARGA_DIARIA!B122="","",C122-D122-E122) -> #REF!
A123: =IF(CARGA_DIARIA!B123="","",CARGA_DIARIA!B123) -> 1487 | B123: =IF(CARGA_DIARIA!B123="","",CARGA_DIARIA!#REF!) -> #REF! | C123: =IF(CARGA_DIARIA!B123="","",IF(CARGA_DIARIA!#REF!=0,0,(CARGA_DIARIA!C123+CARGA_DIARIA!D123+CARGA_DIARIA!E123+CARGA_DIARIA!F123+CARGA_DIARIA!G123+CARGA_DIARIA!H123+CARGA_DIARIA!I123+CARGA_DIARIA!AG123+CARGA_DIARIA!AH123+CARGA_DIARIA!AI123+CARGA_DIARIA!AJ123)/CARGA_DIARIA!#REF!+CARGA_DIARIA!AF123)) -> #REF! | D123: =IF(CARGA_DIARIA!B123="","",IF(CARGA_DIARIA!#REF!=0,0,(CARGA_DIARIA!J123+CARGA_DIARIA!K123+CARGA_DIARIA!L123+CARGA_DIARIA!M123+CARGA_DIARIA!N123+CARGA_DIARIA!O123+CARGA_DIARIA!P123+CARGA_DIARIA!Q123+CARGA_DIARIA!R123+CARGA_DIARIA!S123+CARGA_DIARIA!T123+CARGA_DIARIA!U123+CARGA_DIARIA!V123+CARGA_DIARIA!W123)/CARGA_DIARIA!#REF!)) -> #REF! | E123: =IF(CARGA_DIARIA!B123="","",IF(CARGA_DIARIA!#REF!=0,0,(CARGA_DIARIA!X123+CARGA_DIARIA!Y123+CARGA_DIARIA!Z123+CARGA_DIARIA!AA123)/CARGA_DIARIA!#REF!+CARGA_DIARIA!AB123+CARGA_DIARIA!AC123+CARGA_DIARIA!AD123+CARGA_DIARIA!AE123)) -> #REF! | F123: — | G123: — | H123: =IF(CARGA_DIARIA!B123="","",C123-D123-E123) -> #REF!
A124: =IF(CARGA_DIARIA!B124="","",CARGA_DIARIA!B124) -> 1482.5 | B124: =IF(CARGA_DIARIA!B124="","",CARGA_DIARIA!#REF!) -> #REF! | C124: =IF(CARGA_DIARIA!B124="","",IF(CARGA_DIARIA!#REF!=0,0,(CARGA_DIARIA!C124+CARGA_DIARIA!D124+CARGA_DIARIA!E124+CARGA_DIARIA!F124+CARGA_DIARIA!G124+CARGA_DIARIA!H124+CARGA_DIARIA!I124+CARGA_DIARIA!AG124+CARGA_DIARIA!AH124+CARGA_DIARIA!AI124+CARGA_DIARIA!AJ124)/CARGA_DIARIA!#REF!+CARGA_DIARIA!AF124)) -> #REF! | D124: =IF(CARGA_DIARIA!B124="","",IF(CARGA_DIARIA!#REF!=0,0,(CARGA_DIARIA!J124+CARGA_DIARIA!K124+CARGA_DIARIA!L124+CARGA_DIARIA!M124+CARGA_DIARIA!N124+CARGA_DIARIA!O124+CARGA_DIARIA!P124+CARGA_DIARIA!Q124+CARGA_DIARIA!R124+CARGA_DIARIA!S124+CARGA_DIARIA!T124+CARGA_DIARIA!U124+CARGA_DIARIA!V124+CARGA_DIARIA!W124)/CARGA_DIARIA!#REF!)) -> #REF! | E124: =IF(CARGA_DIARIA!B124="","",IF(CARGA_DIARIA!#REF!=0,0,(CARGA_DIARIA!X124+CARGA_DIARIA!Y124+CARGA_DIARIA!Z124+CARGA_DIARIA!AA124)/CARGA_DIARIA!#REF!+CARGA_DIARIA!AB124+CARGA_DIARIA!AC124+CARGA_DIARIA!AD124+CARGA_DIARIA!AE124)) -> #REF! | F124: — | G124: — | H124: =IF(CARGA_DIARIA!B124="","",C124-D124-E124) -> #REF!
A125: =IF(CARGA_DIARIA!A125="","",CARGA_DIARIA!A125) -> 46218 | B125: =IF(CARGA_DIARIA!A125="","",CARGA_DIARIA!B125) -> 1473 | C125: =IF(CARGA_DIARIA!A125="","",IF(CARGA_DIARIA!B125=0,0,(CARGA_DIARIA!C125+CARGA_DIARIA!D125+CARGA_DIARIA!E125+CARGA_DIARIA!F125+CARGA_DIARIA!G125+CARGA_DIARIA!H125+CARGA_DIARIA!I125+CARGA_DIARIA!AG125+CARGA_DIARIA!AH125+CARGA_DIARIA!AI125+CARGA_DIARIA!AJ125)/CARGA_DIARIA!B125+CARGA_DIARIA!AF125)) -> 35175810 | D125: =IF(CARGA_DIARIA!A125="","",IF(CARGA_DIARIA!B125=0,0,(CARGA_DIARIA!J125+CARGA_DIARIA!K125+CARGA_DIARIA!L125+CARGA_DIARIA!M125+CARGA_DIARIA!N125+CARGA_DIARIA!O125+CARGA_DIARIA!P125+CARGA_DIARIA!Q125+CARGA_DIARIA!R125+CARGA_DIARIA!S125+CARGA_DIARIA!T125+CARGA_DIARIA!U125+CARGA_DIARIA!V125+CARGA_DIARIA!W125)/CARGA_DIARIA!B125)) -> 787762.66 | E125: =IF(CARGA_DIARIA!A125="","",IF(CARGA_DIARIA!B125=0,0,(CARGA_DIARIA!X125+CARGA_DIARIA!Y125+CARGA_DIARIA!Z125+CARGA_DIARIA!AA125)/CARGA_DIARIA!B125+CARGA_DIARIA!AB125+CARGA_DIARIA!AC125+CARGA_DIARIA!AD125+CARGA_DIARIA!AE125)) -> 25430698 | F125: — | G125: — | H125: =IF(CARGA_DIARIA!A125="","",C125-D125-E125) -> 8957349.1
A126: =IF(CARGA_DIARIA!A126="","",CARGA_DIARIA!A126) -> 46219 | B126: =IF(CARGA_DIARIA!A126="","",CARGA_DIARIA!B126) -> 1466 | C126: =IF(CARGA_DIARIA!A126="","",IF(CARGA_DIARIA!B126=0,0,(CARGA_DIARIA!C126+CARGA_DIARIA!D126+CARGA_DIARIA!E126+CARGA_DIARIA!F126+CARGA_DIARIA!G126+CARGA_DIARIA!H126+CARGA_DIARIA!I126+CARGA_DIARIA!AG126+CARGA_DIARIA!AH126+CARGA_DIARIA!AI126+CARGA_DIARIA!AJ126)/CARGA_DIARIA!B126+CARGA_DIARIA!AF126)) -> 49177894 | D126: =IF(CARGA_DIARIA!A126="","",IF(CARGA_DIARIA!B126=0,0,(CARGA_DIARIA!J126+CARGA_DIARIA!K126+CARGA_DIARIA!L126+CARGA_DIARIA!M126+CARGA_DIARIA!N126+CARGA_DIARIA!O126+CARGA_DIARIA!P126+CARGA_DIARIA!Q126+CARGA_DIARIA!R126+CARGA_DIARIA!S126+CARGA_DIARIA!T126+CARGA_DIARIA!U126+CARGA_DIARIA!V126+CARGA_DIARIA!W126)/CARGA_DIARIA!B126)) -> 511705.62 | E126: =IF(CARGA_DIARIA!A126="","",IF(CARGA_DIARIA!B126=0,0,(CARGA_DIARIA!X126+CARGA_DIARIA!Y126+CARGA_DIARIA!Z126+CARGA_DIARIA!AA126)/CARGA_DIARIA!B126+CARGA_DIARIA!AB126+CARGA_DIARIA!AC126+CARGA_DIARIA!AD126+CARGA_DIARIA!AE126)) -> 25637323 | F126: — | G126: — | H126: =IF(CARGA_DIARIA!A126="","",C126-D126-E126) -> 23028865
A127: =IF(CARGA_DIARIA!A127="","",CARGA_DIARIA!A127) -> 46220 | B127: =IF(CARGA_DIARIA!A127="","",CARGA_DIARIA!B127) -> 1471 | C127: =IF(CARGA_DIARIA!A127="","",IF(CARGA_DIARIA!B127=0,0,(CARGA_DIARIA!C127+CARGA_DIARIA!D127+CARGA_DIARIA!E127+CARGA_DIARIA!F127+CARGA_DIARIA!G127+CARGA_DIARIA!H127+CARGA_DIARIA!I127+CARGA_DIARIA!AG127+CARGA_DIARIA!AH127+CARGA_DIARIA!AI127+CARGA_DIARIA!AJ127)/CARGA_DIARIA!B127+CARGA_DIARIA!AF127)) -> 50241448 | D127: =IF(CARGA_DIARIA!A127="","",IF(CARGA_DIARIA!B127=0,0,(CARGA_DIARIA!J127+CARGA_DIARIA!K127+CARGA_DIARIA!L127+CARGA_DIARIA!M127+CARGA_DIARIA!N127+CARGA_DIARIA!O127+CARGA_DIARIA!P127+CARGA_DIARIA!Q127+CARGA_DIARIA!R127+CARGA_DIARIA!S127+CARGA_DIARIA!T127+CARGA_DIARIA!U127+CARGA_DIARIA!V127+CARGA_DIARIA!W127)/CARGA_DIARIA!B127)) -> 542846.44 | E127: =IF(CARGA_DIARIA!A127="","",IF(CARGA_DIARIA!B127=0,0,(CARGA_DIARIA!X127+CARGA_DIARIA!Y127+CARGA_DIARIA!Z127+CARGA_DIARIA!AA127)/CARGA_DIARIA!B127+CARGA_DIARIA!AB127+CARGA_DIARIA!AC127+CARGA_DIARIA!AD127+CARGA_DIARIA!AE127)) -> 25964777 | F127: — | G127: — | H127: =IF(CARGA_DIARIA!A127="","",C127-D127-E127) -> 23733825
A128: =IF(CARGA_DIARIA!A128="","",CARGA_DIARIA!A128) -> 46223 | B128: =IF(CARGA_DIARIA!A128="","",CARGA_DIARIA!B128) -> 1476 | C128: =IF(CARGA_DIARIA!A128="","",IF(CARGA_DIARIA!B128=0,0,(CARGA_DIARIA!C128+CARGA_DIARIA!D128+CARGA_DIARIA!E128+CARGA_DIARIA!F128+CARGA_DIARIA!G128+CARGA_DIARIA!H128+CARGA_DIARIA!I128+CARGA_DIARIA!AG128+CARGA_DIARIA!AH128+CARGA_DIARIA!AI128+CARGA_DIARIA!AJ128)/CARGA_DIARIA!B128+CARGA_DIARIA!AF128)) -> 49188149 | D128: =IF(CARGA_DIARIA!A128="","",IF(CARGA_DIARIA!B128=0,0,(CARGA_DIARIA!J128+CARGA_DIARIA!K128+CARGA_DIARIA!L128+CARGA_DIARIA!M128+CARGA_DIARIA!N128+CARGA_DIARIA!O128+CARGA_DIARIA!P128+CARGA_DIARIA!Q128+CARGA_DIARIA!R128+CARGA_DIARIA!S128+CARGA_DIARIA!T128+CARGA_DIARIA!U128+CARGA_DIARIA!V128+CARGA_DIARIA!W128)/CARGA_DIARIA!B128)) -> 640506.91 | E128: =IF(CARGA_DIARIA!A128="","",IF(CARGA_DIARIA!B128=0,0,(CARGA_DIARIA!X128+CARGA_DIARIA!Y128+CARGA_DIARIA!Z128+CARGA_DIARIA!AA128)/CARGA_DIARIA!B128+CARGA_DIARIA!AB128+CARGA_DIARIA!AC128+CARGA_DIARIA!AD128+CARGA_DIARIA!AE128)) -> 24515468 | F128: — | G128: — | H128: =IF(CARGA_DIARIA!A128="","",C128-D128-E128) -> 24032174
A129: =IF(CARGA_DIARIA!A129="","",CARGA_DIARIA!A129) -> 46224 | B129: =IF(CARGA_DIARIA!A129="","",CARGA_DIARIA!B129) -> 1476 | C129: =IF(CARGA_DIARIA!A129="","",IF(CARGA_DIARIA!B129=0,0,(CARGA_DIARIA!C129+CARGA_DIARIA!D129+CARGA_DIARIA!E129+CARGA_DIARIA!F129+CARGA_DIARIA!G129+CARGA_DIARIA!H129+CARGA_DIARIA!I129+CARGA_DIARIA!AG129+CARGA_DIARIA!AH129+CARGA_DIARIA!AI129+CARGA_DIARIA!AJ129)/CARGA_DIARIA!B129+CARGA_DIARIA!AF129)) -> 49647490 | D129: =IF(CARGA_DIARIA!A129="","",IF(CARGA_DIARIA!B129=0,0,(CARGA_DIARIA!J129+CARGA_DIARIA!K129+CARGA_DIARIA!L129+CARGA_DIARIA!M129+CARGA_DIARIA!N129+CARGA_DIARIA!O129+CARGA_DIARIA!P129+CARGA_DIARIA!Q129+CARGA_DIARIA!R129+CARGA_DIARIA!S129+CARGA_DIARIA!T129+CARGA_DIARIA!U129+CARGA_DIARIA!V129+CARGA_DIARIA!W129)/CARGA_DIARIA!B129)) -> 826834.29 | E129: =IF(CARGA_DIARIA!A129="","",IF(CARGA_DIARIA!B129=0,0,(CARGA_DIARIA!X129+CARGA_DIARIA!Y129+CARGA_DIARIA!Z129+CARGA_DIARIA!AA129)/CARGA_DIARIA!B129+CARGA_DIARIA!AB129+CARGA_DIARIA!AC129+CARGA_DIARIA!AD129+CARGA_DIARIA!AE129)) -> 24705984 | F129: — | G129: — | H129: =IF(CARGA_DIARIA!A129="","",C129-D129-E129) -> 24114671
A130: =IF(CARGA_DIARIA!A130="","",CARGA_DIARIA!A130) -> 46225 | B130: =IF(CARGA_DIARIA!A130="","",CARGA_DIARIA!B130) -> 1476 | C130: =IF(CARGA_DIARIA!A130="","",IF(CARGA_DIARIA!B130=0,0,(CARGA_DIARIA!C130+CARGA_DIARIA!D130+CARGA_DIARIA!E130+CARGA_DIARIA!F130+CARGA_DIARIA!G130+CARGA_DIARIA!H130+CARGA_DIARIA!I130+CARGA_DIARIA!AG130+CARGA_DIARIA!AH130+CARGA_DIARIA!AI130+CARGA_DIARIA!AJ130)/CARGA_DIARIA!B130+CARGA_DIARIA!AF130)) -> 48281088 | D130: =IF(CARGA_DIARIA!A130="","",IF(CARGA_DIARIA!B130=0,0,(CARGA_DIARIA!J130+CARGA_DIARIA!K130+CARGA_DIARIA!L130+CARGA_DIARIA!M130+CARGA_DIARIA!N130+CARGA_DIARIA!O130+CARGA_DIARIA!P130+CARGA_DIARIA!Q130+CARGA_DIARIA!R130+CARGA_DIARIA!S130+CARGA_DIARIA!T130+CARGA_DIARIA!U130+CARGA_DIARIA!V130+CARGA_DIARIA!W130)/CARGA_DIARIA!B130)) -> 329439.04 | E130: =IF(CARGA_DIARIA!A130="","",IF(CARGA_DIARIA!B130=0,0,(CARGA_DIARIA!X130+CARGA_DIARIA!Y130+CARGA_DIARIA!Z130+CARGA_DIARIA!AA130)/CARGA_DIARIA!B130+CARGA_DIARIA!AB130+CARGA_DIARIA!AC130+CARGA_DIARIA!AD130+CARGA_DIARIA!AE130)) -> 24494831 | F130: — | G130: — | H130: =IF(CARGA_DIARIA!A130="","",C130-D130-E130) -> 23456818
A131: =IF(CARGA_DIARIA!A131="","",CARGA_DIARIA!A131) -> 46226 | B131: =IF(CARGA_DIARIA!A131="","",CARGA_DIARIA!B131) -> 1477 | C131: =IF(CARGA_DIARIA!A131="","",IF(CARGA_DIARIA!B131=0,0,(CARGA_DIARIA!C131+CARGA_DIARIA!D131+CARGA_DIARIA!E131+CARGA_DIARIA!F131+CARGA_DIARIA!G131+CARGA_DIARIA!H131+CARGA_DIARIA!I131+CARGA_DIARIA!AG131+CARGA_DIARIA!AH131+CARGA_DIARIA!AI131+CARGA_DIARIA!AJ131)/CARGA_DIARIA!B131+CARGA_DIARIA!AF131)) -> 48067682 | D131: =IF(CARGA_DIARIA!A131="","",IF(CARGA_DIARIA!B131=0,0,(CARGA_DIARIA!J131+CARGA_DIARIA!K131+CARGA_DIARIA!L131+CARGA_DIARIA!M131+CARGA_DIARIA!N131+CARGA_DIARIA!O131+CARGA_DIARIA!P131+CARGA_DIARIA!Q131+CARGA_DIARIA!R131+CARGA_DIARIA!S131+CARGA_DIARIA!T131+CARGA_DIARIA!U131+CARGA_DIARIA!V131+CARGA_DIARIA!W131)/CARGA_DIARIA!B131)) -> 418047.6 | E131: =IF(CARGA_DIARIA!A131="","",IF(CARGA_DIARIA!B131=0,0,(CARGA_DIARIA!X131+CARGA_DIARIA!Y131+CARGA_DIARIA!Z131+CARGA_DIARIA!AA131)/CARGA_DIARIA!B131+CARGA_DIARIA!AB131+CARGA_DIARIA!AC131+CARGA_DIARIA!AD131+CARGA_DIARIA!AE131)) -> 28482247 | F131: — | G131: — | H131: =IF(CARGA_DIARIA!A131="","",C131-D131-E131) -> 19167387
A132: =IF(CARGA_DIARIA!A132="","",CARGA_DIARIA!A132) -> 46227 | B132: =IF(CARGA_DIARIA!A132="","",CARGA_DIARIA!B132) -> 1487.5 | C132: =IF(CARGA_DIARIA!A132="","",IF(CARGA_DIARIA!B132=0,0,(CARGA_DIARIA!C132+CARGA_DIARIA!D132+CARGA_DIARIA!E132+CARGA_DIARIA!F132+CARGA_DIARIA!G132+CARGA_DIARIA!H132+CARGA_DIARIA!I132+CARGA_DIARIA!AG132+CARGA_DIARIA!AH132+CARGA_DIARIA!AI132+CARGA_DIARIA!AJ132)/CARGA_DIARIA!B132+CARGA_DIARIA!AF132)) -> 47301610 | D132: =IF(CARGA_DIARIA!A132="","",IF(CARGA_DIARIA!B132=0,0,(CARGA_DIARIA!J132+CARGA_DIARIA!K132+CARGA_DIARIA!L132+CARGA_DIARIA!M132+CARGA_DIARIA!N132+CARGA_DIARIA!O132+CARGA_DIARIA!P132+CARGA_DIARIA!Q132+CARGA_DIARIA!R132+CARGA_DIARIA!S132+CARGA_DIARIA!T132+CARGA_DIARIA!U132+CARGA_DIARIA!V132+CARGA_DIARIA!W132)/CARGA_DIARIA!B132)) -> 523403.13 | E132: =IF(CARGA_DIARIA!A132="","",IF(CARGA_DIARIA!B132=0,0,(CARGA_DIARIA!X132+CARGA_DIARIA!Y132+CARGA_DIARIA!Z132+CARGA_DIARIA!AA132)/CARGA_DIARIA!B132+CARGA_DIARIA!AB132+CARGA_DIARIA!AC132+CARGA_DIARIA!AD132+CARGA_DIARIA!AE132)) -> 24369582 | F132: — | G132: — | H132: =IF(CARGA_DIARIA!A132="","",C132-D132-E132) -> 22408625
A133: =IF(CARGA_DIARIA!A133="","",CARGA_DIARIA!A133) -> 46230 | B133: =IF(CARGA_DIARIA!A133="","",CARGA_DIARIA!B133) -> 1491.5 | C133: =IF(CARGA_DIARIA!A133="","",IF(CARGA_DIARIA!B133=0,0,(CARGA_DIARIA!C133+CARGA_DIARIA!D133+CARGA_DIARIA!E133+CARGA_DIARIA!F133+CARGA_DIARIA!G133+CARGA_DIARIA!H133+CARGA_DIARIA!I133+CARGA_DIARIA!AG133+CARGA_DIARIA!AH133+CARGA_DIARIA!AI133+CARGA_DIARIA!AJ133)/CARGA_DIARIA!B133+CARGA_DIARIA!AF133)) -> 47296378 | D133: =IF(CARGA_DIARIA!A133="","",IF(CARGA_DIARIA!B133=0,0,(CARGA_DIARIA!J133+CARGA_DIARIA!K133+CARGA_DIARIA!L133+CARGA_DIARIA!M133+CARGA_DIARIA!N133+CARGA_DIARIA!O133+CARGA_DIARIA!P133+CARGA_DIARIA!Q133+CARGA_DIARIA!R133+CARGA_DIARIA!S133+CARGA_DIARIA!T133+CARGA_DIARIA!U133+CARGA_DIARIA!V133+CARGA_DIARIA!W133)/CARGA_DIARIA!B133)) -> 485589.91 | E133: =IF(CARGA_DIARIA!A133="","",IF(CARGA_DIARIA!B133=0,0,(CARGA_DIARIA!X133+CARGA_DIARIA!Y133+CARGA_DIARIA!Z133+CARGA_DIARIA!AA133)/CARGA_DIARIA!B133+CARGA_DIARIA!AB133+CARGA_DIARIA!AC133+CARGA_DIARIA!AD133+CARGA_DIARIA!AE133)) -> 27225768 | F133: — | G133: — | H133: =IF(CARGA_DIARIA!A133="","",C133-D133-E133) -> 19585020
A134: =IF(CARGA_DIARIA!A134="","",CARGA_DIARIA!A134) -> 46231 | B134: =IF(CARGA_DIARIA!A134="","",CARGA_DIARIA!B134) -> 1493.5 | C134: =IF(CARGA_DIARIA!A134="","",IF(CARGA_DIARIA!B134=0,0,(CARGA_DIARIA!C134+CARGA_DIARIA!D134+CARGA_DIARIA!E134+CARGA_DIARIA!F134+CARGA_DIARIA!G134+CARGA_DIARIA!H134+CARGA_DIARIA!I134+CARGA_DIARIA!AG134+CARGA_DIARIA!AH134+CARGA_DIARIA!AI134+CARGA_DIARIA!AJ134)/CARGA_DIARIA!B134+CARGA_DIARIA!AF134)) -> 48986128 | D134: =IF(CARGA_DIARIA!A134="","",IF(CARGA_DIARIA!B134=0,0,(CARGA_DIARIA!J134+CARGA_DIARIA!K134+CARGA_DIARIA!L134+CARGA_DIARIA!M134+CARGA_DIARIA!N134+CARGA_DIARIA!O134+CARGA_DIARIA!P134+CARGA_DIARIA!Q134+CARGA_DIARIA!R134+CARGA_DIARIA!S134+CARGA_DIARIA!T134+CARGA_DIARIA!U134+CARGA_DIARIA!V134+CARGA_DIARIA!W134)/CARGA_DIARIA!B134)) -> 306002.74 | E134: =IF(CARGA_DIARIA!A134="","",IF(CARGA_DIARIA!B134=0,0,(CARGA_DIARIA!X134+CARGA_DIARIA!Y134+CARGA_DIARIA!Z134+CARGA_DIARIA!AA134)/CARGA_DIARIA!B134+CARGA_DIARIA!AB134+CARGA_DIARIA!AC134+CARGA_DIARIA!AD134+CARGA_DIARIA!AE134)) -> 27943197 | F134: — | G134: — | H134: =IF(CARGA_DIARIA!A134="","",C134-D134-E134) -> 20736928
A135: =IF(CARGA_DIARIA!A135="","",CARGA_DIARIA!A135) -> 46232 | B135: =IF(CARGA_DIARIA!A135="","",CARGA_DIARIA!B135) -> 1493.5 | C135: =IF(CARGA_DIARIA!A135="","",IF(CARGA_DIARIA!B135=0,0,(CARGA_DIARIA!C135+CARGA_DIARIA!D135+CARGA_DIARIA!E135+CARGA_DIARIA!F135+CARGA_DIARIA!G135+CARGA_DIARIA!H135+CARGA_DIARIA!I135+CARGA_DIARIA!AG135+CARGA_DIARIA!AH135+CARGA_DIARIA!AI135+CARGA_DIARIA!AJ135)/CARGA_DIARIA!B135+CARGA_DIARIA!AF135)) -> 49999043 | D135: =IF(CARGA_DIARIA!A135="","",IF(CARGA_DIARIA!B135=0,0,(CARGA_DIARIA!J135+CARGA_DIARIA!K135+CARGA_DIARIA!L135+CARGA_DIARIA!M135+CARGA_DIARIA!N135+CARGA_DIARIA!O135+CARGA_DIARIA!P135+CARGA_DIARIA!Q135+CARGA_DIARIA!R135+CARGA_DIARIA!S135+CARGA_DIARIA!T135+CARGA_DIARIA!U135+CARGA_DIARIA!V135+CARGA_DIARIA!W135)/CARGA_DIARIA!B135)) -> 346231.3 | E135: =IF(CARGA_DIARIA!A135="","",IF(CARGA_DIARIA!B135=0,0,(CARGA_DIARIA!X135+CARGA_DIARIA!Y135+CARGA_DIARIA!Z135+CARGA_DIARIA!AA135)/CARGA_DIARIA!B135+CARGA_DIARIA!AB135+CARGA_DIARIA!AC135+CARGA_DIARIA!AD135+CARGA_DIARIA!AE135)) -> 27900275 | F135: — | G135: — | H135: =IF(CARGA_DIARIA!A135="","",C135-D135-E135) -> 21752537
A136: =IF(CARGA_DIARIA!A136="","",CARGA_DIARIA!A136) -> 46233 | B136: =IF(CARGA_DIARIA!A136="","",CARGA_DIARIA!B136) -> 1496 | C136: =IF(CARGA_DIARIA!A136="","",IF(CARGA_DIARIA!B136=0,0,(CARGA_DIARIA!C136+CARGA_DIARIA!D136+CARGA_DIARIA!E136+CARGA_DIARIA!F136+CARGA_DIARIA!G136+CARGA_DIARIA!H136+CARGA_DIARIA!I136+CARGA_DIARIA!AG136+CARGA_DIARIA!AH136+CARGA_DIARIA!AI136+CARGA_DIARIA!AJ136)/CARGA_DIARIA!B136+CARGA_DIARIA!AF136)) -> 50098471 | D136: =IF(CARGA_DIARIA!A136="","",IF(CARGA_DIARIA!B136=0,0,(CARGA_DIARIA!J136+CARGA_DIARIA!K136+CARGA_DIARIA!L136+CARGA_DIARIA!M136+CARGA_DIARIA!N136+CARGA_DIARIA!O136+CARGA_DIARIA!P136+CARGA_DIARIA!Q136+CARGA_DIARIA!R136+CARGA_DIARIA!S136+CARGA_DIARIA!T136+CARGA_DIARIA!U136+CARGA_DIARIA!V136+CARGA_DIARIA!W136)/CARGA_DIARIA!B136)) -> 598295.94 | E136: =IF(CARGA_DIARIA!A136="","",IF(CARGA_DIARIA!B136=0,0,(CARGA_DIARIA!X136+CARGA_DIARIA!Y136+CARGA_DIARIA!Z136+CARGA_DIARIA!AA136)/CARGA_DIARIA!B136+CARGA_DIARIA!AB136+CARGA_DIARIA!AC136+CARGA_DIARIA!AD136+CARGA_DIARIA!AE136)) -> 29287088 | F136: — | G136: — | H136: =IF(CARGA_DIARIA!A136="","",C136-D136-E136) -> 20213087
... A174: =IF(CARGA_DIARIA!A174="","",CARGA_DIARIA!A174) -> 46308 | B174: =IF(CARGA_DIARIA!A174="","",CARGA_DIARIA!B174) -> 1512.5 | C174: =IF(CARGA_DIARIA!A174="","",IF(CARGA_DIARIA!B174=0,0,(CARGA_DIARIA!C174+CARGA_DIARIA!D174+CARGA_DIARIA!E174+CARGA_DIARIA!F174+CARGA_DIARIA!G174+CARGA_DIARIA!H174+CARGA_DIARIA!I174+CARGA_DIARIA!AG174+CARGA_DIARIA!AH174+CARGA_DIARIA!AI174+CARGA_DIARIA!AJ174)/CARGA_DIARIA!B174+CARGA_DIARIA!AF174)) -> 34755494 | D174: =IF(CARGA_DIARIA!A174="","",IF(CARGA_DIARIA!B174=0,0,(CARGA_DIARIA!J174+CARGA_DIARIA!K174+CARGA_DIARIA!L174+CARGA_DIARIA!M174+CARGA_DIARIA!N174+CARGA_DIARIA!O174+CARGA_DIARIA!P174+CARGA_DIARIA!Q174+CARGA_DIARIA!R174+CARGA_DIARIA!S174+CARGA_DIARIA!T174+CARGA_DIARIA!U174+CARGA_DIARIA!V174+CARGA_DIARIA!W174)/CARGA_DIARIA!B174)) -> 415135.12 | E174: =IF(CARGA_DIARIA!A174="","",IF(CARGA_DIARIA!B174=0,0,(CARGA_DIARIA!X174+CARGA_DIARIA!Y174+CARGA_DIARIA!Z174+CARGA_DIARIA!AA174)/CARGA_DIARIA!B174+CARGA_DIARIA!AB174+CARGA_DIARIA!AC174+CARGA_DIARIA!AD174+CARGA_DIARIA!AE174)) -> 28054354 | F174: — | G174: — | H174: =IF(CARGA_DIARIA!A174="","",C174-D174-E174) -> 6286005
A175: =IF(CARGA_DIARIA!B175="","",CARGA_DIARIA!B175) -> 1512.5 | B175: =IF(CARGA_DIARIA!B175="","",CARGA_DIARIA!#REF!) -> #REF! | C175: =IF(CARGA_DIARIA!B175="","",IF(CARGA_DIARIA!#REF!=0,0,(CARGA_DIARIA!C175+CARGA_DIARIA!D175+CARGA_DIARIA!E175+CARGA_DIARIA!F175+CARGA_DIARIA!G175+CARGA_DIARIA!H175+CARGA_DIARIA!I175+CARGA_DIARIA!AG175+CARGA_DIARIA!AH175+CARGA_DIARIA!AI175+CARGA_DIARIA!AJ175)/CARGA_DIARIA!#REF!+CARGA_DIARIA!AF175)) -> #REF! | D175: =IF(CARGA_DIARIA!B175="","",IF(CARGA_DIARIA!#REF!=0,0,(CARGA_DIARIA!J175+CARGA_DIARIA!K175+CARGA_DIARIA!L175+CARGA_DIARIA!M175+CARGA_DIARIA!N175+CARGA_DIARIA!O175+CARGA_DIARIA!P175+CARGA_DIARIA!Q175+CARGA_DIARIA!R175+CARGA_DIARIA!S175+CARGA_DIARIA!T175+CARGA_DIARIA!U175+CARGA_DIARIA!V175+CARGA_DIARIA!W175)/CARGA_DIARIA!#REF!)) -> #REF! | E175: =IF(CARGA_DIARIA!B175="","",IF(CARGA_DIARIA!#REF!=0,0,(CARGA_DIARIA!X175+CARGA_DIARIA!Y175+CARGA_DIARIA!Z175+CARGA_DIARIA!AA175)/CARGA_DIARIA!#REF!+CARGA_DIARIA!AB175+CARGA_DIARIA!AC175+CARGA_DIARIA!AD175+CARGA_DIARIA!AE175)) -> #REF! | F175: — | G175: — | H175: =IF(CARGA_DIARIA!B175="","",C175-D175-E175) -> #REF!
A176: =IF(CARGA_DIARIA!B176="","",CARGA_DIARIA!B176) -> 1512 | B176: =IF(CARGA_DIARIA!B176="","",CARGA_DIARIA!#REF!) -> #REF! | C176: =IF(CARGA_DIARIA!B176="","",IF(CARGA_DIARIA!#REF!=0,0,(CARGA_DIARIA!C176+CARGA_DIARIA!D176+CARGA_DIARIA!E176+CARGA_DIARIA!F176+CARGA_DIARIA!G176+CARGA_DIARIA!H176+CARGA_DIARIA!I176+CARGA_DIARIA!AG176+CARGA_DIARIA!AH176+CARGA_DIARIA!AI176+CARGA_DIARIA!AJ176)/CARGA_DIARIA!#REF!+CARGA_DIARIA!AF176)) -> #REF! | D176: =IF(CARGA_DIARIA!B176="","",IF(CARGA_DIARIA!#REF!=0,0,(CARGA_DIARIA!J176+CARGA_DIARIA!K176+CARGA_DIARIA!L176+CARGA_DIARIA!M176+CARGA_DIARIA!N176+CARGA_DIARIA!O176+CARGA_DIARIA!P176+CARGA_DIARIA!Q176+CARGA_DIARIA!R176+CARGA_DIARIA!S176+CARGA_DIARIA!T176+CARGA_DIARIA!U176+CARGA_DIARIA!V176+CARGA_DIARIA!W176)/CARGA_DIARIA!#REF!)) -> #REF! | E176: =IF(CARGA_DIARIA!B176="","",IF(CARGA_DIARIA!#REF!=0,0,(CARGA_DIARIA!X176+CARGA_DIARIA!Y176+CARGA_DIARIA!Z176+CARGA_DIARIA!AA176)/CARGA_DIARIA!#REF!+CARGA_DIARIA!AB176+CARGA_DIARIA!AC176+CARGA_DIARIA!AD176+CARGA_DIARIA!AE176)) -> #REF! | F176: — | G176: — | H176: =IF(CARGA_DIARIA!B176="","",C176-D176-E176) -> #REF!
A177: =IF(CARGA_DIARIA!B177="","",CARGA_DIARIA!B177) -> 1510.5 | B177: =IF(CARGA_DIARIA!B177="","",CARGA_DIARIA!#REF!) -> #REF! | C177: =IF(CARGA_DIARIA!B177="","",IF(CARGA_DIARIA!#REF!=0,0,(CARGA_DIARIA!C177+CARGA_DIARIA!D177+CARGA_DIARIA!E177+CARGA_DIARIA!F177+CARGA_DIARIA!G177+CARGA_DIARIA!H177+CARGA_DIARIA!I177+CARGA_DIARIA!AG177+CARGA_DIARIA!AH177+CARGA_DIARIA!AI177+CARGA_DIARIA!AJ177)/CARGA_DIARIA!#REF!+CARGA_DIARIA!AF177)) -> #REF! | D177: =IF(CARGA_DIARIA!B177="","",IF(CARGA_DIARIA!#REF!=0,0,(CARGA_DIARIA!J177+CARGA_DIARIA!K177+CARGA_DIARIA!L177+CARGA_DIARIA!M177+CARGA_DIARIA!N177+CARGA_DIARIA!O177+CARGA_DIARIA!P177+CARGA_DIARIA!Q177+CARGA_DIARIA!R177+CARGA_DIARIA!S177+CARGA_DIARIA!T177+CARGA_DIARIA!U177+CARGA_DIARIA!V177+CARGA_DIARIA!W177)/CARGA_DIARIA!#REF!)) -> #REF! | E177: =IF(CARGA_DIARIA!B177="","",IF(CARGA_DIARIA!#REF!=0,0,(CARGA_DIARIA!X177+CARGA_DIARIA!Y177+CARGA_DIARIA!Z177+CARGA_DIARIA!AA177)/CARGA_DIARIA!#REF!+CARGA_DIARIA!AB177+CARGA_DIARIA!AC177+CARGA_DIARIA!AD177+CARGA_DIARIA!AE177)) -> #REF! | F177: — | G177: — | H177: =IF(CARGA_DIARIA!B177="","",C177-D177-E177) -> #REF!
A178: =IF(CARGA_DIARIA!B178="","",CARGA_DIARIA!B178) -> 1510 | B178: =IF(CARGA_DIARIA!B178="","",CARGA_DIARIA!#REF!) -> #REF! | C178: =IF(CARGA_DIARIA!B178="","",IF(CARGA_DIARIA!#REF!=0,0,(CARGA_DIARIA!C178+CARGA_DIARIA!D178+CARGA_DIARIA!E178+CARGA_DIARIA!F178+CARGA_DIARIA!G178+CARGA_DIARIA!H178+CARGA_DIARIA!I178+CARGA_DIARIA!AG178+CARGA_DIARIA!AH178+CARGA_DIARIA!AI178+CARGA_DIARIA!AJ178)/CARGA_DIARIA!#REF!+CARGA_DIARIA!AF178)) -> #REF! | D178: =IF(CARGA_DIARIA!B178="","",IF(CARGA_DIARIA!#REF!=0,0,(CARGA_DIARIA!J178+CARGA_DIARIA!K178+CARGA_DIARIA!L178+CARGA_DIARIA!M178+CARGA_DIARIA!N178+CARGA_DIARIA!O178+CARGA_DIARIA!P178+CARGA_DIARIA!Q178+CARGA_DIARIA!R178+CARGA_DIARIA!S178+CARGA_DIARIA!T178+CARGA_DIARIA!U178+CARGA_DIARIA!V178+CARGA_DIARIA!W178)/CARGA_DIARIA!#REF!)) -> #REF! | E178: =IF(CARGA_DIARIA!B178="","",IF(CARGA_DIARIA!#REF!=0,0,(CARGA_DIARIA!X178+CARGA_DIARIA!Y178+CARGA_DIARIA!Z178+CARGA_DIARIA!AA178)/CARGA_DIARIA!#REF!+CARGA_DIARIA!AB178+CARGA_DIARIA!AC178+CARGA_DIARIA!AD178+CARGA_DIARIA!AE178)) -> #REF! | F178: — | G178: — | H178: =IF(CARGA_DIARIA!B178="","",C178-D178-E178) -> #REF!
A179: =IF(CARGA_DIARIA!A179="","",CARGA_DIARIA!A179) -> 46315 | B179: =IF(CARGA_DIARIA!A179="","",CARGA_DIARIA!B179) -> 1520 | C179: =IF(CARGA_DIARIA!A179="","",IF(CARGA_DIARIA!B179=0,0,(CARGA_DIARIA!C179+CARGA_DIARIA!D179+CARGA_DIARIA!E179+CARGA_DIARIA!F179+CARGA_DIARIA!G179+CARGA_DIARIA!H179+CARGA_DIARIA!I179+CARGA_DIARIA!AG179+CARGA_DIARIA!AH179+CARGA_DIARIA!AI179+CARGA_DIARIA!AJ179)/CARGA_DIARIA!B179+CARGA_DIARIA!AF179)) -> 33429198 | D179: =IF(CARGA_DIARIA!A179="","",IF(CARGA_DIARIA!B179=0,0,(CARGA_DIARIA!J179+CARGA_DIARIA!K179+CARGA_DIARIA!L179+CARGA_DIARIA!M179+CARGA_DIARIA!N179+CARGA_DIARIA!O179+CARGA_DIARIA!P179+CARGA_DIARIA!Q179+CARGA_DIARIA!R179+CARGA_DIARIA!S179+CARGA_DIARIA!T179+CARGA_DIARIA!U179+CARGA_DIARIA!V179+CARGA_DIARIA!W179)/CARGA_DIARIA!B179)) -> 440749.41 | E179: =IF(CARGA_DIARIA!A179="","",IF(CARGA_DIARIA!B179=0,0,(CARGA_DIARIA!X179+CARGA_DIARIA!Y179+CARGA_DIARIA!Z179+CARGA_DIARIA!AA179)/CARGA_DIARIA!B179+CARGA_DIARIA!AB179+CARGA_DIARIA!AC179+CARGA_DIARIA!AD179+CARGA_DIARIA!AE179)) -> 26717612 | F179: — | G179: — | H179: =IF(CARGA_DIARIA!A179="","",C179-D179-E179) -> 6270837.2
A180: =IF(CARGA_DIARIA!A180="","",CARGA_DIARIA!A180) -> 46316 | B180: =IF(CARGA_DIARIA!A180="","",CARGA_DIARIA!B180) -> 1520.5 | C180: =IF(CARGA_DIARIA!A180="","",IF(CARGA_DIARIA!B180=0,0,(CARGA_DIARIA!C180+CARGA_DIARIA!D180+CARGA_DIARIA!E180+CARGA_DIARIA!F180+CARGA_DIARIA!G180+CARGA_DIARIA!H180+CARGA_DIARIA!I180+CARGA_DIARIA!AG180+CARGA_DIARIA!AH180+CARGA_DIARIA!AI180+CARGA_DIARIA!AJ180)/CARGA_DIARIA!B180+CARGA_DIARIA!AF180)) -> 33585200 | D180: =IF(CARGA_DIARIA!A180="","",IF(CARGA_DIARIA!B180=0,0,(CARGA_DIARIA!J180+CARGA_DIARIA!K180+CARGA_DIARIA!L180+CARGA_DIARIA!M180+CARGA_DIARIA!N180+CARGA_DIARIA!O180+CARGA_DIARIA!P180+CARGA_DIARIA!Q180+CARGA_DIARIA!R180+CARGA_DIARIA!S180+CARGA_DIARIA!T180+CARGA_DIARIA!U180+CARGA_DIARIA!V180+CARGA_DIARIA!W180)/CARGA_DIARIA!B180)) -> 496164.97 | E180: =IF(CARGA_DIARIA!A180="","",IF(CARGA_DIARIA!B180=0,0,(CARGA_DIARIA!X180+CARGA_DIARIA!Y180+CARGA_DIARIA!Z180+CARGA_DIARIA!AA180)/CARGA_DIARIA!B180+CARGA_DIARIA!AB180+CARGA_DIARIA!AC180+CARGA_DIARIA!AD180+CARGA_DIARIA!AE180)) -> 26850592 | F180: — | G180: — | H180: =IF(CARGA_DIARIA!A180="","",C180-D180-E180) -> 6238443
A181: =IF(CARGA_DIARIA!A181="","",CARGA_DIARIA!A181) -> 46317 | B181: =IF(CARGA_DIARIA!A181="","",CARGA_DIARIA!B181) -> 1520.5 | C181: =IF(CARGA_DIARIA!A181="","",IF(CARGA_DIARIA!B181=0,0,(CARGA_DIARIA!C181+CARGA_DIARIA!D181+CARGA_DIARIA!E181+CARGA_DIARIA!F181+CARGA_DIARIA!G181+CARGA_DIARIA!H181+CARGA_DIARIA!I181+CARGA_DIARIA!AG181+CARGA_DIARIA!AH181+CARGA_DIARIA!AI181+CARGA_DIARIA!AJ181)/CARGA_DIARIA!B181+CARGA_DIARIA!AF181)) -> 34138058 | D181: =IF(CARGA_DIARIA!A181="","",IF(CARGA_DIARIA!B181=0,0,(CARGA_DIARIA!J181+CARGA_DIARIA!K181+CARGA_DIARIA!L181+CARGA_DIARIA!M181+CARGA_DIARIA!N181+CARGA_DIARIA!O181+CARGA_DIARIA!P181+CARGA_DIARIA!Q181+CARGA_DIARIA!R181+CARGA_DIARIA!S181+CARGA_DIARIA!T181+CARGA_DIARIA!U181+CARGA_DIARIA!V181+CARGA_DIARIA!W181)/CARGA_DIARIA!B181)) -> 160614.46 | E181: =IF(CARGA_DIARIA!A181="","",IF(CARGA_DIARIA!B181=0,0,(CARGA_DIARIA!X181+CARGA_DIARIA!Y181+CARGA_DIARIA!Z181+CARGA_DIARIA!AA181)/CARGA_DIARIA!B181+CARGA_DIARIA!AB181+CARGA_DIARIA!AC181+CARGA_DIARIA!AD181+CARGA_DIARIA!AE181)) -> 26500152 | F181: — | G181: — | H181: =IF(CARGA_DIARIA!A181="","",C181-D181-E181) -> 7477291.8
A182: =IF(CARGA_DIARIA!A182="","",CARGA_DIARIA!A182) -> 46318 | B182: =IF(CARGA_DIARIA!A182="","",CARGA_DIARIA!B182) -> 1524.5 | C182: =IF(CARGA_DIARIA!A182="","",IF(CARGA_DIARIA!B182=0,0,(CARGA_DIARIA!C182+CARGA_DIARIA!D182+CARGA_DIARIA!E182+CARGA_DIARIA!F182+CARGA_DIARIA!G182+CARGA_DIARIA!H182+CARGA_DIARIA!I182+CARGA_DIARIA!AG182+CARGA_DIARIA!AH182+CARGA_DIARIA!AI182+CARGA_DIARIA!AJ182)/CARGA_DIARIA!B182+CARGA_DIARIA!AF182)) -> 34143047 | D182: =IF(CARGA_DIARIA!A182="","",IF(CARGA_DIARIA!B182=0,0,(CARGA_DIARIA!J182+CARGA_DIARIA!K182+CARGA_DIARIA!L182+CARGA_DIARIA!M182+CARGA_DIARIA!N182+CARGA_DIARIA!O182+CARGA_DIARIA!P182+CARGA_DIARIA!Q182+CARGA_DIARIA!R182+CARGA_DIARIA!S182+CARGA_DIARIA!T182+CARGA_DIARIA!U182+CARGA_DIARIA!V182+CARGA_DIARIA!W182)/CARGA_DIARIA!B182)) -> 165735.12 | E182: =IF(CARGA_DIARIA!A182="","",IF(CARGA_DIARIA!B182=0,0,(CARGA_DIARIA!X182+CARGA_DIARIA!Y182+CARGA_DIARIA!Z182+CARGA_DIARIA!AA182)/CARGA_DIARIA!B182+CARGA_DIARIA!AB182+CARGA_DIARIA!AC182+CARGA_DIARIA!AD182+CARGA_DIARIA!AE182)) -> 26425933 | F182: — | G182: — | H182: =IF(CARGA_DIARIA!A182="","",C182-D182-E182) -> 7551378.5
A183: =IF(CARGA_DIARIA!A183="","",CARGA_DIARIA!A183) -> 46321 | B183: =IF(CARGA_DIARIA!A183="","",CARGA_DIARIA!B183) -> 1524.5 | C183: =IF(CARGA_DIARIA!A183="","",IF(CARGA_DIARIA!B183=0,0,(CARGA_DIARIA!C183+CARGA_DIARIA!D183+CARGA_DIARIA!E183+CARGA_DIARIA!F183+CARGA_DIARIA!G183+CARGA_DIARIA!H183+CARGA_DIARIA!I183+CARGA_DIARIA!AG183+CARGA_DIARIA!AH183+CARGA_DIARIA!AI183+CARGA_DIARIA!AJ183)/CARGA_DIARIA!B183+CARGA_DIARIA!AF183)) -> 34498565 | D183: =IF(CARGA_DIARIA!A183="","",IF(CARGA_DIARIA!B183=0,0,(CARGA_DIARIA!J183+CARGA_DIARIA!K183+CARGA_DIARIA!L183+CARGA_DIARIA!M183+CARGA_DIARIA!N183+CARGA_DIARIA!O183+CARGA_DIARIA!P183+CARGA_DIARIA!Q183+CARGA_DIARIA!R183+CARGA_DIARIA!S183+CARGA_DIARIA!T183+CARGA_DIARIA!U183+CARGA_DIARIA!V183+CARGA_DIARIA!W183)/CARGA_DIARIA!B183)) -> 317153.74 | E183: =IF(CARGA_DIARIA!A183="","",IF(CARGA_DIARIA!B183=0,0,(CARGA_DIARIA!X183+CARGA_DIARIA!Y183+CARGA_DIARIA!Z183+CARGA_DIARIA!AA183)/CARGA_DIARIA!B183+CARGA_DIARIA!AB183+CARGA_DIARIA!AC183+CARGA_DIARIA!AD183+CARGA_DIARIA!AE183)) -> 26336054 | F183: — | G183: — | H183: =IF(CARGA_DIARIA!A183="","",C183-D183-E183) -> 7845357.4
A184: =IF(CARGA_DIARIA!A184="","",CARGA_DIARIA!A184) | B184: =IF(CARGA_DIARIA!A184="","",CARGA_DIARIA!B184) | C184: =IF(CARGA_DIARIA!A184="","",IF(CARGA_DIARIA!B184=0,0,(CARGA_DIARIA!C184+CARGA_DIARIA!D184+CARGA_DIARIA!E184+CARGA_DIARIA!F184+CARGA_DIARIA!G184+CARGA_DIARIA!H184+CARGA_DIARIA!I184+CARGA_DIARIA!AG184+CARGA_DIARIA!AH184+CARGA_DIARIA!AI184+CARGA_DIARIA!AJ184)/CARGA_DIARIA!B184+CARGA_DIARIA!AF184)) | D184: =IF(CARGA_DIARIA!A184="","",IF(CARGA_DIARIA!B184=0,0,(CARGA_DIARIA!J184+CARGA_DIARIA!K184+CARGA_DIARIA!L184+CARGA_DIARIA!M184+CARGA_DIARIA!N184+CARGA_DIARIA!O184+CARGA_DIARIA!P184+CARGA_DIARIA!Q184+CARGA_DIARIA!R184+CARGA_DIARIA!S184+CARGA_DIARIA!T184+CARGA_DIARIA!U184+CARGA_DIARIA!V184+CARGA_DIARIA!W184)/CARGA_DIARIA!B184)) | E184: =IF(CARGA_DIARIA!A184="","",IF(CARGA_DIARIA!B184=0,0,(CARGA_DIARIA!X184+CARGA_DIARIA!Y184+CARGA_DIARIA!Z184+CARGA_DIARIA!AA184)/CARGA_DIARIA!B184+CARGA_DIARIA!AB184+CARGA_DIARIA!AC184+CARGA_DIARIA!AD184+CARGA_DIARIA!AE184)) | F184: — | G184: — | H184: =IF(CARGA_DIARIA!A184="","",C184-D184-E184)
A185: =IF(CARGA_DIARIA!A185="","",CARGA_DIARIA!A185) | B185: =IF(CARGA_DIARIA!A185="","",CARGA_DIARIA!B185) | C185: =IF(CARGA_DIARIA!A185="","",IF(CARGA_DIARIA!B185=0,0,(CARGA_DIARIA!C185+CARGA_DIARIA!D185+CARGA_DIARIA!E185+CARGA_DIARIA!F185+CARGA_DIARIA!G185+CARGA_DIARIA!H185+CARGA_DIARIA!I185+CARGA_DIARIA!AG185+CARGA_DIARIA!AH185+CARGA_DIARIA!AI185+CARGA_DIARIA!AJ185)/CARGA_DIARIA!B185+CARGA_DIARIA!AF185)) | D185: =IF(CARGA_DIARIA!A185="","",IF(CARGA_DIARIA!B185=0,0,(CARGA_DIARIA!J185+CARGA_DIARIA!K185+CARGA_DIARIA!L185+CARGA_DIARIA!M185+CARGA_DIARIA!N185+CARGA_DIARIA!O185+CARGA_DIARIA!P185+CARGA_DIARIA!Q185+CARGA_DIARIA!R185+CARGA_DIARIA!S185+CARGA_DIARIA!T185+CARGA_DIARIA!U185+CARGA_DIARIA!V185+CARGA_DIARIA!W185)/CARGA_DIARIA!B185)) | E185: =IF(CARGA_DIARIA!A185="","",IF(CARGA_DIARIA!B185=0,0,(CARGA_DIARIA!X185+CARGA_DIARIA!Y185+CARGA_DIARIA!Z185+CARGA_DIARIA!AA185)/CARGA_DIARIA!B185+CARGA_DIARIA!AB185+CARGA_DIARIA!AC185+CARGA_DIARIA!AD185+CARGA_DIARIA!AE185)) | F185: — | G185: — | H185: =IF(CARGA_DIARIA!A185="","",C185-D185-E185)
A186: =IF(CARGA_DIARIA!A186="","",CARGA_DIARIA!A186) | B186: =IF(CARGA_DIARIA!A186="","",CARGA_DIARIA!B186) | C186: =IF(CARGA_DIARIA!A186="","",IF(CARGA_DIARIA!B186=0,0,(CARGA_DIARIA!C186+CARGA_DIARIA!D186+CARGA_DIARIA!E186+CARGA_DIARIA!F186+CARGA_DIARIA!G186+CARGA_DIARIA!H186+CARGA_DIARIA!I186+CARGA_DIARIA!AG186+CARGA_DIARIA!AH186+CARGA_DIARIA!AI186+CARGA_DIARIA!AJ186)/CARGA_DIARIA!B186+CARGA_DIARIA!AF186)) | D186: =IF(CARGA_DIARIA!A186="","",IF(CARGA_DIARIA!B186=0,0,(CARGA_DIARIA!J186+CARGA_DIARIA!K186+CARGA_DIARIA!L186+CARGA_DIARIA!M186+CARGA_DIARIA!N186+CARGA_DIARIA!O186+CARGA_DIARIA!P186+CARGA_DIARIA!Q186+CARGA_DIARIA!R186+CARGA_DIARIA!S186+CARGA_DIARIA!T186+CARGA_DIARIA!U186+CARGA_DIARIA!V186+CARGA_DIARIA!W186)/CARGA_DIARIA!B186)) | E186: =IF(CARGA_DIARIA!A186="","",IF(CARGA_DIARIA!B186=0,0,(CARGA_DIARIA!X186+CARGA_DIARIA!Y186+CARGA_DIARIA!Z186+CARGA_DIARIA!AA186)/CARGA_DIARIA!B186+CARGA_DIARIA!AB186+CARGA_DIARIA!AC186+CARGA_DIARIA!AD186+CARGA_DIARIA!AE186)) | F186: — | G186: — | H186: =IF(CARGA_DIARIA!A186="","",C186-D186-E186)
A187: =IF(CARGA_DIARIA!A187="","",CARGA_DIARIA!A187) | B187: =IF(CARGA_DIARIA!A187="","",CARGA_DIARIA!B187) | C187: =IF(CARGA_DIARIA!A187="","",IF(CARGA_DIARIA!B187=0,0,(CARGA_DIARIA!C187+CARGA_DIARIA!D187+CARGA_DIARIA!E187+CARGA_DIARIA!F187+CARGA_DIARIA!G187+CARGA_DIARIA!H187+CARGA_DIARIA!I187+CARGA_DIARIA!AG187+CARGA_DIARIA!AH187+CARGA_DIARIA!AI187+CARGA_DIARIA!AJ187)/CARGA_DIARIA!B187+CARGA_DIARIA!AF187)) | D187: =IF(CARGA_DIARIA!A187="","",IF(CARGA_DIARIA!B187=0,0,(CARGA_DIARIA!J187+CARGA_DIARIA!K187+CARGA_DIARIA!L187+CARGA_DIARIA!M187+CARGA_DIARIA!N187+CARGA_DIARIA!O187+CARGA_DIARIA!P187+CARGA_DIARIA!Q187+CARGA_DIARIA!R187+CARGA_DIARIA!S187+CARGA_DIARIA!T187+CARGA_DIARIA!U187+CARGA_DIARIA!V187+CARGA_DIARIA!W187)/CARGA_DIARIA!B187)) | E187: =IF(CARGA_DIARIA!A187="","",IF(CARGA_DIARIA!B187=0,0,(CARGA_DIARIA!X187+CARGA_DIARIA!Y187+CARGA_DIARIA!Z187+CARGA_DIARIA!AA187)/CARGA_DIARIA!B187+CARGA_DIARIA!AB187+CARGA_DIARIA!AC187+CARGA_DIARIA!AD187+CARGA_DIARIA!AE187)) | F187: — | G187: — | H187: =IF(CARGA_DIARIA!A187="","",C187-D187-E187)
A188: =IF(CARGA_DIARIA!A188="","",CARGA_DIARIA!A188) | B188: =IF(CARGA_DIARIA!A188="","",CARGA_DIARIA!B188) | C188: =IF(CARGA_DIARIA!A188="","",IF(CARGA_DIARIA!B188=0,0,(CARGA_DIARIA!C188+CARGA_DIARIA!D188+CARGA_DIARIA!E188+CARGA_DIARIA!F188+CARGA_DIARIA!G188+CARGA_DIARIA!H188+CARGA_DIARIA!I188+CARGA_DIARIA!AG188+CARGA_DIARIA!AH188+CARGA_DIARIA!AI188+CARGA_DIARIA!AJ188)/CARGA_DIARIA!B188+CARGA_DIARIA!AF188)) | D188: =IF(CARGA_DIARIA!A188="","",IF(CARGA_DIARIA!B188=0,0,(CARGA_DIARIA!J188+CARGA_DIARIA!K188+CARGA_DIARIA!L188+CARGA_DIARIA!M188+CARGA_DIARIA!N188+CARGA_DIARIA!O188+CARGA_DIARIA!P188+CARGA_DIARIA!Q188+CARGA_DIARIA!R188+CARGA_DIARIA!S188+CARGA_DIARIA!T188+CARGA_DIARIA!U188+CARGA_DIARIA!V188+CARGA_DIARIA!W188)/CARGA_DIARIA!B188)) | E188: =IF(CARGA_DIARIA!A188="","",IF(CARGA_DIARIA!B188=0,0,(CARGA_DIARIA!X188+CARGA_DIARIA!Y188+CARGA_DIARIA!Z188+CARGA_DIARIA!AA188)/CARGA_DIARIA!B188+CARGA_DIARIA!AB188+CARGA_DIARIA!AC188+CARGA_DIARIA!AD188+CARGA_DIARIA!AE188)) | F188: — | G188: — | H188: =IF(CARGA_DIARIA!A188="","",C188-D188-E188)
A189: =IF(CARGA_DIARIA!A189="","",CARGA_DIARIA!A189) | B189: =IF(CARGA_DIARIA!A189="","",CARGA_DIARIA!B189) | C189: =IF(CARGA_DIARIA!A189="","",IF(CARGA_DIARIA!B189=0,0,(CARGA_DIARIA!C189+CARGA_DIARIA!D189+CARGA_DIARIA!E189+CARGA_DIARIA!F189+CARGA_DIARIA!G189+CARGA_DIARIA!H189+CARGA_DIARIA!I189+CARGA_DIARIA!AG189+CARGA_DIARIA!AH189+CARGA_DIARIA!AI189+CARGA_DIARIA!AJ189)/CARGA_DIARIA!B189+CARGA_DIARIA!AF189)) | D189: =IF(CARGA_DIARIA!A189="","",IF(CARGA_DIARIA!B189=0,0,(CARGA_DIARIA!J189+CARGA_DIARIA!K189+CARGA_DIARIA!L189+CARGA_DIARIA!M189+CARGA_DIARIA!N189+CARGA_DIARIA!O189+CARGA_DIARIA!P189+CARGA_DIARIA!Q189+CARGA_DIARIA!R189+CARGA_DIARIA!S189+CARGA_DIARIA!T189+CARGA_DIARIA!U189+CARGA_DIARIA!V189+CARGA_DIARIA!W189)/CARGA_DIARIA!B189)) | E189: =IF(CARGA_DIARIA!A189="","",IF(CARGA_DIARIA!B189=0,0,(CARGA_DIARIA!X189+CARGA_DIARIA!Y189+CARGA_DIARIA!Z189+CARGA_DIARIA!AA189)/CARGA_DIARIA!B189+CARGA_DIARIA!AB189+CARGA_DIARIA!AC189+CARGA_DIARIA!AD189+CARGA_DIARIA!AE189)) | F189: — | G189: — | H189: =IF(CARGA_DIARIA!A189="","",C189-D189-E189)
A190: =IF(CARGA_DIARIA!A190="","",CARGA_DIARIA!A190) | B190: =IF(CARGA_DIARIA!A190="","",CARGA_DIARIA!B190) | C190: =IF(CARGA_DIARIA!A190="","",IF(CARGA_DIARIA!B190=0,0,(CARGA_DIARIA!C190+CARGA_DIARIA!D190+CARGA_DIARIA!E190+CARGA_DIARIA!F190+CARGA_DIARIA!G190+CARGA_DIARIA!H190+CARGA_DIARIA!I190+CARGA_DIARIA!AG190+CARGA_DIARIA!AH190+CARGA_DIARIA!AI190+CARGA_DIARIA!AJ190)/CARGA_DIARIA!B190+CARGA_DIARIA!AF190)) | D190: =IF(CARGA_DIARIA!A190="","",IF(CARGA_DIARIA!B190=0,0,(CARGA_DIARIA!J190+CARGA_DIARIA!K190+CARGA_DIARIA!L190+CARGA_DIARIA!M190+CARGA_DIARIA!N190+CARGA_DIARIA!O190+CARGA_DIARIA!P190+CARGA_DIARIA!Q190+CARGA_DIARIA!R190+CARGA_DIARIA!S190+CARGA_DIARIA!T190+CARGA_DIARIA!U190+CARGA_DIARIA!V190+CARGA_DIARIA!W190)/CARGA_DIARIA!B190)) | E190: =IF(CARGA_DIARIA!A190="","",IF(CARGA_DIARIA!B190=0,0,(CARGA_DIARIA!X190+CARGA_DIARIA!Y190+CARGA_DIARIA!Z190+CARGA_DIARIA!AA190)/CARGA_DIARIA!B190+CARGA_DIARIA!AB190+CARGA_DIARIA!AC190+CARGA_DIARIA!AD190+CARGA_DIARIA!AE190)) | F190: — | G190: — | H190: =IF(CARGA_DIARIA!A190="","",C190-D190-E190)
... A502: =IF(CARGA_DIARIA!A502="","",CARGA_DIARIA!A502) | B502: =IF(CARGA_DIARIA!A502="","",CARGA_DIARIA!B502) | C502: =IF(CARGA_DIARIA!A502="","",IF(CARGA_DIARIA!B502=0,0,(CARGA_DIARIA!C502+CARGA_DIARIA!D502+CARGA_DIARIA!E502+CARGA_DIARIA!F502+CARGA_DIARIA!G502+CARGA_DIARIA!H502+CARGA_DIARIA!I502+CARGA_DIARIA!AG502+CARGA_DIARIA!AH502+CARGA_DIARIA!AI502+CARGA_DIARIA!AJ502)/CARGA_DIARIA!B502+CARGA_DIARIA!AF502)) | D502: =IF(CARGA_DIARIA!A502="","",IF(CARGA_DIARIA!B502=0,0,(CARGA_DIARIA!J502+CARGA_DIARIA!K502+CARGA_DIARIA!L502+CARGA_DIARIA!M502+CARGA_DIARIA!N502+CARGA_DIARIA!O502+CARGA_DIARIA!P502+CARGA_DIARIA!Q502+CARGA_DIARIA!R502+CARGA_DIARIA!S502+CARGA_DIARIA!T502+CARGA_DIARIA!U502+CARGA_DIARIA!V502+CARGA_DIARIA!W502)/CARGA_DIARIA!B502)) | E502: =IF(CARGA_DIARIA!A502="","",IF(CARGA_DIARIA!B502=0,0,(CARGA_DIARIA!X502+CARGA_DIARIA!Y502+CARGA_DIARIA!Z502+CARGA_DIARIA!AA502)/CARGA_DIARIA!B502+CARGA_DIARIA!AB502+CARGA_DIARIA!AC502+CARGA_DIARIA!AD502+CARGA_DIARIA!AE502)) | F502: — | G502: — | H502: =IF(CARGA_DIARIA!A502="","",C502-D502-E502)

Sheet CHEQUES
A1: CHEQUES EN CARTERA — Listado completo para flujo de fondos
A2: Pegá acá los datos exportados del sistema. Fecha de acreditación = Fecha de pago + 2 días hábiles (48hs). El dashboard lee esta hoja automáticamente.
A3: Razón Social | B3: N° Cheque | C3: Monto (ARS) | D3: Fecha de Emisión | E3: Fecha de Pago | F3: Fecha Acreditación (Pago + 48hs) | G3: Observaciones
A4: LUMELL SA | B4: 00000371 | C4: 1000400 | E4: 46362 | F4: =+E4+2 -> 46364
A5: LUMELL SA | B5: 00000368 | C5: 3060000 | E5: 46362 | F5: =+E5+2 -> 46364
A6: LUMELL SA | B6: 00000370 | C6: 3000400 | E6: 46362 | F6: =+E6+2 -> 46364
A7: LUMELL SA | B7: 00000369 | C7: 3004000 | E7: 46362 | F7: =+E7+2 -> 46364
A8: LUMELL SA | B8: 00000367 | C8: 3500000 | E8: 46362 | F8: =+E8+2 -> 46364
A9: LUMELL SA | B9: 00000364 | C9: 3051000 | E9: 46360 | F9: =+E9+2 -> 46362
A10: LUMELL SA | B10: 00000365 | C10: 2000800 | E10: 46360 | F10: =+E10+2 -> 46362
A11: LUMELL SA | B11: 00000363 | C11: 3800000 | E11: 46360 | F11: =+E11+2 -> 46362
A12: LUMELL SA | B12: 00000366 | C12: 2000040 | E12: 46360 | F12: =+E12+2 -> 46362
A13: MARISQUERIA SANTA RITA SRL | B13: 00007659 | C13: 9356025 | E13: 46358 | F13: =+E13+2 -> 46360
A14: COMERCIAL INAL 2005 SA | B14: 00007897 | C14: 36301440 | E14: 46355 | F14: =+E14+2 -> 46357
A15: COMERCIAL INAL 2005 SA | B15: 00007847 | C15: 47448800 | E15: 46354 | F15: =+E15+2 -> 46356
... A129: MARISQUERIA SANTA RITA SRL | B129: 00005676 | C129: 1771900 | E129: 46325 | F129: =+E129+2 -> 46327
A130: TOTAL | C130: =SUM(C4:C129) -> 1.0045854e+09 | F130: =+E130+2 -> 2
F131: =IF(E131="","",E131+2)
F132: =IF(E132="","",E132+2)
F133: =IF(E133="","",E133+2)
F134: =IF(E134="","",E134+2)
F135: =IF(E135="","",E135+2)
A137: 📌 Para agregar cheques: pegá las filas del sistema sobre las filas grises, respetando el formato de fechas DD/MM/AAAA. La col. F (Acreditación) se calcula sola.
A599: Cuenta corriente valor: VAL01
A600: Vencimiento al valor: 20280408

Sheet PROVEEDORES_LOCALES
A1: SALDO DE PROVEEDORES LOCALES — Ranking y composición
A2: Actualizá esta hoja cada vez que recibas el saldo de proveedores. El TC se toma de la celda B3 para convertir a USD.
A3: Fecha de actualización | B3: 46314 | C3: TC BNA (ARS/USD) | D3: 1520
A4: Proveedor | B4: CUIT / Referencia | C4: Saldo (ARS) | D4: Saldo (USD) | E4: % sobre total | F4: Observaciones
A5: ARG SEAMAN ELECTRONICS S.A. | C5: 69169.65 | D5: =+C5/$D$3 -> 45.506349 | E5: =+D5/$D$268 -> 1.2406263e-05
A6: CLEANING IN PACE S.R.L. | C6: 6849315 | D6: =+C6/$D$3 -> 4506.1283 | E6: =+D6/$D$268 -> 0.0012284926
A7: MODOC S.A | C7: 497341.47 | D7: =+C7/$D$3 -> 327.19834 | E7: =+D7/$D$268 -> 8.9203126e-05
A8: NALDO LOMBARDI S A | C8: 1519999 | D8: =+C8/$D$3 -> 999.99934 | E8: =+D8/$D$268 -> 0.0002726269
A9: A.I.M.A. ELECROMECANICA SOCIEDAD DE HECHO | C9: 1021542.5 | D9: =+C9/$D$3 -> 672.06743 | E9: =+D9/$D$268 -> 0.00018322378
A10: ABETE Y CIA. S.A. | C10: 9067449.7 | D10: =+C10/$D$3 -> 5965.4274 | E10: =+D10/$D$268 -> 0.001626337
A11: ABREU JOSE LUIS | C11: 17959738 | D11: =+C11/$D$3 -> 11815.617 | E11: =+D11/$D$268 -> 0.0032212571
A12: ADOLFO FORTIER S A C I F I A | C12: 1019788 | D12: =+C12/$D$3 -> 670.91316 | E12: =+D12/$D$268 -> 0.00018290909
A13: ADOLFO KUHN SRL | C13: 199650 | D13: =+C13/$D$3 -> 131.34868 | E13: =+D13/$D$268 -> 3.5809208e-05
A14: ALLENDE Y BREA SOCIEDAD CIVIL | C14: 13078095 | D14: =+C14/$D$3 -> 8604.0099 | E14: =+D14/$D$268 -> 0.0023456861
A15: ALMACEN NAVAL ELENA SRL | C15: 66542.74 | D15: =+C15/$D$3 -> 43.778118 | E15: =+D15/$D$268 -> 1.19351e-05
A16: ALPAHELI S.R.L. | C16: 5051000 | D16: =+C16/$D$3 -> 3323.0263 | E16: =+D16/$D$268 -> 0.00090594695
... A267: ZAN REPARACIONES NAVALES S.R.L | C267: 1580000 | D267: =+C267/$D$3 -> 1039.4737 | E267: =+D267/$D$268 -> 0.00028338867
A268: TOTAL PROVEEDORES | C268: =SUM(C5:C267) -> 5.5753816e+09 | D268: =SUM(D5:D267) -> 3668014.2 | E268: =SUM(E5:E267) -> 1 | K268: 05924 | L268: COOP. DE TRABAJO PUCARA LIMITADA | M268: PV | N268: GRUAS-AUTOELEVADORES | O268: 17200000 | P268: PR026 | Q268: 81112000 | R268: 30000000 | S268: 0 | T268: 59850000 | U268: 188162000
K269: 00350 | L269: COOPERATIVA DE TRABAJO DE ESTIBAJE HIPOCOOP LTDA | M269: PV | N269: SERVICIOS DE ESTIBAJES | O269: 0 | P269: PR019 | Q269: 72096294 | R269: 0 | S269: 0 | T269: 0 | U269: 72096294
A270: 📌 Para agregar proveedores: insertá filas antes de la fila TOTAL. El % se recalcula solo. Actualizá la fecha y el TC en la fila 3 cada vez que cargues datos nuevos. | K270: 03951 | L270: COOPERATIVA DE TRABAJO DE ESTIBAJE HIPOCOOP LTDA | M270: PV | N270: SERVICIOS DE ESTIBAJES | O270: 0 | P270: PR019 | Q270: 73352281 | R270: 0 | S270: 0 | T270: 0 | U270: 73352281
K271: 04859 | L271: COSTANERA UNO SA | M271: PV | N271: REPUESTOS PARA BARCOS | O271: 560405.35 | P271: PR046 | Q271: 0 | R271: 0 | S271: 0 | T271: 0 | U271: 560405.35
K272: 05786 | L272: CRAITO ARGENTINA SA | M272: PV | N272: SULFITO SOLTAX PARA LANGOSTINO | O272: 0 | P272: PR159 | Q272: 2504920.5 | R272: 7246169.2 | S272: 0 | T272: 0 | U272: 9751089.7
K273: 01118 | L273: CROCE HNOS. AGENTES MARITIMOS S.R.L. | M273: PV | N273: DESPACHANTES y AGENTES MARITIMOS | O273: 10003970 | P273: PR015 | Q273: 5622496.4 | R273: 0 | S273: 0 | T273: 0 | U273: 15626466
K274: 07330 | L274: CURCI CLAUDIO OMAR | M274: PV | N274: ACRILICOS BUQUES/PLANTA | O274: 119200 | P274: PR065 | Q274: 0 | R274: 0 | S274: 0 | T274: 0 | U274: 119200
K275: 08135 | L275: CURITIBA SRL | M275: PV | N275: SIN ACTIVIDAD CODIFICADA | O275: 0 | P275: PR999 | Q275: 0 | R275: 0 | S275: 0 | T275: -204.43 | U275: -204.43
K276: 08608 | L276: D ALBIS DARIO OSVALDO | M276: PV | N276: AUTOELEVADORES-MATERIALES Y REPARACIONES | O276: 0 | P276: PR079 | Q276: 0 | R276: 204974 | S276: 0 | T276: 0 | U276: 204974
K277: 06351 | L277: DADANTE FEDERICO | M277: PV | N277: SERVICIO MECANICO | O277: 1290000 | P277: PR050 | Q277: 0 | R277: 0 | S277: 0 | T277: 0 | U277: 1290000
K278: 07289 | L278: DANODIS S.A. | M278: PV | N278: PROVEEDURIA - INSUMOS PARA BUQUES | O278: 5986114 | P278: PR041 | Q278: 0 | R278: 0 | S278: 0 | T278: 0 | U278: 5986114
K279: 07745 | L279: DATCOM SOLUCIONES TECNOLOGICAS S.A. | M279: PV | N279: SISTEMAS INFORMATICOS | O279: 4450622 | P279: PR067 | Q279: 0 | R279: 0 | S279: 0 | T279: 0 | U279: 4450622
K280: 09027 | L280: DAUVERNE LUIS MARIA JULIAN | M280: PV | N280: IMPRENTA (ETIQUETAS/TALONARIOS) | O280: 0 | P280: PR062 | Q280: 561415.81 | R280: 493716.31 | S280: 0 | T280: 0 | U280: 1055132.1
K281: 08433 | L281: DELTA BLUE LANCHAS SRL | M281: PV | N281: SERVICIOS MARITIMOS | O281: 2934008 | P281: PR148 | Q281: 2924328 | R281: 0 | S281: 0 | T281: 0 | U281: 5858336
K282: 04109 | L282: DEVOMP SRL | M282: PV | N282: MAT. CONST, ELECTRICOS Y PLOMERIA | O282: 4818624.3 | P282: PR016 | Q282: 11669472 | R282: 0 | S282: 0 | T282: 0 | U282: 16488097
... K499: 02429 | L499: YPF S.A. | M499: PV | N499: COMBUSTIBLES - LUBRICANTES | O499: 6.6269277e+08 | P499: PR013 | Q499: 0 | R499: 0 | S499: 0 | T499: 0 | U499: 6.6269277e+08
K501: Parámetros
K502: Código de proveedor desde: hasta:
K503: Deuda al día valor: 20261019
K504: No incluye valor: PR006

Sheet Hoja1
A1: Código de proveedor | B1: Razón Social | C1: Módulo de formulario | D1: Descripción | E1: Mes en curso | F1: Actividad comercial | G1: Mes anterior | H1: Mes anterior 2 | I1: Mes Ant 3 | J1: Mes 4 y anteriores | K1: TOTAL
A2: 09021 | B2: CLEANING IN PACE S.R.L. | C2: PV | D2: LIMPIEZA PLANTA Y OFICINAS | E2: 1828854.5 | F2: PR077 | G2: 4600000 | H2: 0.01 | I2: 0 | J2: 0 | K2: 6428854.5
A3: 09007 | B3: LA INDUSTRIAL ELECTRICA S A | C3: PV | D3: ARTS.DE FERRETERIA BUQUES/PLANTA | E3: 0 | F3: PR020 | G3: 0 | H3: 0 | I3: 0 | J3: 1.08 | K3: 1.08
A4: 08250 | B4: NALDO LOMBARDI S A | C4: PV | D4: SIN ACTIVIDAD CODIFICADA | E4: 0 | F4: PR999 | G4: 218997 | H4: 0 | I4: 0 | J4: 0 | K4: 218997
A5: 05594 | B5: SALEM ALDO ALBERTO Y AICARDI DERNANDO SEBASTIAN S H | C5: PV | D5: ARTS.DE FERRETERIA BUQUES/PLANTA | E5: 0 | F5: PR020 | G5: 8383134.1 | H5: 0 | I5: 0 | J5: 0 | K5: 8383134.1
A6: 07467 | B6: A LONEIRA S.A. | C6: PV | D6: FABRICACION DE ARTICULOS DE LONA | E6: 0 | F6: PR145 | G6: 560000 | H6: 0 | I6: 0 | J6: 125000 | K6: 685000
A7: 00128 | B7: ABETE Y CIA. S.A. | C7: PV | D7: ARTS.DE FERRETERIA BUQUES/PLANTA | E7: 2459435.3 | F7: PR020 | G7: 1048053.7 | H7: 0 | I7: 0 | J7: 0 | K7: 3507489
A8: 07598 | B8: ABREU JOSE LUIS | C8: PV | D8: METALURGICA BUQUES/PLANTA | E8: 508267.1 | F8: PR111 | G8: 0 | H8: 0 | I8: 0 | J8: 0 | K8: 508267.1
A9: 06732 | B9: ACUPRI S. R. L | C9: PV | D9: TRANSPORTES Y FLETES | E9: 1355200 | F9: PR054 | G9: 0 | H9: 0 | I9: 0 | J9: 0 | K9: 1355200
A10: 08892 | B10: ADECCO ARGENTINA SA | C10: PV | D10: SIN ACTIVIDAD CODIFICADA | E10: 179.54 | F10: PR999 | G10: 0 | H10: 0 | I10: 0 | J10: 0 | K10: 179.54
A11: 03315 | B11: ADMINISTRACION PORTUARIA DE PUERTO MADRYN | C11: PV | D11: SERVICIOS DE TERCEROS | E11: 3310060 | F11: PR055 | G11: 0 | H11: 0 | I11: 0 | J11: 0 | K11: 3310060
A12: 00504 | B12: ADOLFO FORTIER S A C I F I A | C12: PV | D12: REPUESTOS PARA RODADOS | E12: 946441.43 | F12: PR045 | G12: 0 | H12: 0 | I12: 0 | J12: 0 | K12: 946441.43
A13: 05568 | B13: ADOLFO KUHN SRL | C13: PV | D13: SERVICIO MECANICO | E13: 49247 | F13: PR050 | G13: 0 | H13: 0 | I13: 0 | J13: 0 | K13: 49247
... A279: 09611 | B279: ZAHN ALEXIS | C279: PV | D279: ALQUILERES | E279: 1350000 | F279: 8 | G279: 0 | H279: 0 | I279: 0 | J279: 0 | K279: 1350000

Sheet PRESTAMOS_USD
A1: PRÉSTAMOS EN DÓLARES — Detalle y proyección de intereses (sistema bullet)
A2: Interés aprox. = Capital × (TNA / 365) × Días del plazo · Todos los importes en USD · TNA = Tasa Nominal Anual
A3: Fecha de referencia | B3: 46314
A4: Banco | B4: Monto (USD) | C4: TNA (%) | D4: Fecha inicio | E4: Fecha vencimiento | F4: Días plazo | G4: Interés aprox. (USD) | H4: Total a pagar (USD) | I4: Días restantes | J4: Observaciones
A5: Banco Patagonia | B5: 1000000 | C5: 0.039 | D5: 46281 | E5: 46451 | F5: =IFERROR(E5-D5,0) -> 170 | G5: =IFERROR(B5*(C5/365)*F5,0) -> 18164.384 | H5: =IFERROR(B5+G5,0) -> 1018164.4 | I5: =IFERROR(E5-TODAY(),"Vencido") -> 130
A6: Banco Patagonia | B6: 1000000 | C6: 0.039 | D6: 46300 | E6: 46469 | F6: =IFERROR(E6-D6,0) -> 169 | G6: =IFERROR(B6*(C6/365)*F6,0) -> 18057.534 | H6: =IFERROR(B6+G6,0) -> 1018057.5 | I6: =IFERROR(E6-TODAY(),"Vencido") -> 148
A7: Banco Patagonia | B7: 1000000 | C7: 0.039 | D7: 46260 | E7: 46434 | F7: =IFERROR(E7-D7,0) -> 174 | G7: =IFERROR(B7*(C7/365)*F7,0) -> 18591.781 | H7: =IFERROR(B7+G7,0) -> 1018591.8 | I7: =IFERROR(E7-TODAY(),"Vencido") -> 113
A8: Banco Patagonia | B8: 1000000 | C8: 0.038 | D8: 46153 | E8: 46323 | F8: =IFERROR(E8-D8,0) -> 170 | G8: =IFERROR(B8*(C8/365)*F8,0) -> 17698.63 | H8: =IFERROR(B8+G8,0) -> 1017698.6 | I8: =IFERROR(E8-TODAY(),"Vencido") -> 2
A9: Banco Patagonia | B9: 1000000 | C9: 0.031 | D9: 46191 | E9: 46366 | F9: =IFERROR(E9-D9,0) -> 175 | G9: =IFERROR(B9*(C9/365)*F9,0) -> 14863.014 | H9: =IFERROR(B9+G9,0) -> 1014863 | I9: =IFERROR(E9-TODAY(),"Vencido") -> 45
A10: Banco Frances | B10: 1000000 | C10: 0.0349 | D10: 46227 | E10: 46407 | F10: =IFERROR(E10-D10,0) -> 180 | G10: =IFERROR(B10*(C10/365)*F10,0) -> 17210.959 | H10: =IFERROR(B10+G10,0) -> 1017211 | I10: =IFERROR(E10-TODAY(),"Vencido") -> 86
A11: Banco Frances | B11: 1000000 | C11: 0.0323 | D11: 46178 | E11: 46358 | F11: =IFERROR(E11-D11,0) -> 180 | G11: =IFERROR(B11*(C11/365)*F11,0) -> 15928.767 | H11: =IFERROR(B11+G11,0) -> 1015928.8 | I11: =IFERROR(E11-TODAY(),"Vencido") -> 37
A12: Banco Frances | B12: 1000000 | C12: 0.0323 | D12: 46183 | E12: 46360 | F12: =IFERROR(E12-D12,0) -> 177 | G12: =IFERROR(B12*(C12/365)*F12,0) -> 15663.288 | H12: =IFERROR(B12+G12,0) -> 1015663.3 | I12: =IFERROR(E12-TODAY(),"Vencido") -> 39
A13: Banco Frances | B13: 1000000 | C13: 0.04 | D13: 46255 | E13: 46434 | F13: =IFERROR(E13-D13,0) -> 179 | G13: =IFERROR(B13*(C13/365)*F13,0) -> 19616.438 | H13: =IFERROR(B13+G13,0) -> 1019616.4 | I13: =IFERROR(E13-TODAY(),"Vencido") -> 113
A14: Banco Frances | B14: 1000000 | C14: 0.039 | D14: 46269 | E14: 46449 | F14: =IFERROR(E14-D14,0) -> 180 | G14: =IFERROR(B14*(C14/365)*F14,0) -> 19232.877 | H14: =IFERROR(B14+G14,0) -> 1019232.9 | I14: =IFERROR(E14-TODAY(),"Vencido") -> 128
A15: Banco Frances | B15: 1000000 | C15: 0.0339 | D15: 46202 | E15: 46379 | F15: =IFERROR(E15-D15,0) -> 177 | G15: =IFERROR(B15*(C15/365)*F15,0) -> 16439.178 | H15: =IFERROR(B15+G15,0) -> 1016439.2 | I15: =IFERROR(E15-TODAY(),"Vencido") -> 58
A16: Banco Frances | B16: 1000000 | C16: 0.0365 | D16: 46255 | E16: 46435 | F16: =IFERROR(E16-D16,0) -> 180 | G16: =IFERROR(B16*(C16/365)*F16,0) -> 18000 | H16: =IFERROR(B16+G16,0) -> 1018000 | I16: =IFERROR(E16-TODAY(),"Vencido") -> 114
... A19: Banco Galicia | B19: 1000000 | C19: 0.035 | D19: 46244 | E19: 46331 | F19: =IFERROR(E19-D19,0) -> 87 | G19: =IFERROR(B19*(C19/365)*F19,0) -> 8342.4658 | H19: =IFERROR(B19+G19,0) -> 1008342.5 | I19: =IFERROR(E19-TODAY(),"Vencido") -> 10
A20: Banco Santander | B20: 913342 | C20: 0.035 | D20: 46269 | E20: 46603 | F20: =IFERROR(E20-D20,0) -> 334 | G20: =IFERROR(B20*(C20/365)*F20,0) -> 29251.967 | H20: =IFERROR(B20+G20,0) -> 942593.97 | I20: =IFERROR(E20-TODAY(),"Vencido") -> 282 | J20: Se paga en 12 cuotas
A21: Banco Santander | B21: 733333 | C21: 0.035 | D21: 46286 | E21: 46620 | F21: =IFERROR(E21-D21,0) -> 334 | G21: =IFERROR(B21*(C21/365)*F21,0) -> 23486.747 | H21: =IFERROR(B21+G21,0) -> 756819.75 | I21: =IFERROR(E21-TODAY(),"Vencido") -> 299 | J21: Se paga en 12 cuotas
A22: TOTAL | B22: =SUM(B5:B21) -> 17646675 | G22: =SUM(G5:G21) -> 325287.76 | H22: =SUM(H5:H21) -> 17971963
F23: =IFERROR(E23-D23,0) -> 0 | G23: =IFERROR(B23*(C23/365)*F23,0) -> 0 | H23: =IFERROR(B23+G23,0) -> 0 | I23: =IFERROR(E23-TODAY(),"") -> -46321
F24: =IFERROR(E24-D24,0) -> 0 | G24: =IFERROR(B24*(C24/365)*F24,0) -> 0 | H24: =IFERROR(B24+G24,0) -> 0 | I24: =IFERROR(E24-TODAY(),"") -> -46321
F25: =IFERROR(E25-D25,0) -> 0 | G25: =IFERROR(B25*(C25/365)*F25,0) -> 0 | H25: =IFERROR(B25+G25,0) -> 0 | I25: =IFERROR(E25-TODAY(),"") -> -46321
F26: =IFERROR(E26-D26,0) -> 0 | G26: =IFERROR(B26*(C26/365)*F26,0) -> 0 | H26: =IFERROR(B26+G26,0) -> 0 | I26: =IFERROR(E26-TODAY(),"") -> -46321
F27: =IFERROR(E27-D27,0) -> 0 | G27: =IFERROR(B27*(C27/365)*F27,0) -> 0 | H27: =IFERROR(B27+G27,0) -> 0 | I27: =IFERROR(E27-TODAY(),"") -> -46321
A29: 📌 Celdas en AMARILLO = datos a ingresar manualmente. Celdas en VERDE = calculadas automáticamente. Celdas en ROJO = total a pagar al vencimiento.
